DeMux4way/DeMux4way.v
module DeMux4way(
    input din,            // Data input
    input [1:0] select,  // Select lines
    output reg a,        // Output 0
    output reg b,        // Output 1
    output reg c,        // Output 2
    output reg d         // Output 3
);

    always @(*) begin
        // Initialize outputs to 0
        a = 0;
        b = 0;
        c = 0;
        d = 0;

        // Select the output based on the select lines
        case (select)
            2'b00: a = din;  // Route input to output a
            2'b01: b = din;  // Route input to output b
            2'b10: c = din;  // Route input to output c
            2'b11: d = din;  // Route input to output d
            default: begin
                a = 0;
                b = 0;
                c = 0;
                d = 0;
            end
        endcase
    end

endmodule

Project-01/DeMux4way/DeMux4way_tb.v
module DeMux4way_tb;
    reg din;              // Data input
    reg [1:0] select;    // Select lines
    wire a, b, c, d;     // Outputs

    // Instantiate the demux
    DeMux4way uut (
        .din(din),
        .select(select),
        .a(a),
        .b(b),
        .c(c),
        .d(d)
    );

    integer output_file;

    initial begin
        $dumpfile("DeMux4way.vcd");
        $dumpvars(0, DeMux4way_tb);
        // Open the output file
        
        output_file = $fopen("DeMux4way.out", "w");
        
        // Write the header
        $fwrite(output_file, "| din | sel  |  a  |  b  |  c  |  d  |\n");

        // Test cases for din = 0
        din = 0;

        // Test select = 00
        select = 2'b00;
        #10; // Wait for 10 time units
        $fwrite(output_file, "|  %b  |  %b  |  %b  |  %b  |  %b  |  %b  |\n", din, select, a, b, c, d);

        // Test select = 01
        select = 2'b01;
        #10; // Wait for 10 time units
        $fwrite(output_file, "|  %b  |  %b  |  %b  |  %b  |  %b  |  %b  |\n", din, select, a, b, c, d);

        // Test select = 10
        select = 2'b10;
        #10; // Wait for 10 time units
        $fwrite(output_file, "|  %b  |  %b  |  %b  |  %b  |  %b  |  %b  |\n", din, select, a, b, c, d);

        // Test select = 11
        select = 2'b11;
        #10; // Wait for 10 time units
        $fwrite(output_file, "|  %b  |  %b  |  %b  |  %b  |  %b  |  %b  |\n", din, select, a, b, c, d);

        // Test cases for din = 1
        din = 1;

        // Test select = 00
        select = 2'b00;
        #10; // Wait for 10 time units
        $fwrite(output_file, "|  %b  |  %b  |  %b  |  %b  |  %b  |  %b  |\n", din, select, a, b, c, d);

        // Test select = 01
        select = 2'b01;
        #10; // Wait for 10 time units
        $fwrite(output_file, "|  %b  |  %b  |  %b  |  %b  |  %b  |  %b  |\n", din, select, a, b, c, d);

        // Test select = 10
        select = 2'b10;
        #10; // Wait for 10 time units
        $fwrite(output_file, "|  %b  |  %b  |  %b  |  %b  |  %b  |  %b  |\n", din, select, a, b, c, d);

        // Test select = 11
        select = 2'b11;
        #10; // Wait for 10 time units
        $fwrite(output_file, "|  %b  |  %b  |  %b  |  %b  |  %b  |  %b  |\n", din, select, a, b, c, d);

        // Close the output file
        $fclose(output_file);
        
        // End simulation
        $finish;
    end

    initial begin
        // Monitor the output
        $monitor("din=%b, select=%b, a=%b, b=%b, c=%b, d=%b", din, select, a, b, c, d);
    end
endmodule

Project-01/DeMux4way/DeMux4way.vcd
$date
	Tue Aug 06 20:21:46 2024
$end
$version
	Icarus Verilog
$end
$timescale
	1s
$end
$scope module DeMux4way_tb $end
$var wire 1 ! d $end
$var wire 1 " c $end
$var wire 1 # b $end
$var wire 1 $ a $end
$var reg 1 % din $end
$var reg 2 & select [1:0] $end
$var integer 32 ' output_file [31:0] $end
$scope module uut $end
$var wire 1 % din $end
$var wire 2 ( select [1:0] $end
$var reg 1 $ a $end
$var reg 1 # b $end
$var reg 1 " c $end
$var reg 1 ! d $end
$upscope $end
$upscope $end
$enddefinitions $end
$comment Show the parameter values. $end
$dumpall
$end
#0
$dumpvars
b0 (
b10000000000000000000000000000011 '
b0 &
0%
0$
0#
0"
0!
$end
#10
b1 &
b1 (
#20
b10 &
b10 (
#30
b11 &
b11 (
#40
1$
b0 &
b0 (
1%
#50
1#
0$
b1 &
b1 (
#60
1"
0#
b10 &
b10 (
#70
1!
0"
b11 &
b11 (
