Project-03/Ram512/RAM512.v
module RAM512 (
    input wire [8:0] address,   // 9-bit address to select one of 512 registers
    input wire [15:0] in,       // 16-bit input data to be written
    input wire load,            // Load signal
    output reg [15:0] out       // 16-bit output data
);

    // Declare an array of 512 registers, each 16 bits wide
    reg [15:0] memory [0:511];

    // Always block to handle read and write operations
    always @(posedge load or negedge load) begin
        if (load) begin
            // Write data to the specified address
            memory[address] <= in;
        end
    end

    // Always block to handle reading from memory
    always @(*) begin
        // Output the value stored at the specified address
        out = memory[address];
    end

endmodule

Project-03/Ram512/RAM512_tb.v
`timescale 1ns / 1ps

module tb_RAM512;

    // Parameters
    parameter ADDRESS_WIDTH = 9; // 9 bits for 512 addresses
    parameter DATA_WIDTH = 16;    // 16 bits for data

    // Inputs
    reg [ADDRESS_WIDTH-1:0] address; // Address input
    reg [DATA_WIDTH-1:0] in;         // Data input
    reg load;                        // Load signal

    // Outputs
    wire [DATA_WIDTH-1:0] out;       // Output data

    // Instantiate the RAM512 module
    RAM512 uut (
        .address(address),
        .in(in),
        .load(load),
        .out(out)
    );

    // File handling
    integer output_file;
    integer i;

    // Initial block
    initial begin
        // Dump waveform data to VCD file
        $dumpfile("RAM512.vcd");
        $dumpvars(0, tb_RAM512);

        // Open the output file
        output_file = $fopen("RAM512.out", "w");
        if (output_file == 0) begin
            $display("Error: Could not open output_file.txt");
            $finish;
        end

        // Dump waveform data to VCD file (optional)
        $dumpfile("RAM512.vcd");
        $dumpvars(0, tb_RAM512);

        // Test sequence
        // Write to all addresses
        for (i = 0; i < 512; i = i + 1) begin
            address = i;                       // Set the address
            in = 16'h5A5A + i;                // Set the data to write
            load = 1;                         // Set load to 1 to enable writing
            #10;                               // Wait for 10 time units to allow writing
            $fwrite(output_file, "Address: %b, Written Data: %h\n", address, in);

            load = 0;                         // Set load to 0 to disable writing
            #10;                               // Wait for 10 time units before the next operation
            $fwrite(output_file, "Address: %b, Written Data: %h\n", address, in);
        end

        // Add a delay to allow for all writes to settle
        #20;

        // Read from all addresses
        for (i = 0; i < 512; i = i + 1) begin
            address = i;                      // Set the address to read
            #10;                              // Wait for 10 time units to allow reading
            $fwrite(output_file, "Address: %b, Read Data: %h\n", address, out);
        end

        // Close the output file
        $fclose(output_file);

        // Finish simulation
        $finish;
    end

endmodule

Project-03/Ram512/RAM512.vcd
$date
	Tue Aug 20 20:07:26 2024
$end
$version
	Icarus Verilog
$end
$timescale
	1ps
$end
$scope module tb_RAM512 $end
$var wire 16 ! out [15:0] $end
$var parameter 32 " ADDRESS_WIDTH $end
$var parameter 32 # DATA_WIDTH $end
$var reg 9 $ address [8:0] $end
$var reg 16 % in [15:0] $end
$var reg 1 & load $end
$var integer 32 ' i [31:0] $end
$var integer 32 ( output_file [31:0] $end
$scope module uut $end
$var wire 9 ) address [8:0] $end
$var wire 16 * in [15:0] $end
$var wire 1 & load $end
$var reg 16 + out [15:0] $end
$upscope $end
$upscope $end
$scope module tb_RAM512 $end
$scope module uut $end
$upscope $end
$upscope $end
$enddefinitions $end
$comment Show the parameter values. $end
$dumpall
b10000 #
b1001 "
$end
#0
$dumpvars
b101101001011010 +
b101101001011010 *
b0 )
b10000000000000000000000000000011 (
b0 '
1&
b101101001011010 %
b0 $
b101101001011010 !
$end
#10000
0&
#20000
b101101001011011 !
b101101001011011 +
1&
b101101001011011 %
b101101001011011 *
b1 $
b1 )
b1 '
#30000
0&
#40000
b101101001011100 !
b101101001011100 +
1&
b101101001011100 %
b101101001011100 *
b10 $
b10 )
b10 '
#50000
0&
#60000
b101101001011101 !
b101101001011101 +
1&
b101101001011101 %
b101101001011101 *
b11 $
b11 )
b11 '
#70000
0&
#80000
b101101001011110 !
b101101001011110 +
1&
b101101001011110 %
b101101001011110 *
b100 $
b100 )
b100 '
#90000
0&
#100000
b101101001011111 !
b101101001011111 +
1&
b101101001011111 %
b101101001011111 *
b101 $
b101 )
b101 '
#110000
0&
#120000
b101101001100000 !
b101101001100000 +
1&
b101101001100000 %
b101101001100000 *
b110 $
b110 )
b110 '
#130000
0&
#140000
b101101001100001 !
b101101001100001 +
1&
b101101001100001 %
b101101001100001 *
b111 $
b111 )
b111 '
#150000
0&
#160000
b101101001100010 !
b101101001100010 +
1&
b101101001100010 %
b101101001100010 *
b1000 $
b1000 )
b1000 '
#170000
0&
#180000
b101101001100011 !
b101101001100011 +
1&
b101101001100011 %
b101101001100011 *
b1001 $
b1001 )
b1001 '
#190000
0&
#200000
b101101001100100 !
b101101001100100 +
1&
b101101001100100 %
b101101001100100 *
b1010 $
b1010 )
b1010 '
#210000
0&
#220000
b101101001100101 !
b101101001100101 +
1&
b101101001100101 %
b101101001100101 *
b1011 $
b1011 )
b1011 '
#230000
0&
#240000
b101101001100110 !
b101101001100110 +
1&
b101101001100110 %
b101101001100110 *
b1100 $
b1100 )
b1100 '
#250000
0&
#260000
b101101001100111 !
b101101001100111 +
1&
b101101001100111 %
b101101001100111 *
b1101 $
b1101 )
b1101 '
#270000
0&
#280000
b101101001101000 !
b101101001101000 +
1&
b101101001101000 %
b101101001101000 *
b1110 $
b1110 )
b1110 '
#290000
0&
#300000
b101101001101001 !
b101101001101001 +
1&
b101101001101001 %
b101101001101001 *
b1111 $
b1111 )
b1111 '
#310000
0&
#320000
b101101001101010 !
b101101001101010 +
1&
b101101001101010 %
b101101001101010 *
b10000 $
b10000 )
b10000 '
#330000
0&
#340000
b101101001101011 !
b101101001101011 +
1&
b101101001101011 %
b101101001101011 *
b10001 $
b10001 )
b10001 '
#350000
0&
#360000
b101101001101100 !
b101101001101100 +
1&
b101101001101100 %
b101101001101100 *
b10010 $
b10010 )
b10010 '
#370000
0&
#380000
b101101001101101 !
b101101001101101 +
1&
b101101001101101 %
b101101001101101 *
b10011 $
b10011 )
b10011 '
#390000
0&
#400000
b101101001101110 !
b101101001101110 +
1&
b101101001101110 %
b101101001101110 *
b10100 $
b10100 )
b10100 '
#410000
0&
#420000
b101101001101111 !
b101101001101111 +
1&
b101101001101111 %
b101101001101111 *
b10101 $
b10101 )
b10101 '
#430000
0&
#440000
b101101001110000 !
b101101001110000 +
1&
b101101001110000 %
b101101001110000 *
b10110 $
b10110 )
b10110 '
#450000
0&
#460000
b101101001110001 !
b101101001110001 +
1&
b101101001110001 %
b101101001110001 *
b10111 $
b10111 )
b10111 '
#470000
0&
#480000
b101101001110010 !
b101101001110010 +
1&
b101101001110010 %
b101101001110010 *
b11000 $
b11000 )
b11000 '
#490000
0&
#500000
b101101001110011 !
b101101001110011 +
1&
b101101001110011 %
b101101001110011 *
b11001 $
b11001 )
b11001 '
#510000
0&
#520000
b101101001110100 !
b101101001110100 +
1&
b101101001110100 %
b101101001110100 *
b11010 $
b11010 )
b11010 '
#530000
0&
#540000
b101101001110101 !
b101101001110101 +
1&
b101101001110101 %
b101101001110101 *
b11011 $
b11011 )
b11011 '
#550000
0&
#560000
b101101001110110 !
b101101001110110 +
1&
b101101001110110 %
b101101001110110 *
b11100 $
b11100 )
b11100 '
#570000
0&
#580000
b101101001110111 !
b101101001110111 +
1&
b101101001110111 %
b101101001110111 *
b11101 $
b11101 )
b11101 '
#590000
0&
#600000
b101101001111000 !
b101101001111000 +
1&
b101101001111000 %
b101101001111000 *
b11110 $
b11110 )
b11110 '
#610000
0&
#620000
b101101001111001 !
b101101001111001 +
1&
b101101001111001 %
b101101001111001 *
b11111 $
b11111 )
b11111 '
#630000
0&
#640000
b101101001111010 !
b101101001111010 +
1&
b101101001111010 %
b101101001111010 *
b100000 $
b100000 )
b100000 '
#650000
0&
#660000
b101101001111011 !
b101101001111011 +
1&
b101101001111011 %
b101101001111011 *
b100001 $
b100001 )
b100001 '
#670000
0&
#680000
b101101001111100 !
b101101001111100 +
1&
b101101001111100 %
b101101001111100 *
b100010 $
b100010 )
b100010 '
#690000
0&
#700000
b101101001111101 !
b101101001111101 +
1&
b101101001111101 %
b101101001111101 *
b100011 $
b100011 )
b100011 '
#710000
0&
#720000
b101101001111110 !
b101101001111110 +
1&
b101101001111110 %
b101101001111110 *
b100100 $
b100100 )
b100100 '
#730000
0&
#740000
b101101001111111 !
b101101001111111 +
1&
b101101001111111 %
b101101001111111 *
b100101 $
b100101 )
b100101 '
#750000
0&
#760000
b101101010000000 !
b101101010000000 +
1&
b101101010000000 %
b101101010000000 *
b100110 $
b100110 )
b100110 '
#770000
0&
#780000
b101101010000001 !
b101101010000001 +
1&
b101101010000001 %
b101101010000001 *
b100111 $
b100111 )
b100111 '
#790000
0&
#800000
b101101010000010 !
b101101010000010 +
1&
b101101010000010 %
b101101010000010 *
b101000 $
b101000 )
b101000 '
#810000
0&
#820000
b101101010000011 !
b101101010000011 +
1&
b101101010000011 %
b101101010000011 *
b101001 $
b101001 )
b101001 '
#830000
0&
#840000
b101101010000100 !
b101101010000100 +
1&
b101101010000100 %
b101101010000100 *
b101010 $
b101010 )
b101010 '
#850000
0&
#860000
b101101010000101 !
b101101010000101 +
1&
b101101010000101 %
b101101010000101 *
b101011 $
b101011 )
b101011 '
#870000
0&
#880000
b101101010000110 !
b101101010000110 +
1&
b101101010000110 %
b101101010000110 *
b101100 $
b101100 )
b101100 '
#890000
0&
#900000
b101101010000111 !
b101101010000111 +
1&
b101101010000111 %
b101101010000111 *
b101101 $
b101101 )
b101101 '
#910000
0&
#920000
b101101010001000 !
b101101010001000 +
1&
b101101010001000 %
b101101010001000 *
b101110 $
b101110 )
b101110 '
#930000
0&
#940000
b101101010001001 !
b101101010001001 +
1&
b101101010001001 %
b101101010001001 *
b101111 $
b101111 )
b101111 '
#950000
0&
#960000
b101101010001010 !
b101101010001010 +
1&
b101101010001010 %
b101101010001010 *
b110000 $
b110000 )
b110000 '
#970000
0&
#980000
b101101010001011 !
b101101010001011 +
1&
b101101010001011 %
b101101010001011 *
b110001 $
b110001 )
b110001 '
#990000
0&
#1000000
b101101010001100 !
b101101010001100 +
1&
b101101010001100 %
b101101010001100 *
b110010 $
b110010 )
b110010 '
#1010000
0&
#1020000
b101101010001101 !
b101101010001101 +
1&
b101101010001101 %
b101101010001101 *
b110011 $
b110011 )
b110011 '
#1030000
0&
#1040000
b101101010001110 !
b101101010001110 +
1&
b101101010001110 %
b101101010001110 *
b110100 $
b110100 )
b110100 '
#1050000
0&
#1060000
b101101010001111 !
b101101010001111 +
1&
b101101010001111 %
b101101010001111 *
b110101 $
b110101 )
b110101 '
#1070000
0&
#1080000
b101101010010000 !
b101101010010000 +
1&
b101101010010000 %
b101101010010000 *
b110110 $
b110110 )
b110110 '
#1090000
0&
#1100000
b101101010010001 !
b101101010010001 +
1&
b101101010010001 %
b101101010010001 *
b110111 $
b110111 )
b110111 '
#1110000
0&
#1120000
b101101010010010 !
b101101010010010 +
1&
b101101010010010 %
b101101010010010 *
b111000 $
b111000 )
b111000 '
#1130000
0&
#1140000
b101101010010011 !
b101101010010011 +
1&
b101101010010011 %
b101101010010011 *
b111001 $
b111001 )
b111001 '
#1150000
0&
#1160000
b101101010010100 !
b101101010010100 +
1&
b101101010010100 %
b101101010010100 *
b111010 $
b111010 )
b111010 '
#1170000
0&
#1180000
b101101010010101 !
b101101010010101 +
1&
b101101010010101 %
b101101010010101 *
b111011 $
b111011 )
b111011 '
#1190000
0&
#1200000
b101101010010110 !
b101101010010110 +
1&
b101101010010110 %
b101101010010110 *
b111100 $
b111100 )
b111100 '
#1210000
0&
#1220000
b101101010010111 !
b101101010010111 +
1&
b101101010010111 %
b101101010010111 *
b111101 $
b111101 )
b111101 '
#1230000
0&
#1240000
b101101010011000 !
b101101010011000 +
1&
b101101010011000 %
b101101010011000 *
b111110 $
b111110 )
b111110 '
#1250000
0&
#1260000
b101101010011001 !
b101101010011001 +
1&
b101101010011001 %
b101101010011001 *
b111111 $
b111111 )
b111111 '
#1270000
0&
#1280000
b101101010011010 !
b101101010011010 +
1&
b101101010011010 %
b101101010011010 *
b1000000 $
b1000000 )
b1000000 '
#1290000
0&
#1300000
b101101010011011 !
b101101010011011 +
1&
b101101010011011 %
b101101010011011 *
b1000001 $
b1000001 )
b1000001 '
#1310000
0&
#1320000
b101101010011100 !
b101101010011100 +
1&
b101101010011100 %
b101101010011100 *
b1000010 $
b1000010 )
b1000010 '
#1330000
0&
#1340000
b101101010011101 !
b101101010011101 +
1&
b101101010011101 %
b101101010011101 *
b1000011 $
b1000011 )
b1000011 '
#1350000
0&
#1360000
b101101010011110 !
b101101010011110 +
1&
b101101010011110 %
b101101010011110 *
b1000100 $
b1000100 )
b1000100 '
#1370000
0&
#1380000
b101101010011111 !
b101101010011111 +
1&
b101101010011111 %
b101101010011111 *
b1000101 $
b1000101 )
b1000101 '
#1390000
0&
#1400000
b101101010100000 !
b101101010100000 +
1&
b101101010100000 %
b101101010100000 *
b1000110 $
b1000110 )
b1000110 '
#1410000
0&
#1420000
b101101010100001 !
b101101010100001 +
1&
b101101010100001 %
b101101010100001 *
b1000111 $
b1000111 )
b1000111 '
#1430000
0&
#1440000
b101101010100010 !
b101101010100010 +
1&
b101101010100010 %
b101101010100010 *
b1001000 $
b1001000 )
b1001000 '
#1450000
0&
#1460000
b101101010100011 !
b101101010100011 +
1&
b101101010100011 %
b101101010100011 *
b1001001 $
b1001001 )
b1001001 '
#1470000
0&
#1480000
b101101010100100 !
b101101010100100 +
1&
b101101010100100 %
b101101010100100 *
b1001010 $
b1001010 )
b1001010 '
#1490000
0&
#1500000
b101101010100101 !
b101101010100101 +
1&
b101101010100101 %
b101101010100101 *
b1001011 $
b1001011 )
b1001011 '
#1510000
0&
#1520000
b101101010100110 !
b101101010100110 +
1&
b101101010100110 %
b101101010100110 *
b1001100 $
b1001100 )
b1001100 '
#1530000
0&
#1540000
b101101010100111 !
b101101010100111 +
1&
b101101010100111 %
b101101010100111 *
b1001101 $
b1001101 )
b1001101 '
#1550000
0&
#1560000
b101101010101000 !
b101101010101000 +
1&
b101101010101000 %
b101101010101000 *
b1001110 $
b1001110 )
b1001110 '
#1570000
0&
#1580000
b101101010101001 !
b101101010101001 +
1&
b101101010101001 %
b101101010101001 *
b1001111 $
b1001111 )
b1001111 '
#1590000
0&
#1600000
b101101010101010 !
b101101010101010 +
1&
b101101010101010 %
b101101010101010 *
b1010000 $
b1010000 )
b1010000 '
#1610000
0&
#1620000
b101101010101011 !
b101101010101011 +
1&
b101101010101011 %
b101101010101011 *
b1010001 $
b1010001 )
b1010001 '
#1630000
0&
#1640000
b101101010101100 !
b101101010101100 +
1&
b101101010101100 %
b101101010101100 *
b1010010 $
b1010010 )
b1010010 '
#1650000
0&
#1660000
b101101010101101 !
b101101010101101 +
1&
b101101010101101 %
b101101010101101 *
b1010011 $
b1010011 )
b1010011 '
#1670000
0&
#1680000
b101101010101110 !
b101101010101110 +
1&
b101101010101110 %
b101101010101110 *
b1010100 $
b1010100 )
b1010100 '
#1690000
0&
#1700000
b101101010101111 !
b101101010101111 +
1&
b101101010101111 %
b101101010101111 *
b1010101 $
b1010101 )
b1010101 '
#1710000
0&
#1720000
b101101010110000 !
b101101010110000 +
1&
b101101010110000 %
b101101010110000 *
b1010110 $
b1010110 )
b1010110 '
#1730000
0&
#1740000
b101101010110001 !
b101101010110001 +
1&
b101101010110001 %
b101101010110001 *
b1010111 $
b1010111 )
b1010111 '
#1750000
0&
#1760000
b101101010110010 !
b101101010110010 +
1&
b101101010110010 %
b101101010110010 *
b1011000 $
b1011000 )
b1011000 '
#1770000
0&
#1780000
b101101010110011 !
b101101010110011 +
1&
b101101010110011 %
b101101010110011 *
b1011001 $
b1011001 )
b1011001 '
#1790000
0&
#1800000
b101101010110100 !
b101101010110100 +
1&
b101101010110100 %
b101101010110100 *
b1011010 $
b1011010 )
b1011010 '
#1810000
0&
#1820000
b101101010110101 !
b101101010110101 +
1&
b101101010110101 %
b101101010110101 *
b1011011 $
b1011011 )
b1011011 '
#1830000
0&
#1840000
b101101010110110 !
b101101010110110 +
1&
b101101010110110 %
b101101010110110 *
b1011100 $
b1011100 )
b1011100 '
#1850000
0&
#1860000
b101101010110111 !
b101101010110111 +
1&
b101101010110111 %
b101101010110111 *
b1011101 $
b1011101 )
b1011101 '
#1870000
0&
#1880000
b101101010111000 !
b101101010111000 +
1&
b101101010111000 %
b101101010111000 *
b1011110 $
b1011110 )
b1011110 '
#1890000
0&
#1900000
b101101010111001 !
b101101010111001 +
1&
b101101010111001 %
b101101010111001 *
b1011111 $
b1011111 )
b1011111 '
#1910000
0&
#1920000
b101101010111010 !
b101101010111010 +
1&
b101101010111010 %
b101101010111010 *
b1100000 $
b1100000 )
b1100000 '
#1930000
0&
#1940000
b101101010111011 !
b101101010111011 +
1&
b101101010111011 %
b101101010111011 *
b1100001 $
b1100001 )
b1100001 '
#1950000
0&
#1960000
b101101010111100 !
b101101010111100 +
1&
b101101010111100 %
b101101010111100 *
b1100010 $
b1100010 )
b1100010 '
#1970000
0&
#1980000
b101101010111101 !
b101101010111101 +
1&
b101101010111101 %
b101101010111101 *
b1100011 $
b1100011 )
b1100011 '
#1990000
0&
#2000000
b101101010111110 !
b101101010111110 +
1&
b101101010111110 %
b101101010111110 *
b1100100 $
b1100100 )
b1100100 '
#2010000
0&
#2020000
b101101010111111 !
b101101010111111 +
1&
b101101010111111 %
b101101010111111 *
b1100101 $
b1100101 )
b1100101 '
#2030000
0&
#2040000
b101101011000000 !
b101101011000000 +
1&
b101101011000000 %
b101101011000000 *
b1100110 $
b1100110 )
b1100110 '
#2050000
0&
#2060000
b101101011000001 !
b101101011000001 +
1&
b101101011000001 %
b101101011000001 *
b1100111 $
b1100111 )
b1100111 '
#2070000
0&
#2080000
b101101011000010 !
b101101011000010 +
1&
b101101011000010 %
b101101011000010 *
b1101000 $
b1101000 )
b1101000 '
#2090000
0&
#2100000
b101101011000011 !
b101101011000011 +
1&
b101101011000011 %
b101101011000011 *
b1101001 $
b1101001 )
b1101001 '
#2110000
0&
#2120000
b101101011000100 !
b101101011000100 +
1&
b101101011000100 %
b101101011000100 *
b1101010 $
b1101010 )
b1101010 '
#2130000
0&
#2140000
b101101011000101 !
b101101011000101 +
1&
b101101011000101 %
b101101011000101 *
b1101011 $
b1101011 )
b1101011 '
#2150000
0&
#2160000
b101101011000110 !
b101101011000110 +
1&
b101101011000110 %
b101101011000110 *
b1101100 $
b1101100 )
b1101100 '
#2170000
0&
#2180000
b101101011000111 !
b101101011000111 +
1&
b101101011000111 %
b101101011000111 *
b1101101 $
b1101101 )
b1101101 '
#2190000
0&
#2200000
b101101011001000 !
b101101011001000 +
1&
b101101011001000 %
b101101011001000 *
b1101110 $
b1101110 )
b1101110 '
#2210000
0&
#2220000
b101101011001001 !
b101101011001001 +
1&
b101101011001001 %
b101101011001001 *
b1101111 $
b1101111 )
b1101111 '
#2230000
0&
#2240000
b101101011001010 !
b101101011001010 +
1&
b101101011001010 %
b101101011001010 *
b1110000 $
b1110000 )
b1110000 '
#2250000
0&
#2260000
b101101011001011 !
b101101011001011 +
1&
b101101011001011 %
b101101011001011 *
b1110001 $
b1110001 )
b1110001 '
#2270000
0&
#2280000
b101101011001100 !
b101101011001100 +
1&
b101101011001100 %
b101101011001100 *
b1110010 $
b1110010 )
b1110010 '
#2290000
0&
#2300000
b101101011001101 !
b101101011001101 +
1&
b101101011001101 %
b101101011001101 *
b1110011 $
b1110011 )
b1110011 '
#2310000
0&
#2320000
b101101011001110 !
b101101011001110 +
1&
b101101011001110 %
b101101011001110 *
b1110100 $
b1110100 )
b1110100 '
#2330000
0&
#2340000
b101101011001111 !
b101101011001111 +
1&
b101101011001111 %
b101101011001111 *
b1110101 $
b1110101 )
b1110101 '
#2350000
0&
#2360000
b101101011010000 !
b101101011010000 +
1&
b101101011010000 %
b101101011010000 *
b1110110 $
b1110110 )
b1110110 '
#2370000
0&
#2380000
b101101011010001 !
b101101011010001 +
1&
b101101011010001 %
b101101011010001 *
b1110111 $
b1110111 )
b1110111 '
#2390000
0&
#2400000
b101101011010010 !
b101101011010010 +
1&
b101101011010010 %
b101101011010010 *
b1111000 $
b1111000 )
b1111000 '
#2410000
0&
#2420000
b101101011010011 !
b101101011010011 +
1&
b101101011010011 %
b101101011010011 *
b1111001 $
b1111001 )
b1111001 '
#2430000
0&
#2440000
b101101011010100 !
b101101011010100 +
1&
b101101011010100 %
b101101011010100 *
b1111010 $
b1111010 )
b1111010 '
#2450000
0&
#2460000
b101101011010101 !
b101101011010101 +
1&
b101101011010101 %
b101101011010101 *
b1111011 $
b1111011 )
b1111011 '
#2470000
0&
#2480000
b101101011010110 !
b101101011010110 +
1&
b101101011010110 %
b101101011010110 *
b1111100 $
b1111100 )
b1111100 '
#2490000
0&
#2500000
b101101011010111 !
b101101011010111 +
1&
b101101011010111 %
b101101011010111 *
b1111101 $
b1111101 )
b1111101 '
#2510000
0&
#2520000
b101101011011000 !
b101101011011000 +
1&
b101101011011000 %
b101101011011000 *
b1111110 $
b1111110 )
b1111110 '
#2530000
0&
#2540000
b101101011011001 !
b101101011011001 +
1&
b101101011011001 %
b101101011011001 *
b1111111 $
b1111111 )
b1111111 '
#2550000
0&
#2560000
b101101011011010 !
b101101011011010 +
1&
b101101011011010 %
b101101011011010 *
b10000000 $
b10000000 )
b10000000 '
#2570000
0&
#2580000
b101101011011011 !
b101101011011011 +
1&
b101101011011011 %
b101101011011011 *
b10000001 $
b10000001 )
b10000001 '
#2590000
0&
#2600000
b101101011011100 !
b101101011011100 +
1&
b101101011011100 %
b101101011011100 *
b10000010 $
b10000010 )
b10000010 '
#2610000
0&
#2620000
b101101011011101 !
b101101011011101 +
1&
b101101011011101 %
b101101011011101 *
b10000011 $
b10000011 )
b10000011 '
#2630000
0&
#2640000
b101101011011110 !
b101101011011110 +
1&
b101101011011110 %
b101101011011110 *
b10000100 $
b10000100 )
b10000100 '
#2650000
0&
#2660000
b101101011011111 !
b101101011011111 +
1&
b101101011011111 %
b101101011011111 *
b10000101 $
b10000101 )
b10000101 '
#2670000
0&
#2680000
b101101011100000 !
b101101011100000 +
1&
b101101011100000 %
b101101011100000 *
b10000110 $
b10000110 )
b10000110 '
#2690000
0&
#2700000
b101101011100001 !
b101101011100001 +
1&
b101101011100001 %
b101101011100001 *
b10000111 $
b10000111 )
b10000111 '
#2710000
0&
#2720000
b101101011100010 !
b101101011100010 +
1&
b101101011100010 %
b101101011100010 *
b10001000 $
b10001000 )
b10001000 '
#2730000
0&
#2740000
b101101011100011 !
b101101011100011 +
1&
b101101011100011 %
b101101011100011 *
b10001001 $
b10001001 )
b10001001 '
#2750000
0&
#2760000
b101101011100100 !
b101101011100100 +
1&
b101101011100100 %
b101101011100100 *
b10001010 $
b10001010 )
b10001010 '
#2770000
0&
#2780000
b101101011100101 !
b101101011100101 +
1&
b101101011100101 %
b101101011100101 *
b10001011 $
b10001011 )
b10001011 '
#2790000
0&
#2800000
b101101011100110 !
b101101011100110 +
1&
b101101011100110 %
b101101011100110 *
b10001100 $
b10001100 )
b10001100 '
#2810000
0&
#2820000
b101101011100111 !
b101101011100111 +
1&
b101101011100111 %
b101101011100111 *
b10001101 $
b10001101 )
b10001101 '
#2830000
0&
#2840000
b101101011101000 !
b101101011101000 +
1&
b101101011101000 %
b101101011101000 *
b10001110 $
b10001110 )
b10001110 '
#2850000
0&
#2860000
b101101011101001 !
b101101011101001 +
1&
b101101011101001 %
b101101011101001 *
b10001111 $
b10001111 )
b10001111 '
#2870000
0&
#2880000
b101101011101010 !
b101101011101010 +
1&
b101101011101010 %
b101101011101010 *
b10010000 $
b10010000 )
b10010000 '
#2890000
0&
#2900000
b101101011101011 !
b101101011101011 +
1&
b101101011101011 %
b101101011101011 *
b10010001 $
b10010001 )
b10010001 '
#2910000
0&
#2920000
b101101011101100 !
b101101011101100 +
1&
b101101011101100 %
b101101011101100 *
b10010010 $
b10010010 )
b10010010 '
#2930000
0&
#2940000
b101101011101101 !
b101101011101101 +
1&
b101101011101101 %
b101101011101101 *
b10010011 $
b10010011 )
b10010011 '
#2950000
0&
#2960000
b101101011101110 !
b101101011101110 +
1&
b101101011101110 %
b101101011101110 *
b10010100 $
b10010100 )
b10010100 '
#2970000
0&
#2980000
b101101011101111 !
b101101011101111 +
1&
b101101011101111 %
b101101011101111 *
b10010101 $
b10010101 )
b10010101 '
#2990000
0&
#3000000
b101101011110000 !
b101101011110000 +
1&
b101101011110000 %
b101101011110000 *
b10010110 $
b10010110 )
b10010110 '
#3010000
0&
#3020000
b101101011110001 !
b101101011110001 +
1&
b101101011110001 %
b101101011110001 *
b10010111 $
b10010111 )
b10010111 '
#3030000
0&
#3040000
b101101011110010 !
b101101011110010 +
1&
b101101011110010 %
b101101011110010 *
b10011000 $
b10011000 )
b10011000 '
#3050000
0&
#3060000
b101101011110011 !
b101101011110011 +
1&
b101101011110011 %
b101101011110011 *
b10011001 $
b10011001 )
b10011001 '
#3070000
0&
#3080000
b101101011110100 !
b101101011110100 +
1&
b101101011110100 %
b101101011110100 *
b10011010 $
b10011010 )
b10011010 '
#3090000
0&
#3100000
b101101011110101 !
b101101011110101 +
1&
b101101011110101 %
b101101011110101 *
b10011011 $
b10011011 )
b10011011 '
#3110000
0&
#3120000
b101101011110110 !
b101101011110110 +
1&
b101101011110110 %
b101101011110110 *
b10011100 $
b10011100 )
b10011100 '
#3130000
0&
#3140000
b101101011110111 !
b101101011110111 +
1&
b101101011110111 %
b101101011110111 *
b10011101 $
b10011101 )
b10011101 '
#3150000
0&
#3160000
b101101011111000 !
b101101011111000 +
1&
b101101011111000 %
b101101011111000 *
b10011110 $
b10011110 )
b10011110 '
#3170000
0&
#3180000
b101101011111001 !
b101101011111001 +
1&
b101101011111001 %
b101101011111001 *
b10011111 $
b10011111 )
b10011111 '
#3190000
0&
#3200000
b101101011111010 !
b101101011111010 +
1&
b101101011111010 %
b101101011111010 *
b10100000 $
b10100000 )
b10100000 '
#3210000
0&
#3220000
b101101011111011 !
b101101011111011 +
1&
b101101011111011 %
b101101011111011 *
b10100001 $
b10100001 )
b10100001 '
#3230000
0&
#3240000
b101101011111100 !
b101101011111100 +
1&
b101101011111100 %
b101101011111100 *
b10100010 $
b10100010 )
b10100010 '
#3250000
0&
#3260000
b101101011111101 !
b101101011111101 +
1&
b101101011111101 %
b101101011111101 *
b10100011 $
b10100011 )
b10100011 '
#3270000
0&
#3280000
b101101011111110 !
b101101011111110 +
1&
b101101011111110 %
b101101011111110 *
b10100100 $
b10100100 )
b10100100 '
#3290000
0&
#3300000
b101101011111111 !
b101101011111111 +
1&
b101101011111111 %
b101101011111111 *
b10100101 $
b10100101 )
b10100101 '
#3310000
0&
#3320000
b101101100000000 !
b101101100000000 +
1&
b101101100000000 %
b101101100000000 *
b10100110 $
b10100110 )
b10100110 '
#3330000
0&
#3340000
b101101100000001 !
b101101100000001 +
1&
b101101100000001 %
b101101100000001 *
b10100111 $
b10100111 )
b10100111 '
#3350000
0&
#3360000
b101101100000010 !
b101101100000010 +
1&
b101101100000010 %
b101101100000010 *
b10101000 $
b10101000 )
b10101000 '
#3370000
0&
#3380000
b101101100000011 !
b101101100000011 +
1&
b101101100000011 %
b101101100000011 *
b10101001 $
b10101001 )
b10101001 '
#3390000
0&
#3400000
b101101100000100 !
b101101100000100 +
1&
b101101100000100 %
b101101100000100 *
b10101010 $
b10101010 )
b10101010 '
#3410000
0&
#3420000
b101101100000101 !
b101101100000101 +
1&
b101101100000101 %
b101101100000101 *
b10101011 $
b10101011 )
b10101011 '
#3430000
0&
#3440000
b101101100000110 !
b101101100000110 +
1&
b101101100000110 %
b101101100000110 *
b10101100 $
b10101100 )
b10101100 '
#3450000
0&
#3460000
b101101100000111 !
b101101100000111 +
1&
b101101100000111 %
b101101100000111 *
b10101101 $
b10101101 )
b10101101 '
#3470000
0&
#3480000
b101101100001000 !
b101101100001000 +
1&
b101101100001000 %
b101101100001000 *
b10101110 $
b10101110 )
b10101110 '
#3490000
0&
#3500000
b101101100001001 !
b101101100001001 +
1&
b101101100001001 %
b101101100001001 *
b10101111 $
b10101111 )
b10101111 '
#3510000
0&
#3520000
b101101100001010 !
b101101100001010 +
1&
b101101100001010 %
b101101100001010 *
b10110000 $
b10110000 )
b10110000 '
#3530000
0&
#3540000
b101101100001011 !
b101101100001011 +
1&
b101101100001011 %
b101101100001011 *
b10110001 $
b10110001 )
b10110001 '
#3550000
0&
#3560000
b101101100001100 !
b101101100001100 +
1&
b101101100001100 %
b101101100001100 *
b10110010 $
b10110010 )
b10110010 '
#3570000
0&
#3580000
b101101100001101 !
b101101100001101 +
1&
b101101100001101 %
b101101100001101 *
b10110011 $
b10110011 )
b10110011 '
#3590000
0&
#3600000
b101101100001110 !
b101101100001110 +
1&
b101101100001110 %
b101101100001110 *
b10110100 $
b10110100 )
b10110100 '
#3610000
0&
#3620000
b101101100001111 !
b101101100001111 +
1&
b101101100001111 %
b101101100001111 *
b10110101 $
b10110101 )
b10110101 '
#3630000
0&
#3640000
b101101100010000 !
b101101100010000 +
1&
b101101100010000 %
b101101100010000 *
b10110110 $
b10110110 )
b10110110 '
#3650000
0&
#3660000
b101101100010001 !
b101101100010001 +
1&
b101101100010001 %
b101101100010001 *
b10110111 $
b10110111 )
b10110111 '
#3670000
0&
#3680000
b101101100010010 !
b101101100010010 +
1&
b101101100010010 %
b101101100010010 *
b10111000 $
b10111000 )
b10111000 '
#3690000
0&
#3700000
b101101100010011 !
b101101100010011 +
1&
b101101100010011 %
b101101100010011 *
b10111001 $
b10111001 )
b10111001 '
#3710000
0&
#3720000
b101101100010100 !
b101101100010100 +
1&
b101101100010100 %
b101101100010100 *
b10111010 $
b10111010 )
b10111010 '
#3730000
0&
#3740000
b101101100010101 !
b101101100010101 +
1&
b101101100010101 %
b101101100010101 *
b10111011 $
b10111011 )
b10111011 '
