Project-03/Ram4k/RAM4k.v
module RAM4K (
    input wire clk,              // Clock signal
    input wire [11:0] address,   // 12-bit address to select one of 4096 registers
    input wire [15:0] in,         // 16-bit input data to be written
    input wire load,              // Load signal
    output reg [15:0] out         // 16-bit output data
);

    // Declare an array of 4096 registers, each 16 bits wide
    reg [15:0] memory [0:4095];

    // Always block to handle read and write operations
    always @(posedge clk) begin
        if (load) begin
            // Write data to the specified address if load is high
            memory[address] <= in;
        end
    end

    // Always block to handle reading from memory
    always @(*) begin
        // Output the value stored at the specified address
        out = memory[address];
    end

endmodule

Project-03/Ram4k/RAM4k_tb.v
`timescale 1ns / 1ps

module tb_RAM4K;

    // Parameters
    parameter ADDRESS_WIDTH = 12; // 12 bits for 4096 addresses
    parameter DATA_WIDTH = 16;    // 16 bits for data

    // Inputs
    reg clk;                         // Clock signal
    reg [ADDRESS_WIDTH-1:0] address; // Address input
    reg [DATA_WIDTH-1:0] in;         // Data input
    reg load;                        // Load signal

    // Outputs
    wire [DATA_WIDTH-1:0] out;       // Output data

    // Instantiate the RAM4K module
    RAM4K uut (
        .clk(clk),
        .address(address),
        .in(in),
        .load(load),
        .out(out)
    );

    // File handling
    integer output_file;
    integer i;

    // Clock generation
    initial begin
        clk = 0;
        forever #5 clk = ~clk; // Toggle clock every 5 time units
    end

    // Initial block
    initial begin
        // Open the output file
        output_file = $fopen("output_file.txt", "w");
        if (output_file == 0) begin
            $display("Error: Could not open output_file.txt");
            $finish;
        end

        // Dump waveform data to VCD file (optional)
        $dumpfile("RAM4K.vcd");
        $dumpvars(0, tb_RAM4K);

        // Test sequence
        // Write to all addresses
        for (i = 0; i < 4096; i = i + 1) begin
            address = i;                       // Set the address
            in = 16'h5A5A + i;                // Set the data to write
            load = 1;                         // Set load to 1 to enable writing
            #10;                               // Wait for 10 time units to allow writing
            $fwrite(output_file, "Address: %b, Written Data: %h\n", address, in);

            load = 0;                         // Set load to 0 to disable writing
            #10;                               // Wait for 10 time units before the next operation
        end

        // Add a delay to allow for all writes to settle
        #20;

        // Read from all addresses
        for (i = 0; i < 4096; i = i + 1) begin
            address = i;                      // Set the address to read
            #10;                              // Wait for 10 time units to allow reading
            $fwrite(output_file, "Address: %b, Read Data: %h\n", address, out);
        end

        // Close the output file
        $fclose(output_file);

        // Finish simulation
        $finish;
    end

endmodule

Project-03/Ram4k/RAM4K.vcd
$date
	Wed Aug 21 20:25:16 2024
$end
$version
	Icarus Verilog
$end
$timescale
	1ps
$end
$scope module tb_RAM4K $end
$var wire 16 ! out [15:0] $end
$var parameter 32 " ADDRESS_WIDTH $end
$var parameter 32 # DATA_WIDTH $end
$var reg 12 $ address [11:0] $end
$var reg 1 % clk $end
$var reg 16 & in [15:0] $end
$var reg 1 ' load $end
$var integer 32 ( i [31:0] $end
$var integer 32 ) output_file [31:0] $end
$scope module uut $end
$var wire 12 * address [11:0] $end
$var wire 1 % clk $end
$var wire 16 + in [15:0] $end
$var wire 1 ' load $end
$var reg 16 , out [15:0] $end
$upscope $end
$upscope $end
$enddefinitions $end
$comment Show the parameter values. $end
$dumpall
b10000 #
b1100 "
$end
#0
$dumpvars
bx ,
b101101001011010 +
b0 *
b10000000000000000000000000000011 )
b0 (
1'
b101101001011010 &
0%
b0 $
bx !
$end
#5000
b101101001011010 !
b101101001011010 ,
1%
#10000
0%
0'
#15000
1%
#20000
bx !
bx ,
0%
1'
b101101001011011 &
b101101001011011 +
b1 $
b1 *
b1 (
#25000
b101101001011011 !
b101101001011011 ,
1%
#30000
0%
0'
#35000
1%
#40000
bx !
bx ,
0%
1'
b101101001011100 &
b101101001011100 +
b10 $
b10 *
b10 (
#45000
b101101001011100 !
b101101001011100 ,
1%
#50000
0%
0'
#55000
1%
#60000
bx !
bx ,
0%
1'
b101101001011101 &
b101101001011101 +
b11 $
b11 *
b11 (
#65000
b101101001011101 !
b101101001011101 ,
1%
#70000
0%
0'
#75000
1%
#80000
bx !
bx ,
0%
1'
b101101001011110 &
b101101001011110 +
b100 $
b100 *
b100 (
#85000
b101101001011110 !
b101101001011110 ,
1%
#90000
0%
0'
#95000
1%
#100000
bx !
bx ,
0%
1'
b101101001011111 &
b101101001011111 +
b101 $
b101 *
b101 (
#105000
b101101001011111 !
b101101001011111 ,
1%
#110000
0%
0'
#115000
1%
#120000
bx !
bx ,
0%
1'
b101101001100000 &
b101101001100000 +
b110 $
b110 *
b110 (
#125000
b101101001100000 !
b101101001100000 ,
1%
#130000
0%
0'
#135000
1%
#140000
bx !
bx ,
0%
1'
b101101001100001 &
b101101001100001 +
b111 $
b111 *
b111 (
#145000
b101101001100001 !
b101101001100001 ,
1%
#150000
0%
0'
#155000
1%
#160000
bx !
bx ,
0%
1'
b101101001100010 &
b101101001100010 +
b1000 $
b1000 *
b1000 (
#165000
b101101001100010 !
b101101001100010 ,
1%
#170000
0%
0'
#175000
1%
#180000
bx !
bx ,
0%
1'
b101101001100011 &
b101101001100011 +
b1001 $
b1001 *
b1001 (
#185000
b101101001100011 !
b101101001100011 ,
1%
#190000
0%
0'
#195000
1%
#200000
bx !
bx ,
0%
1'
b101101001100100 &
b101101001100100 +
b1010 $
b1010 *
b1010 (
#205000
b101101001100100 !
b101101001100100 ,
1%
#210000
0%
0'
#215000
1%
#220000
bx !
bx ,
0%
1'
b101101001100101 &
b101101001100101 +
b1011 $
b1011 *
b1011 (
#225000
b101101001100101 !
b101101001100101 ,
1%
#230000
0%
0'
#235000
1%
#240000
bx !
bx ,
0%
1'
b101101001100110 &
b101101001100110 +
b1100 $
b1100 *
b1100 (
#245000
b101101001100110 !
b101101001100110 ,
1%
#250000
0%
0'
#255000
1%
#260000
bx !
bx ,
0%
1'
b101101001100111 &
b101101001100111 +
b1101 $
b1101 *
b1101 (
#265000
b101101001100111 !
b101101001100111 ,
1%
#270000
0%
0'
#275000
1%
#280000
bx !
bx ,
0%
1'
b101101001101000 &
b101101001101000 +
b1110 $
b1110 *
b1110 (
#285000
b101101001101000 !
b101101001101000 ,
1%
#290000
0%
0'
#295000
1%
#300000
bx !
bx ,
0%
1'
b101101001101001 &
b101101001101001 +
b1111 $
b1111 *
b1111 (
#305000
b101101001101001 !
b101101001101001 ,
1%
#310000
0%
0'
#315000
1%
#320000
bx !
bx ,
0%
1'
b101101001101010 &
b101101001101010 +
b10000 $
b10000 *
b10000 (
#325000
b101101001101010 !
b101101001101010 ,
1%
#330000
0%
0'
#335000
1%
#340000
bx !
bx ,
0%
1'
b101101001101011 &
b101101001101011 +
b10001 $
b10001 *
b10001 (
#345000
b101101001101011 !
b101101001101011 ,
1%
#350000
0%
0'
#355000
1%
#360000
bx !
bx ,
0%
1'
b101101001101100 &
b101101001101100 +
b10010 $
b10010 *
b10010 (
#365000
b101101001101100 !
b101101001101100 ,
1%
#370000
0%
0'
#375000
1%
#380000
bx !
bx ,
0%
1'
b101101001101101 &
b101101001101101 +
b10011 $
b10011 *
b10011 (
#385000
b101101001101101 !
b101101001101101 ,
1%
#390000
0%
0'
#395000
1%
#400000
bx !
bx ,
0%
1'
b101101001101110 &
b101101001101110 +
b10100 $
b10100 *
b10100 (
#405000
b101101001101110 !
b101101001101110 ,
1%
#410000
0%
0'
#415000
1%
#420000
bx !
bx ,
0%
1'
b101101001101111 &
b101101001101111 +
b10101 $
b10101 *
b10101 (
#425000
b101101001101111 !
b101101001101111 ,
1%
#430000
0%
0'
#435000
1%
#440000
bx !
bx ,
0%
1'
b101101001110000 &
b101101001110000 +
b10110 $
b10110 *
b10110 (
#445000
b101101001110000 !
b101101001110000 ,
1%
#450000
0%
0'
#455000
1%
#460000
bx !
bx ,
0%
1'
b101101001110001 &
b101101001110001 +
b10111 $
b10111 *
b10111 (
#465000
b101101001110001 !
b101101001110001 ,
1%
#470000
0%
0'
#475000
1%
#480000
bx !
bx ,
0%
1'
b101101001110010 &
b101101001110010 +
b11000 $
b11000 *
b11000 (
#485000
b101101001110010 !
b101101001110010 ,
1%
#490000
0%
0'
#495000
1%
#500000
bx !
bx ,
0%
1'
b101101001110011 &
b101101001110011 +
b11001 $
b11001 *
b11001 (
#505000
b101101001110011 !
b101101001110011 ,
1%
#510000
0%
0'
#515000
1%
#520000
bx !
bx ,
0%
1'
b101101001110100 &
b101101001110100 +
b11010 $
b11010 *
b11010 (
#525000
b101101001110100 !
b101101001110100 ,
1%
#530000
0%
0'
#535000
1%
#540000
bx !
bx ,
0%
1'
b101101001110101 &
b101101001110101 +
b11011 $
b11011 *
b11011 (
#545000
b101101001110101 !
b101101001110101 ,
1%
#550000
0%
0'
#555000
1%
#560000
bx !
bx ,
0%
1'
b101101001110110 &
b101101001110110 +
b11100 $
b11100 *
b11100 (
#565000
b101101001110110 !
b101101001110110 ,
1%
#570000
0%
0'
#575000
1%
#580000
bx !
bx ,
0%
1'
b101101001110111 &
b101101001110111 +
b11101 $
b11101 *
b11101 (
#585000
b101101001110111 !
b101101001110111 ,
1%
#590000
0%
0'
#595000
1%
#600000
bx !
bx ,
0%
1'
b101101001111000 &
b101101001111000 +
b11110 $
b11110 *
b11110 (
#605000
b101101001111000 !
b101101001111000 ,
1%
#610000
0%
0'
#615000
1%
#620000
bx !
bx ,
0%
1'
b101101001111001 &
b101101001111001 +
b11111 $
b11111 *
b11111 (
#625000
b101101001111001 !
b101101001111001 ,
1%
#630000
0%
0'
#635000
1%
#640000
bx !
bx ,
0%
1'
b101101001111010 &
b101101001111010 +
b100000 $
b100000 *
b100000 (
#645000
b101101001111010 !
b101101001111010 ,
1%
#650000
0%
0'
#655000
1%
#660000
bx !
bx ,
0%
1'
b101101001111011 &
b101101001111011 +
b100001 $
b100001 *
b100001 (
#665000
b101101001111011 !
b101101001111011 ,
1%
#670000
0%
0'
#675000
1%
#680000
bx !
bx ,
0%
1'
b101101001111100 &
b101101001111100 +
b100010 $
b100010 *
b100010 (
#685000
b101101001111100 !
b101101001111100 ,
1%
#690000
0%
0'
#695000
1%
#700000
bx !
bx ,
0%
1'
b101101001111101 &
b101101001111101 +
b100011 $
b100011 *
b100011 (
#705000
b101101001111101 !
b101101001111101 ,
1%
#710000
0%
0'
#715000
1%
#720000
bx !
bx ,
0%
1'
b101101001111110 &
b101101001111110 +
b100100 $
b100100 *
b100100 (
#725000
b101101001111110 !
b101101001111110 ,
1%
#730000
0%
0'
#735000
1%
#740000
bx !
bx ,
0%
1'
b101101001111111 &
b101101001111111 +
b100101 $
b100101 *
b100101 (
#745000
b101101001111111 !
b101101001111111 ,
1%
#750000
0%
0'
#755000
1%
#760000
bx !
bx ,
0%
1'
b101101010000000 &
b101101010000000 +
b100110 $
b100110 *
b100110 (
#765000
b101101010000000 !
b101101010000000 ,
1%
#770000
0%
0'
#775000
1%
#780000
bx !
bx ,
0%
1'
b101101010000001 &
b101101010000001 +
b100111 $
b100111 *
b100111 (
#785000
b101101010000001 !
b101101010000001 ,
1%
#790000
0%
0'
#795000
1%
#800000
bx !
bx ,
0%
1'
b101101010000010 &
b101101010000010 +
b101000 $
b101000 *
b101000 (
#805000
b101101010000010 !
b101101010000010 ,
1%
#810000
0%
0'
#815000
1%
#820000
bx !
bx ,
0%
1'
b101101010000011 &
b101101010000011 +
b101001 $
b101001 *
b101001 (
#825000
b101101010000011 !
b101101010000011 ,
1%
#830000
0%
0'
#835000
1%
#840000
bx !
bx ,
0%
1'
b101101010000100 &
b101101010000100 +
b101010 $
b101010 *
b101010 (
#845000
b101101010000100 !
b101101010000100 ,
1%
#850000
0%
0'
#855000
1%
#860000
bx !
bx ,
0%
1'
b101101010000101 &
b101101010000101 +
b101011 $
b101011 *
b101011 (
#865000
b101101010000101 !
b101101010000101 ,
1%
#870000
0%
0'
#875000
1%
#880000
bx !
bx ,
0%
1'
b101101010000110 &
b101101010000110 +
b101100 $
b101100 *
b101100 (
#885000
b101101010000110 !
b101101010000110 ,
1%
#890000
0%
0'
#895000
1%
#900000
bx !
bx ,
0%
1'
b101101010000111 &
b101101010000111 +
b101101 $
b101101 *
b101101 (
#905000
b101101010000111 !
b101101010000111 ,
1%
#910000
0%
0'
#915000
1%
#920000
bx !
bx ,
0%
1'
b101101010001000 &
b101101010001000 +
b101110 $
b101110 *
b101110 (
#925000
b101101010001000 !
b101101010001000 ,
1%
#930000
0%
0'
#935000
1%
#940000
bx !
bx ,
0%
1'
b101101010001001 &
b101101010001001 +
b101111 $
b101111 *
b101111 (
#945000
b101101010001001 !
b101101010001001 ,
1%
#950000
0%
0'
#955000
1%
#960000
bx !
bx ,
0%
1'
b101101010001010 &
b101101010001010 +
b110000 $
b110000 *
b110000 (
#965000
b101101010001010 !
b101101010001010 ,
1%
#970000
0%
0'
#975000
1%
#980000
bx !
bx ,
0%
1'
b101101010001011 &
b101101010001011 +
b110001 $
b110001 *
b110001 (
#985000
b101101010001011 !
b101101010001011 ,
1%
#990000
0%
0'
#995000
1%
#1000000
bx !
bx ,
0%
1'
b101101010001100 &
b101101010001100 +
b110010 $
b110010 *
b110010 (
#1005000
b101101010001100 !
b101101010001100 ,
1%
#1010000
0%
0'
#1015000
1%
#1020000
bx !
bx ,
0%
1'
b101101010001101 &
b101101010001101 +
b110011 $
b110011 *
b110011 (
#1025000
b101101010001101 !
b101101010001101 ,
1%
#1030000
0%
0'
#1035000
1%
#1040000
bx !
bx ,
0%
1'
b101101010001110 &
b101101010001110 +
b110100 $
b110100 *
b110100 (
#1045000
b101101010001110 !
b101101010001110 ,
1%
#1050000
0%
0'
#1055000
1%
#1060000
bx !
bx ,
0%
1'
b101101010001111 &
b101101010001111 +
b110101 $
b110101 *
b110101 (
#1065000
b101101010001111 !
b101101010001111 ,
1%
#1070000
0%
0'
#1075000
1%
#1080000
bx !
bx ,
0%
1'
b101101010010000 &
b101101010010000 +
b110110 $
b110110 *
b110110 (
#1085000
b101101010010000 !
b101101010010000 ,
1%
#1090000
0%
0'
#1095000
1%
#1100000
bx !
bx ,
0%
1'
b101101010010001 &
b101101010010001 +
b110111 $
b110111 *
b110111 (
#1105000
b101101010010001 !
b101101010010001 ,
1%
#1110000
0%
0'
#1115000
1%
#1120000
bx !
bx ,
0%
1'
b101101010010010 &
b101101010010010 +
b111000 $
b111000 *
b111000 (
#1125000
b101101010010010 !
b101101010010010 ,
1%
#1130000
0%
0'
#1135000
1%
#1140000
bx !
bx ,
0%
1'
b101101010010011 &
b101101010010011 +
b111001 $
b111001 *
b111001 (
#1145000
b101101010010011 !
b101101010010011 ,
1%
#1150000
0%
0'
#1155000
1%
#1160000
bx !
bx ,
0%
1'
b101101010010100 &
b101101010010100 +
b111010 $
b111010 *
b111010 (
#1165000
b101101010010100 !
b101101010010100 ,
1%
#1170000
0%
0'
#1175000
1%
#1180000
bx !
bx ,
0%
1'
b101101010010101 &
b101101010010101 +
b111011 $
b111011 *
b111011 (
#1185000
b101101010010101 !
b101101010010101 ,
1%
#1190000
0%
0'
#1195000
1%
#1200000
bx !
bx ,
0%
1'
b101101010010110 &
b101101010010110 +
b111100 $
b111100 *
b111100 (
#1205000
b101101010010110 !
b101101010010110 ,
1%
#1210000
0%
0'
#1215000
1%
#1220000
bx !
bx ,
0%
1'
b101101010010111 &
b101101010010111 +
b111101 $
b111101 *
b111101 (
#1225000
b101101010010111 !
b101101010010111 ,
1%
#1230000
0%
0'
#1235000
1%
#1240000
bx !
bx ,
0%
1'
b101101010011000 &
b101101010011000 +
b111110 $
b111110 *
b111110 (
#1245000
b101101010011000 !
b101101010011000 ,
1%
#1250000
0%
0'
#1255000
1%
#1260000
bx !
bx ,
0%
1'
b101101010011001 &
b101101010011001 +
b111111 $
b111111 *
b111111 (
#1265000
b101101010011001 !
b101101010011001 ,
1%
#1270000
0%
0'
#1275000
1%
#1280000
bx !
bx ,
0%
1'
b101101010011010 &
b101101010011010 +
b1000000 $
b1000000 *
b1000000 (
#1285000
b101101010011010 !
b101101010011010 ,
1%
#1290000
0%
0'
#1295000
1%
#1300000
bx !
bx ,
0%
1'
b101101010011011 &
b101101010011011 +
b1000001 $
b1000001 *
b1000001 (
#1305000
b101101010011011 !
b101101010011011 ,
1%
#1310000
0%
0'
#1315000
1%
#1320000
bx !
bx ,
0%
1'
b101101010011100 &
b101101010011100 +
b1000010 $
b1000010 *
b1000010 (
#1325000
b101101010011100 !
b101101010011100 ,
1%
#1330000
0%
0'
#1335000
1%
#1340000
bx !
bx ,
0%
1'
b101101010011101 &
b101101010011101 +
b1000011 $
b1000011 *
b1000011 (
#1345000
b101101010011101 !
b101101010011101 ,
1%
#1350000
0%
0'
#1355000
1%
#1360000
bx !
bx ,
0%
1'
b101101010011110 &
b101101010011110 +
b1000100 $
b1000100 *
b1000100 (
#1365000
b101101010011110 !
b101101010011110 ,
1%
#1370000
0%
0'
#1375000
1%
#1380000
bx !
bx ,
0%
1'
b101101010011111 &
b101101010011111 +
b1000101 $
b1000101 *
b1000101 (
#1385000
b101101010011111 !
b101101010011111 ,
1%
#1390000
0%
0'
#1395000
1%
#1400000
bx !
bx ,
0%
1'
b101101010100000 &
b101101010100000 +
b1000110 $
b1000110 *
b1000110 (
#1405000
b101101010100000 !
b101101010100000 ,
1%
#1410000
0%
0'
#1415000
1%
#1420000
bx !
bx ,
0%
1'
b101101010100001 &
b101101010100001 +
b1000111 $
b1000111 *
b1000111 (
#1425000
b101101010100001 !
b101101010100001 ,
1%
#1430000
0%
0'
#1435000
1%
#1440000
bx !
bx ,
0%
1'
b101101010100010 &
b101101010100010 +
b1001000 $
b1001000 *
b1001000 (
#1445000
b101101010100010 !
b101101010100010 ,
1%
#1450000
0%
0'
#1455000
1%
#1460000
bx !
bx ,
0%
1'
b101101010100011 &
b101101010100011 +
b1001001 $
b1001001 *
b1001001 (
#1465000
b101101010100011 !
b101101010100011 ,
1%
#1470000
0%
0'
#1475000
1%
#1480000
bx !
bx ,
0%
1'
b101101010100100 &
b101101010100100 +
b1001010 $
b1001010 *
b1001010 (
#1485000
b101101010100100 !
b101101010100100 ,
1%
#1490000
0%
0'
#1495000
1%
#1500000
bx !
bx ,
0%
1'
b101101010100101 &
b101101010100101 +
b1001011 $
b1001011 *
b1001011 (
#1505000
b101101010100101 !
b101101010100101 ,
1%
#1510000
0%
0'
#1515000
1%
#1520000
bx !
bx ,
0%
1'
b101101010100110 &
b101101010100110 +
b1001100 $
b1001100 *
b1001100 (
#1525000
b101101010100110 !
b101101010100110 ,
1%
#1530000
0%
0'
#1535000
1%
#1540000
bx !
bx ,
0%
1'
b101101010100111 &
b101101010100111 +
b1001101 $
b1001101 *
b1001101 (
#1545000
b101101010100111 !
b101101010100111 ,
1%
#1550000
0%
0'
#1555000
1%
#1560000
bx !
bx ,
0%
1'
b101101010101000 &
b101101010101000 +
b1001110 $
b1001110 *
b1001110 (
#1565000
b101101010101000 !
b101101010101000 ,
1%
#1570000
0%
0'
#1575000
1%
#1580000
bx !
bx ,
0%
1'
b101101010101001 &
b101101010101001 +
b1001111 $
b1001111 *
b1001111 (
#1585000
b101101010101001 !
b101101010101001 ,
1%
#1590000
0%
0'
#1595000
1%
#1600000
bx !
bx ,
0%
1'
b101101010101010 &
b101101010101010 +
b1010000 $
b1010000 *
b1010000 (
#1605000
b101101010101010 !
b101101010101010 ,
1%
#1610000
0%
0'
#1615000
1%
#1620000
bx !
bx ,
0%
1'
b101101010101011 &
b101101010101011 +
b1010001 $
b1010001 *
b1010001 (
#1625000
b101101010101011 !
b101101010101011 ,
1%
#1630000
0%
0'
#1635000
1%
#1640000
bx !
bx ,
0%
1'
b101101010101100 &
b101101010101100 +
b1010010 $
b1010010 *
b1010010 (
#1645000
b101101010101100 !
b101101010101100 ,
1%
#1650000
0%
0'
#1655000
1%
#1660000
bx !
bx ,
0%
1'
b101101010101101 &
b101101010101101 +
b1010011 $
b1010011 *
b1010011 (
#1665000
b101101010101101 !
b101101010101101 ,
1%
#1670000
0%
0'
#1675000
1%
#1680000
bx !
bx ,
0%
1'
b101101010101110 &
b101101010101110 +
b1010100 $
b1010100 *
b1010100 (
#1685000
b101101010101110 !
b101101010101110 ,
1%
#1690000
0%
0'
#1695000
1%
#1700000
bx !
bx ,
0%
1'
b101101010101111 &
b101101010101111 +
b1010101 $
b1010101 *
b1010101 (
#1705000
b101101010101111 !
b101101010101111 ,
1%
#1710000
0%
0'
#1715000
1%
#1720000
bx !
bx ,
0%
1'
b101101010110000 &
b101101010110000 +
b1010110 $
b1010110 *
b1010110 (
#1725000
b101101010110000 !
b101101010110000 ,
1%
#1730000
0%
0'
#1735000
1%
#1740000
bx !
bx ,
0%
1'
b101101010110001 &
b101101010110001 +
b1010111 $
b1010111 *
b1010111 (
#1745000
b101101010110001 !
b101101010110001 ,
1%
#1750000
0%
0'
#1755000
1%
#1760000
bx !
bx ,
0%
1'
b101101010110010 &
b101101010110010 +
b1011000 $
b1011000 *
b1011000 (
#1765000
b101101010110010 !
b101101010110010 ,
1%
#1770000
0%
0'
#1775000
1%
#1780000
bx !
bx ,
0%
1'
b101101010110011 &
b101101010110011 +
b1011001 $
b1011001 *
b1011001 (
#1785000
b101101010110011 !
b101101010110011 ,
1%
#1790000
0%
0'
#1795000
1%
#1800000
bx !
bx ,
0%
1'
b101101010110100 &
b101101010110100 +
b1011010 $
b1011010 *
b1011010 (
#1805000
b101101010110100 !
b101101010110100 ,
1%
#1810000
0%
0'
#1815000
1%
#1820000
bx !
bx ,
0%
1'
b101101010110101 &
b101101010110101 +
b1011011 $
b1011011 *
b1011011 (
#1825000
b101101010110101 !
b101101010110101 ,
1%
#1830000
0%
0'
#1835000
1%
#1840000
bx !
bx ,
0%
1'
b101101010110110 &
b101101010110110 +
b1011100 $
b1011100 *
b1011100 (
#1845000
b101101010110110 !
b101101010110110 ,
1%
#1850000
0%
0'
#1855000
1%
#1860000
bx !
bx ,
0%
1'
b101101010110111 &
b101101010110111 +
b1011101 $
b1011101 *
b1011101 (
#1865000
b101101010110111 !
b101101010110111 ,
1%
#1870000
0%
0'
#1875000
1%
#1880000
bx !
bx ,
0%
1'
b101101010111000 &
b101101010111000 +
b1011110 $
b1011110 *
b1011110 (
#1885000
b101101010111000 !
b101101010111000 ,
1%
#1890000
0%
0'
#1895000
1%
#1900000
bx !
bx ,
0%
1'
b101101010111001 &
b101101010111001 +
b1011111 $
b1011111 *
b1011111 (
#1905000
b101101010111001 !
b101101010111001 ,
1%
#1910000
0%
0'
#1915000
1%
#1920000
bx !
bx ,
0%
1'
b101101010111010 &
b101101010111010 +
b1100000 $
b1100000 *
b1100000 (
#1925000
b101101010111010 !
b101101010111010 ,
1%
#1930000
0%
0'
#1935000
1%
#1940000
bx !
bx ,
0%
1'
b101101010111011 &
b101101010111011 +
b1100001 $
b1100001 *
b1100001 (
#1945000
b101101010111011 !
b101101010111011 ,
1%
#1950000
0%
0'
#1955000
1%
#1960000
bx !
bx ,
0%
1'
b101101010111100 &
b101101010111100 +
b1100010 $
b1100010 *
b1100010 (
#1965000
b101101010111100 !
b101101010111100 ,
1%
#1970000
0%
0'
#1975000
1%
#1980000
bx !
bx ,
0%
1'
b101101010111101 &
b101101010111101 +
b1100011 $
b1100011 *
b1100011 (
#1985000
b101101010111101 !
b101101010111101 ,
1%
#1990000
0%
0'
#1995000
1%
#2000000
bx !
bx ,
0%
1'
b101101010111110 &
b101101010111110 +
b1100100 $
b1100100 *
b1100100 (
#2005000
b101101010111110 !
b101101010111110 ,
1%
#2010000
0%
0'
#2015000
1%
#2020000
bx !
bx ,
0%
1'
b101101010111111 &
b101101010111111 +
b1100101 $
b1100101 *
b1100101 (
#2025000
b101101010111111 !
b101101010111111 ,
1%
#2030000
0%
0'
#2035000
1%
#2040000
bx !
bx ,
0%
1'
b101101011000000 &
b101101011000000 +
b1100110 $
b1100110 *
b1100110 (
#2045000
b101101011000000 !
b101101011000000 ,
1%
#2050000
0%
0'
#2055000
1%
#2060000
bx !
bx ,
0%
1'
b101101011000001 &
b101101011000001 +
b1100111 $
b1100111 *
b1100111 (
#2065000
b101101011000001 !
b101101011000001 ,
1%
#2070000
0%
0'
#2075000
1%
#2080000
bx !
bx ,
0%
1'
b101101011000010 &
b101101011000010 +
b1101000 $
b1101000 *
b1101000 (
#2085000
b101101011000010 !
b101101011000010 ,
1%
#2090000
0%
0'
#2095000
1%
#2100000
bx !
bx ,
0%
1'
b101101011000011 &
b101101011000011 +
b1101001 $
b1101001 *
b1101001 (
#2105000
b101101011000011 !
b101101011000011 ,
1%
#2110000
0%
0'
#2115000
1%
#2120000
bx !
bx ,
0%
1'
b101101011000100 &
b101101011000100 +
b1101010 $
b1101010 *
b1101010 (
#2125000
b101101011000100 !
b101101011000100 ,
1%
#2130000
0%
0'
#2135000
1%
#2140000
bx !
bx ,
0%
1'
b101101011000101 &
b101101011000101 +
b1101011 $
b1101011 *
b1101011 (
#2145000
b101101011000101 !
b101101011000101 ,
1%
#2150000
0%
0'
#2155000
1%
#2160000
bx !
bx ,
0%
1'
b101101011000110 &
b101101011000110 +
b1101100 $
b1101100 *
b1101100 (
#2165000
b101101011000110 !
b101101011000110 ,
1%
#2170000
0%
0'
#2175000
1%
#2180000
bx !
bx ,
0%
1'
b101101011000111 &
b101101011000111 +
b1101101 $
b1101101 *
b1101101 (
#2185000
b101101011000111 !
b101101011000111 ,
1%
#2190000
0%
0'
#2195000
1%
#2200000
bx !
bx ,
0%
1'
b101101011001000 &
b101101011001000 +
b1101110 $
b1101110 *
b1101110 (
#2205000
b101101011001000 !
b101101011001000 ,
1%
#2210000
0%
0'
#2215000
1%
#2220000
bx !
bx ,
0%
1'
b101101011001001 &
b101101011001001 +
b1101111 $
b1101111 *
b1101111 (
#2225000
b101101011001001 !
b101101011001001 ,
1%
#2230000
0%
0'
#2235000
1%
#2240000
bx !
bx ,
0%
1'
b101101011001010 &
b101101011001010 +
b1110000 $
b1110000 *
b1110000 (
#2245000
b101101011001010 !
b101101011001010 ,
1%
#2250000
0%
0'
#2255000
1%
#2260000
bx !
bx ,
0%
1'
b101101011001011 &
b101101011001011 +
b1110001 $
b1110001 *
b1110001 (
#2265000
b101101011001011 !
b101101011001011 ,
1%
#2270000
0%
0'
#2275000
1%
#2280000
bx !
bx ,
0%
1'
b101101011001100 &
b101101011001100 +
b1110010 $
b1110010 *
b1110010 (
#2285000
b101101011001100 !
b101101011001100 ,
1%
#2290000
0%
0'
#2295000
1%
#2300000
bx !
bx ,
0%
1'
b101101011001101 &
b101101011001101 +
b1110011 $
b1110011 *
b1110011 (
#2305000
b101101011001101 !
b101101011001101 ,
1%
#2310000
0%
0'
#2315000
1%
#2320000
bx !
bx ,
0%
1'
b101101011001110 &
b101101011001110 +
b1110100 $
b1110100 *
b1110100 (
#2325000
b101101011001110 !
b101101011001110 ,
1%
#2330000
0%
0'
#2335000
1%
#2340000
bx !
bx ,
0%
1'
b101101011001111 &
b101101011001111 +
b1110101 $
b1110101 *
b1110101 (
#2345000
b101101011001111 !
b101101011001111 ,
1%
#2350000
0%
0'
#2355000
1%
#2360000
bx !
bx ,
0%
1'
b101101011010000 &
b101101011010000 +
b1110110 $
b1110110 *
b1110110 (
#2365000
b101101011010000 !
b101101011010000 ,
1%
#2370000
0%
0'
#2375000
1%
#2380000
bx !
bx ,
0%
1'
b101101011010001 &
b101101011010001 +
b1110111 $
b1110111 *
b1110111 (
#2385000
b101101011010001 !
b101101011010001 ,
1%
#2390000
0%
0'
#2395000
1%
#2400000
bx !
bx ,
0%
1'
b101101011010010 &
b101101011010010 +
b1111000 $
b1111000 *
b1111000 (
#2405000
b101101011010010 !
b101101011010010 ,
1%
#2410000
0%
0'
#2415000
1%
#2420000
bx !
bx ,
0%
1'
b101101011010011 &
b101101011010011 +
b1111001 $
b1111001 *
b1111001 (
#2425000
b101101011010011 !
b101101011010011 ,
1%
#2430000
0%
0'
#2435000
1%
#2440000
bx !
bx ,
0%
1'
b101101011010100 &
b101101011010100 +
b1111010 $
b1111010 *
b1111010 (
#2445000
b101101011010100 !
b101101011010100 ,
1%
#2450000
0%
0'
#2455000
1%
#2460000
bx !
bx ,
0%
1'
b101101011010101 &
b101101011010101 +
b1111011 $
b1111011 *
b1111011 (
#2465000
b101101011010101 !
b101101011010101 ,
1%
#2470000
0%
0'
#2475000
1%
#2480000
bx !
bx ,
0%
1'
b101101011010110 &
b101101011010110 +
b1111100 $
b1111100 *
b1111100 (
#2485000
b101101011010110 !
b101101011010110 ,
1%
#2490000
0%
0'
#2495000
1%
#2500000
bx !
bx ,
0%
1'
b101101011010111 &
b101101011010111 +
b1111101 $
b1111101 *
b1111101 (
#2505000
b101101011010111 !
b101101011010111 ,
1%
#2510000
0%
0'
#2515000
1%
#2520000
bx !
bx ,
0%
1'
b101101011011000 &
b101101011011000 +
b1111110 $
b1111110 *
b1111110 (
#2525000
b101101011011000 !
b101101011011000 ,
1%
#2530000
0%
0'
#2535000
1%
#2540000
bx !
bx ,
0%
1'
b101101011011001 &
b101101011011001 +
b1111111 $
b1111111 *
b1111111 (
#2545000
b101101011011001 !
b101101011011001 ,
1%
#2550000
0%
0'
#2555000
1%
#2560000
bx !
bx ,
0%
1'
b101101011011010 &
b101101011011010 +
b10000000 $
b10000000 *
b10000000 (
#2565000
b101101011011010 !
b101101011011010 ,
1%
#2570000
0%
0'
#2575000
1%
#2580000
bx !
bx ,
0%
1'
b101101011011011 &
b101101011011011 +
b10000001 $
b10000001 *
b10000001 (
#2585000
b101101011011011 !
b101101011011011 ,
1%
#2590000
0%
0'
#2595000
1%
#2600000
bx !
bx ,
0%
1'
b101101011011100 &
b101101011011100 +
b10000010 $
b10000010 *
b10000010 (
#2605000
b101101011011100 !
b101101011011100 ,
1%
#2610000
0%
0'
#2615000
1%
