Project-01/Mux4way16/Mux4way16.v
module mux4way16(
    input [15:0] a, b, c, d,
    input [1:0] sel,
    output [15:0] out
);

assign out = (sel == 2'b00) ? a :
            (sel == 2'b01) ? b :
            (sel == 2'b10) ? c :
            (sel == 2'b11) ? d : 16'bx;

endmodule

Mux4way16/Mux4way16_tb.v
`timescale 1ns / 1ps

module tb_mux4way16;

    // Inputs
    reg [15:0] a, b, c, d;
    reg [1:0] sel;

    // Output
    wire [15:0] out;

    // Instantiate the multiplexer
    mux4way16 uut (
        .a(a),
        .b(b),
        .c(c),
        .d(d),
        .sel(sel),
        .out(out)
    );

    // File for output
    integer file;

    initial begin
        $dumpfile("Mux4way16.vcd");
        $dumpvars(0, tb_mux4way16);
        // Open the output file
        file = $fopen("Mux4way16.out", "w");

        // Write the header
        $fwrite(file, "|        a         |        b         |        c         |        d         | sel  |       out        |\n");

        // Test cases
        test_case(16'b0000000000000000, 16'b0000000000000000, 16'b0000000000000000, 16'b0000000000000000, 2'b00);
        test_case(16'b0000000000000000, 16'b0000000000000000, 16'b0000000000000000, 16'b0000000000000000, 2'b01);
        test_case(16'b0000000000000000, 16'b0000000000000000, 16'b0000000000000000, 16'b0000000000000000, 2'b10);
        test_case(16'b0000000000000000, 16'b0000000000000000, 16'b0000000000000000, 16'b0000000000000000, 2'b11);
        test_case(16'b0001001000110100, 16'b1001100001110110, 16'b1010101010101010, 16'b0101010101010101, 2'b00);
        test_case(16'b0001001000110100, 16'b1001100001110110, 16'b1010101010101010, 16'b0101010101010101, 2'b01);
        test_case(16'b0001001000110100, 16'b1001100001110110, 16'b1010101010101010, 16'b0101010101010101, 2'b10);
        test_case(16'b0001001000110100, 16'b1001100001110110, 16'b1010101010101010, 16'b0101010101010101, 2'b11);

        // Close the output file
        $fclose(file);
        $finish;
    end

    // Task to apply inputs and write output
    task test_case(input [15:0] a_input, input [15:0] b_input, input [15:0] c_input, input [15:0] d_input, input [1:0] sel_input);
        begin
            // Assign inputs
            a = a_input;
            b = b_input;
            c = c_input;
            d = d_input;
            sel = sel_input;

            // Wait for a time unit for the output to stabilize
            #10;

            // Write the results to the file
            $fwrite(file, "| %016b | %016b | %016b | %016b |  %02b  | %016b |\n", a, b, c, d, sel, out);
        end
    endtask

endmodule

Project-01/Mux4way16/Mux4way16.vcd
$date
	Thu Aug 08 23:45:12 2024
$end
$version
	Icarus Verilog
$end
$timescale
	1ps
$end
$scope module tb_mux4way16 $end
$var wire 16 ! out [15:0] $end
$var reg 16 " a [15:0] $end
$var reg 16 # b [15:0] $end
$var reg 16 $ c [15:0] $end
$var reg 16 % d [15:0] $end
$var reg 2 & sel [1:0] $end
$var integer 32 ' file [31:0] $end
$scope module uut $end
$var wire 16 ( a [15:0] $end
$var wire 16 ) b [15:0] $end
$var wire 16 * c [15:0] $end
$var wire 16 + d [15:0] $end
$var wire 2 , sel [1:0] $end
$var wire 16 - out [15:0] $end
$upscope $end
$scope task test_case $end
$var reg 16 . a_input [15:0] $end
$var reg 16 / b_input [15:0] $end
$var reg 16 0 c_input [15:0] $end
$var reg 16 1 d_input [15:0] $end
$var reg 2 2 sel_input [1:0] $end
$upscope $end
$upscope $end
$enddefinitions $end
$comment Show the parameter values. $end
$dumpall
$end
#0
$dumpvars
b0 2
b0 1
b0 0
b0 /
b0 .
b0 -
b0 ,
b0 +
b0 *
b0 )
b0 (
b10000000000000000000000000000011 '
b0 &
b0 %
b0 $
b0 #
b0 "
b0 !
$end
#10000
b1 &
b1 ,
b1 2
#20000
b10 &
b10 ,
b10 2
#30000
b11 &
b11 ,
b11 2
#40000
b1001000110100 !
b1001000110100 -
b0 &
b0 ,
b101010101010101 %
b101010101010101 +
b1010101010101010 $
b1010101010101010 *
b1001100001110110 #
b1001100001110110 )
b1001000110100 "
b1001000110100 (
b0 2
b101010101010101 1
b1010101010101010 0
b1001100001110110 /
b1001000110100 .
#50000
b1001100001110110 !
b1001100001110110 -
b1 &
b1 ,
b1 2
#60000
b1010101010101010 !
b1010101010101010 -
b10 &
b10 ,
b10 2
#70000
b101010101010101 !
b101010101010101 -
b11 &
b11 ,
b11 2
