Project-02/FullAdder/FullAdder.v
module full_adder (
    input wire A,        // First input bit
    input wire B,        // Second input bit
    input wire Cin,      // Carry input
    output wire Sum,     // Sum output
    output wire Cout     // Carry output
);

// Logic for Sum and Carry
assign Sum = A ^ B ^ Cin;     // Sum is the XOR of A, B, and Cin
assign Cout = (A & B) | (Cin & (A ^ B)); // Carry is generated from A and B or Cin with the XOR of A and B

endmodule

Project-02/FullAdder/FullAdder_tb.v
module test_full_adder;

// Declare inputs and outputs
reg A;
reg B;
reg Cin;
wire Sum;
wire Cout;

// Instantiate the full adder
full_adder fa (
    .A(A),
    .B(B),
    .Cin(Cin),
    .Sum(Sum),
    .Cout(Cout)
);

// File descriptor for output
integer file;

// Test procedure
initial begin
    $dumpfile("FullAdder.vcd");
    $dumpvars(0, test_full_adder);
    // Open the output file
    file = $fopen("FullAdder.out", "w");
    
    // Print the table header to the file
    $fdisplay(file, "|   A   |   B   |  Cin  |  Sum  | Cout |");
    
    // Test all combinations of A, B, and Cin
    A = 0; B = 0; Cin = 0; #10;
    $fdisplay(file, "|   %b   |   %b   |   %b   |   %b   |   %b  |", A, B, Cin, Sum, Cout);
    
    A = 0; B = 0; Cin = 1; #10;
    $fdisplay(file, "|   %b   |   %b   |   %b   |   %b   |   %b  |", A, B, Cin, Sum, Cout);
    
    A = 0; B = 1; Cin = 0; #10;
    $fdisplay(file, "|   %b   |   %b   |   %b   |   %b   |   %b  |", A, B, Cin, Sum, Cout);
    
    A = 0; B = 1; Cin = 1; #10;
    $fdisplay(file, "|   %b   |   %b   |   %b   |   %b   |   %b  |", A, B, Cin, Sum, Cout);
    
    A = 1; B = 0; Cin = 0; #10;
    $fdisplay(file, "|   %b   |   %b   |   %b   |   %b   |   %b  |", A, B, Cin, Sum, Cout);
    
    A = 1; B = 0; Cin = 1; #10;
    $fdisplay(file, "|   %b   |   %b   |   %b   |   %b   |   %b  |", A, B, Cin, Sum, Cout);
    
    A = 1; B = 1; Cin = 0; #10;
    $fdisplay(file, "|   %b   |   %b   |   %b   |   %b   |   %b  |", A, B, Cin, Sum, Cout);
    
    A = 1; B = 1; Cin = 1; #10;
    $fdisplay(file, "|   %b   |   %b   |   %b   |   %b   |   %b  |", A, B, Cin, Sum, Cout);
    
    // Close the output file
    $fclose(file);
    
    $finish; // End the simulation
end

endmodule

Project-02/FullAdder/FullAdder.vcd
$date
	Fri Aug 09 21:55:03 2024
$end
$version
	Icarus Verilog
$end
$timescale
	1s
$end
$scope module test_full_adder $end
$var wire 1 ! Sum $end
$var wire 1 " Cout $end
$var reg 1 # A $end
$var reg 1 $ B $end
$var reg 1 % Cin $end
$var integer 32 & file [31:0] $end
$scope module fa $end
$var wire 1 # A $end
$var wire 1 $ B $end
$var wire 1 % Cin $end
$var wire 1 " Cout $end
$var wire 1 ! Sum $end
$upscope $end
$upscope $end
$enddefinitions $end
$comment Show the parameter values. $end
$dumpall
$end
#0
$dumpvars
b10000000000000000000000000000011 &
0%
0$
0#
0"
0!
$end
#10
1!
1%
#20
0%
1$
#30
1"
0!
1%
#40
0"
1!
0%
0$
1#
#50
1"
0!
1%
#60
0%
1$
#70
1!
1%
