Project-05/HackCPU/ALU.v
// ALU Module
module ALU (
    input wire [15:0] A,
    input wire [15:0] D,
    input wire [15:0] instruction,
    output reg [15:0] result,
    output reg zero
);
    always @(*) begin
        case (instruction[11:8]) // Example ALU operation decoder
            4'b0000: result = A + D; // Example: ADD
            4'b0001: result = A - D; // Example: SUB
            // Add more operations as needed
            default: result = 16'b0; // Default case
        endcase

        zero = (result == 16'b0); // Set zero flag if result is zero
    end
endmodule

Project-05/HackCPU/HackCPU.v
module HackCPU (
    input wire clk,
    input wire reset,
    input wire [15:0] inM,          // Input from memory
    input wire [15:0] instruction,   // Current instruction
    output reg [15:0] outM,          // Output to memory
    output reg [15:0] addressM,      // Address to write to memory
    output reg writeM,               // Write enable signal
    output reg [15:0] pc             // Program counter
);

    // Registers A and D
    reg [15:0] A; // Register A
    reg [15:0] D; // Register D

    // ALU operation
    wire [15:0] aluResult;
    wire aluZero; // ALU zero flag

    // ALU implementation
    ALU alu (
        .A(A),
        .D(D),
        .instruction(instruction),
        .result(aluResult),
        .zero(aluZero)
    );

    // Program Counter Logic
    always @(posedge clk or posedge reset) begin
        if (reset) begin
            pc <= 16'b0; // Reset PC to 0
            A <= 16'b0;  // Reset A to 0
            D <= 16'b0;  // Reset D to 0
        end else begin
            pc <= pc + 1; // Increment PC for simple instructions
        end
    end

    // Main CPU Logic
    always @(posedge clk) begin
        // Default outputs
        outM <= 16'b0;
        addressM <= 16'b0;
        writeM <= 1'b0;

        // Decode instruction on clock edge
        case (instruction[15:12]) // Decode instruction
            4'b0000: begin // A-instruction
                A <= instruction[11:0]; // Load value into A
            end
            4'b0001: begin // C-instruction
                D <= aluResult; // Store ALU result in D
                outM <= D; // Prepare output to memory
                addressM <= A; // Address for memory write
                writeM <= 1'b1; // Enable memory write
            end
            // Additional instruction cases can be added here
            default: begin
                // Handle other instructions
            end
        endcase
    end

endmodule

Project-05/HackCPU/HackCPU_tb.v
`timescale 1ns / 1ps

module tb_HackCPU;

    // Parameters
    parameter CLK_PERIOD = 10; // Clock period in nanoseconds

    // Inputs
    reg clk;                     // Clock signal
    reg reset;                   // Reset signal
    reg [15:0] inM;              // Input from memory
    reg [15:0] instruction;      // Current instruction

    // Outputs
    wire [15:0] outM;            // Output to memory
    wire [15:0] addressM;        // Address to write to memory
    wire writeM;                 // Write enable signal
    wire [15:0] pc;              // Program counter

    // Instantiate the HackCPU
    HackCPU uut (
        .clk(clk),
        .reset(reset),
        .inM(inM),
        .instruction(instruction),
        .outM(outM),
        .addressM(addressM),
        .writeM(writeM),
        .pc(pc)
    );

    // Clock generation
    initial begin
        clk = 0;
        forever #(CLK_PERIOD / 2) clk = ~clk; // Toggle clock every half period
    end

    // Declare output file as an integer
    integer output_file;

    // Test procedure
    initial begin
        // Open output file
        output_file = $fopen("HackCPU.out", "w");
        if (!output_file) begin
            $display("Error opening output file");
            $finish;
        end

        // Open VCD dump file for waveform analysis
        $dumpfile("HackCPU.vcd");
        $dumpvars(0, tb_HackCPU);

        // Reset the CPU
        reset = 1;
        #CLK_PERIOD; // Wait for one clock cycle
        reset = 0;

        // Test Case 1: A-instruction
        instruction = 16'b0000000000000001; // Load 1 into A
        #CLK_PERIOD; // Wait for one clock cycle
        $fwrite(output_file, "PC:%d , A:%d , D:%d , outM:%d , addressM:%d , writeM:%b \n", pc, uut.A, uut.D, outM, addressM, writeM);
        $display("Executed A-instruction: PC: %d, A: %d, D: %d, outM: %d, addressM: %d, writeM: %b", pc, uut.A, uut.D, outM, addressM, writeM);

        // Test Case 2: C-instruction (D = A + D)
        uut.D = 16'd5; // Set D to 5 before executing the instruction
        instruction = 16'b0001000000000000; // C-instruction: D = A + D
        #CLK_PERIOD; // Wait for one clock cycle
        $fwrite(output_file, "PC: %d, A: %d, D: %d, outM: %d, addressM: %d, writeM: %b\n", pc, uut.A, uut.D, outM, addressM, writeM);
        $display("Executed C-instruction: PC: %d, A: %d, D: %d, outM: %d, addressM: %d, writeM: %b", pc, uut.A, uut.D, outM, addressM, writeM);

        // Test Case 3: Write to Memory
        instruction = 16'b0001000000000001; // C-instruction: Write D to memory at address A
        #CLK_PERIOD; // Wait for one clock cycle
        $fwrite(output_file, "PC: %d, A: %d, D: %d, outM: %d, addressM: %d, writeM: %b\n", pc, uut.A, uut.D, outM, addressM, writeM);
        $display("Executed Write to Memory: PC: %d, A: %d, D: %d, outM: %d, addressM: %d, writeM: %b", pc, uut.A, uut.D, outM, addressM, writeM);

        // Test Case 4: Reset the CPU
        reset = 1;
        #CLK_PERIOD; // Wait for one clock cycle
        reset = 0;

        // Test Case 5: Another A-instruction
        instruction = 16'b0000000000000010; // Load 2 into A
        #CLK_PERIOD; // Wait for one clock cycle
        $fwrite(output_file, "PC: %d, A: %d, D: %d, outM: %d, addressM: %d, writeM: %b\n", pc, uut.A, uut.D, outM, addressM, writeM);
        $display("Executed A-instruction: PC: %d, A: %d, D: %d, outM: %d, addressM: %d, writeM: %b", pc, uut.A, uut.D, outM, addressM, writeM);

        // Close output file
        $fclose(output_file);

        // Finish simulation
        $finish;
    end

endmodule

Project-05/HackCPU/HackCPU.vcd
$date
	Tue Aug 27 19:41:44 2024
$end
$version
	Icarus Verilog
$end
$timescale
	1ps
$end
$scope module tb_HackCPU $end
$var wire 1 ! writeM $end
$var wire 16 " pc [15:0] $end
$var wire 16 # outM [15:0] $end
$var wire 16 $ addressM [15:0] $end
$var parameter 32 % CLK_PERIOD $end
$var reg 1 & clk $end
$var reg 16 ' inM [15:0] $end
$var reg 16 ( instruction [15:0] $end
$var reg 1 ) reset $end
$var integer 32 * output_file [31:0] $end
$scope module uut $end
$var wire 1 & clk $end
$var wire 16 + inM [15:0] $end
$var wire 16 , instruction [15:0] $end
$var wire 1 ) reset $end
$var wire 1 - aluZero $end
$var wire 16 . aluResult [15:0] $end
$var reg 16 / A [15:0] $end
$var reg 16 0 D [15:0] $end
$var reg 16 1 addressM [15:0] $end
$var reg 16 2 outM [15:0] $end
$var reg 16 3 pc [15:0] $end
$var reg 1 ! writeM $end
$scope module alu $end
$var wire 16 4 A [15:0] $end
$var wire 16 5 D [15:0] $end
$var wire 16 6 instruction [15:0] $end
$var reg 16 7 result [15:0] $end
$var reg 1 - zero $end
$upscope $end
$upscope $end
$upscope $end
$enddefinitions $end
$comment Show the parameter values. $end
$dumpall
b1010 %
$end
#0
$dumpvars
b0 7
bx 6
b0 5
b0 4
b0 3
bx 2
bx 1
b0 0
b0 /
b0 .
1-
bx ,
bx +
b10000000000000000000000000000011 *
1)
bx (
bx '
0&
bx $
bx #
b0 "
x!
$end
#5000
0!
b0 $
b0 1
b0 #
b0 2
1&
#10000
0&
b1 (
b1 ,
b1 6
0)
#15000
0-
b1 .
b1 7
b1 /
b1 4
b1 "
b1 3
1&
#20000
b110 .
b110 7
0&
b1000000000000 (
b1000000000000 ,
b1000000000000 6
b101 0
b101 5
#25000
b111 .
b111 7
1!
b1 $
b1 1
b101 #
b101 2
b110 0
b110 5
b10 "
b10 3
1&
#30000
0&
b1000000000001 (
b1000000000001 ,
b1000000000001 6
#35000
b1000 .
b1000 7
b111 0
b111 5
1!
b1 $
b1 1
b110 #
b110 2
b11 "
b11 3
1&
#40000
1-
b0 .
b0 7
b0 0
b0 5
b0 /
b0 4
b0 "
b0 3
0&
1)
#45000
1!
b0 $
b0 1
b0 #
b0 2
1&
#50000
0&
b10 (
b10 ,
b10 6
0)
#55000
0-
b10 .
b10 7
b10 /
b10 4
0!
b1 "
b1 3
1&
