Project-03/Register16/Register16.v

module reg16(
    input clk,       // Clock input
    input rst,       // Reset input
    input ld,        // Load signal
    input [15:0] d,  // 16-bit input data
    output reg [15:0] q // 16-bit output data
);

    always @(posedge clk or posedge rst) begin
        if (rst) begin
            q <= 16'b0; // Reset the register to 0
        end else if (ld) begin
            q <= d; // Load the input data into the register
        end
    end

endmodule

Project-03/Register16/Register16_tb.v
`timescale 1ns / 1ps

module reg16_tb;

    // Inputs
    reg clk;
    reg rst;
    reg ld;
    reg [15:0] d;

    // Outputs
    wire [15:0] q;

    // Instantiate the register module
    reg16 uut (
        .clk(clk),
        .rst(rst),
        .ld(ld),
        .d(d),
        .q(q)
    );

    integer output_file;
    integer i;
    reg [15:0] test_inputs [0:21]; // Array to hold 22 test inputs



    initial begin
        // Open output file
        output_file = $fopen("Register16.out", "w");
        $dumpfile("Register16.vcd");
        $dumpvars(0, reg16_tb);
        
        // Write the header
        $fwrite(output_file, "| time |   in   | load |  out   |\n");

        // Initialize inputs
        clk = 0;
        rst = 0;
        ld = 0;
        d = 16'b0;

        // Initial state
        #1;
        $fwrite(output_file, "|  %0d+  | %d  |  %d  | %d  |\n", $time, d, ld, q);

        // Reset the register
        #1 rst = 1; // Assert reset
        #1 rst = 0; // Deassert reset

        // Define test inputs
        test_inputs[0]  = 16'h0000;     // 0
        test_inputs[1]  = 16'hFFFF;     // -32123
        test_inputs[2]  = 16'h1234;     // 11111
        test_inputs[3]  = 16'h3039;     // 12345
        test_inputs[4]  = 16'h0001;     // 1
        test_inputs[5]  = 16'h0002;     // 2
        test_inputs[6]  = 16'h0004;     // 4
        test_inputs[7]  = 16'h0008;     // 8
        test_inputs[8]  = 16'h0010;     // 16
        test_inputs[9]  = 16'h0020;     // 32
        test_inputs[10] = 16'h0040;     // 64
        test_inputs[11] = 16'h0080;     // 128
        test_inputs[12] = 16'h0100;     // 256
        test_inputs[13] = 16'hFFFE;     // -2
        test_inputs[14] = 16'hFFFD;     // -3
        test_inputs[15] = 16'hFF9B;     // -65
        test_inputs[16] = 16'hFFFB;     // -5
        test_inputs[17] = 16'hFFF7;     // -9
        test_inputs[18] = 16'h80A3;     // -129
        test_inputs[19] = 16'hA9B5;     // -643
        test_inputs[20] = 16'hFFCC;     // -54
        test_inputs[21] = 16'hFFB8;     // -74

        // Loop through each test input and manage time output
        for (i = 0; i < 22; i = i + 1) begin
            // Load data into the register
            #1 d = test_inputs[i]; // Load test input
            #1 ld = 1; // Assert load
            $fwrite(output_file, "|  %0d+  | %d  |  %d  | %d  |\n", $time, d, ld, q);

            #1;
            #1 ld = 0; // Deassert load
            #1; // Wait for one clock cycle
            
            // Print output for current time
            #1; // Wait for one clock cycle
            
            // Print output for next time
            $fwrite(output_file, "|  %0d   | %d  |  %d  | %d  |\n", $time, d, ld, q);
        end

        // End the simulation
        #10 $fclose(output_file);
        #10 $finish;
    end

    // Clock generation
    always #5 clk = ~clk;

endmodule

Project-03/Register16/Register16.vcd
$date
	Sat Aug 17 21:45:40 2024
$end
$version
	Icarus Verilog
$end
$timescale
	1ps
$end
$scope module reg16_tb $end
$var wire 16 ! q [15:0] $end
$var reg 1 " clk $end
$var reg 16 # d [15:0] $end
$var reg 1 $ ld $end
$var reg 1 % rst $end
$var integer 32 & i [31:0] $end
$var integer 32 ' output_file [31:0] $end
$scope module uut $end
$var wire 1 " clk $end
$var wire 16 ( d [15:0] $end
$var wire 1 $ ld $end
$var wire 1 % rst $end
$var reg 16 ) q [15:0] $end
$upscope $end
$upscope $end
$enddefinitions $end
$comment Show the parameter values. $end
$dumpall
$end
#0
$dumpvars
bx )
b0 (
b10000000000000000000000000000011 '
bx &
0%
0$
b0 #
0"
bx !
$end
#2000
b0 !
b0 )
1%
#3000
b0 &
0%
#5000
1$
1"
#7000
0$
#9000
b1 &
#10000
b1111111111111111 #
b1111111111111111 (
0"
#11000
1$
#13000
0$
#15000
b10 &
1"
#16000
b1001000110100 #
b1001000110100 (
#17000
1$
#19000
0$
#20000
0"
#21000
b11 &
#22000
b11000000111001 #
b11000000111001 (
#23000
1$
#25000
0$
1"
#27000
b100 &
#28000
b1 #
b1 (
#29000
1$
#30000
0"
#31000
0$
#33000
b101 &
#34000
b10 #
b10 (
#35000
b10 !
b10 )
1$
1"
#37000
0$
#39000
b110 &
#40000
b100 #
b100 (
0"
#41000
1$
#43000
0$
#45000
b111 &
1"
#46000
b1000 #
b1000 (
#47000
1$
#49000
0$
#50000
0"
#51000
b1000 &
#52000
b10000 #
b10000 (
#53000
1$
#55000
0$
1"
#57000
b1001 &
#58000
b100000 #
b100000 (
#59000
1$
#60000
0"
#61000
0$
#63000
b1010 &
#64000
b1000000 #
b1000000 (
#65000
b1000000 !
b1000000 )
1$
1"
#67000
0$
#69000
b1011 &
#70000
b10000000 #
b10000000 (
0"
#71000
1$
#73000
0$
#75000
b1100 &
1"
#76000
b100000000 #
b100000000 (
#77000
1$
#79000
0$
#80000
0"
#81000
b1101 &
#82000
b1111111111111110 #
b1111111111111110 (
#83000
1$
#85000
0$
1"
#87000
b1110 &
#88000
b1111111111111101 #
b1111111111111101 (
#89000
1$
#90000
0"
#91000
0$
#93000
b1111 &
#94000
b1111111110011011 #
b1111111110011011 (
#95000
b1111111110011011 !
b1111111110011011 )
1$
1"
#97000
0$
#99000
b10000 &
#100000
b1111111111111011 #
b1111111111111011 (
0"
#101000
1$
#103000
0$
#105000
b10001 &
1"
#106000
b1111111111110111 #
b1111111111110111 (
#107000
1$
#109000
0$
#110000
0"
#111000
b10010 &
#112000
b1000000010100011 #
b1000000010100011 (
#113000
1$
#115000
0$
1"
#117000
b10011 &
#118000
b1010100110110101 #
b1010100110110101 (
#119000
1$
#120000
0"
#121000
0$
#123000
b10100 &
#124000
b1111111111001100 #
b1111111111001100 (
#125000
b1111111111001100 !
b1111111111001100 )
1$
1"
#127000
0$
#129000
b10101 &
#130000
b1111111110111000 #
b1111111110111000 (
0"
#131000
1$
#133000
0$
#135000
b10110 &
1"
