Project-01/Mux/Mux.v
module Mux (
    input wire a,
    input wire b,
    input wire sel,

    output wire out
);

    assign out = (sel) ? b : a;
    
endmodule

Mux/Mux_tb.v
`timescale 1ns / 1ps

module Mux_tb;

    reg a;      // Declare input a
    reg b;      // Declare input b
    reg sel;    // Declare select signal

    wire out;   // Declare output

    // Instantiate the Mux module
    Mux uut (
        .a(a),
        .b(b),
        .sel(sel),
        .out(out)
    );

    integer output_file;

    initial begin
        $dumpfile("Mux.vcd");
        $dumpvars(0, Mux_tb);

        // Open output file for writing results
        output_file = $fopen("Mux.out", "w");
        $fwrite(output_file, "|   a   |   b   |  sel  |  out  |\n");

        // Test all combinations of a, b, and sel
        // Test case 1: A = 0, B = 0
        a = 0; b = 0; sel = 0; #10; // Wait for 10 time units
        $fwrite(output_file, "|   %b   |   %b   |   %b   |   %b   |\n", a, b, sel, out);

        sel = 1; #10; // Wait for 10 time units
        $fwrite(output_file, "|   %b   |   %b   |   %b   |   %b   |\n", a, b, sel, out);

        // Test case 2: A = 0, B = 1
        a = 0; b = 1; sel = 0; #10; // Wait for 10 time units
        $fwrite(output_file, "|   %b   |   %b   |   %b   |   %b   |\n", a, b, sel, out);

        sel = 1; #10; // Wait for 10 time units
        $fwrite(output_file, "|   %b   |   %b   |   %b   |   %b   |\n", a, b, sel, out);

        // Test case 3: A = 1, B = 0
        a = 1; b = 0; sel = 0; #10; // Wait for 10 time units
        $fwrite(output_file, "|   %b   |   %b   |   %b   |   %b   |\n", a, b, sel, out);

        sel = 1; #10; // Wait for 10 time units
        $fwrite(output_file, "|   %b   |   %b   |   %b   |   %b   |\n", a, b, sel, out);

        // Test case 4: A = 1, B = 1
        a = 1; b = 1; sel = 0; #10; // Wait for 10 time units
        $fwrite(output_file, "|   %b   |   %b   |   %b   |   %b   |\n", a, b, sel, out);

        sel = 1; #10; // Wait for 10 time units
        $fwrite(output_file, "|   %b   |   %b   |   %b   |   %b   |\n", a, b, sel, out);

        // Close the output file and finish the simulation
        $fclose(output_file);
        $finish;
    end

endmodule

Project-01/Mux/Mux.vcd
$date
	Sun Aug 04 23:15:38 2024
$end
$version
	Icarus Verilog
$end
$timescale
	1ps
$end
$scope module Mux_tb $end
$var wire 1 ! out $end
$var reg 1 " a $end
$var reg 1 # b $end
$var reg 1 $ sel $end
$var integer 32 % output_file [31:0] $end
$scope module uut $end
$var wire 1 " a $end
$var wire 1 # b $end
$var wire 1 $ sel $end
$var wire 1 ! out $end
$upscope $end
$upscope $end
$enddefinitions $end
$comment Show the parameter values. $end
$dumpall
$end
#0
$dumpvars
b10000000000000000000000000000011 %
0$
0#
0"
0!
$end
#10000
1$
#20000
0$
1#
#30000
1!
1$
#40000
0$
0#
1"
#50000
0!
1$
#60000
1!
0$
1#
#70000
1$
