Project-05/Memory/Keyboard.v
// Keyboard Module Implementation
module Keyboard (
    output reg [15:0] out      // Output data
);
    initial begin
        out = 16'hFFFF; // Simulate a key press as a constant output
    end
endmodule

Project-05/Memory/Screen.v
module Screen (
    input [15:0] in,           // Input data
    input load,                // Load signal
    input [12:0] address,      // Address input for screen memory
    output reg [15:0] out      // Output data
);
    reg [15:0] memory [0:8191]; // Screen memory (8K words)

    // Handle load operation
    always @(posedge load) begin
        if (load) begin
            memory[address] <= in; // Load data into screen memory
        end
    end

    // Handle read operation
    always @(*) begin
        out = memory[address]; // Output the value from screen memory
    end
endmodule

Project-05/Memory/RAM16k.v
// RAM16K.v
module RAM16K(input [15:0] in, input load, input [13:0] address, output reg [15:0] out);
    // Example memory array, not the actual implementation
    reg [15:0] memory [0:16383];  // 16K words of memory
    always @(*) begin
        if (load) begin
            memory[address] = in;
        end
        out = memory[address];
    end
endmodule

Project-05/Memory/Memory.v
module Memory (
    input [15:0] in,           // Input data
    input load,                // Load signal
    input [14:0] address,      // Address input (15 bits)
    output reg [15:0] out      // Output data
);

    // Internal signals
    wire [15:0] ram_out;       // Output from RAM
    wire [15:0] screen_out;    // Output from Screen
    wire [15:0] keyboard_out;  // Output from Keyboard
    wire ram_load;             // Load signal for RAM
    wire screen_load;          // Load signal for Screen
    wire keyboard_load;        // Load signal for Keyboard
    wire [13:0] ram_address;   // Address for RAM
    wire [12:0] screen_address; // Address for Screen

    // Address decoding
    assign ram_load = load & (address[14] == 1'b0); // Load to RAM if address is in RAM space
    assign screen_load = load & (address >= 15'h4000) & (address < 15'h6000); // Load to Screen
    assign keyboard_load = address == 15'h6000; // Load to Keyboard at address 0x6000

    assign ram_address = address[13:0]; // RAM address (0 to 16383)
    assign screen_address = address[12:0]; // Screen address (0 to 8191)

    // RAM instantiation
    RAM16K ram (
        .in(in),
        .load(ram_load),
        .address(ram_address),
        .out(ram_out)
    );

    // Screen and Keyboard instantiation
    Screen screen (
        .in(in),
        .load(screen_load),
        .address(screen_address),
        .out(screen_out)
    );

    Keyboard keyboard (
        .out(keyboard_out)
    );

    // Output logic
    always @(*) begin
        if (address > 15'h6000) begin
            out = 16'b0; // Invalid access
        end else if (address >= 15'h4000 && address < 15'h6000) begin
            out = screen_out; // Access Screen
        end else if (address == 15'h6000) begin
            out = keyboard_out; // Access Keyboard
        end else begin
            out = ram_out; // Access RAM
        end
    end

endmodule

Project-05/Memory/Memory_tb.v
`timescale 1ns / 1ps


module tb_Memory;

    // Testbench signals
    reg [15:0] in;              // Input data
    reg load;                   // Load signal
    reg [14:0] address;         // Address input
    wire [15:0] out;            // Output data

    integer log_file;           // Log file descriptor
    integer i;                  // Loop variable

    // Instantiate the Memory module
    Memory memory (
        .in(in),
        .load(load),
        .address(address),
        .out(out)
    );

    // Open output file and VCD file
    initial begin
        $dumpfile("Memory.vcd");
        $dumpvars(0, tb_Memory);

        // Open output file for logging
        log_file = $fopen("Memory.out", "w");
        if (log_file == 0) begin
            $display("Error: Could not open Memory.out for writing.");
            $finish;
        end
    end

    // Test procedure
    initial begin
        // Initialize inputs
        in = 16'b0;
        load = 0;
        address = 15'b0;

        // Test RAM functionality using a loop
        $display("Testing RAM functionality...");
        for (i = 0; i < 16; i = i + 1) begin
            address = i; // Test addresses 0x0000 to 0x000F
            in = 16'hA0 + i; // Example data (0xA0 to 0xAF)
            load = 1; // Enable loading
            #10; // Wait for a short period
            load = 0; // Disable loading
            #10; // Wait for a short period

            // Read back from RAM
            address = i;
            #10;
            if (out !== in) begin
                $display("Error: Expected 0x%h, got %h at address 0x%h", in, out, address);
                $fwrite(log_file, "Error: Expected 0x%h, got %h at address 0x%h\n", in, out, address);
            end else begin
                $display("RAM Test Passed: Read 0x%h from address 0x%h", out, address);
                $fwrite(log_file, "RAM Test Passed: Read 0x%h from address 0x%h\n", out, address);
            end
        end

        // Test Screen functionality using a loop
        $display("Testing Screen functionality...");
        for (integer i = 0; i < 16; i = i + 1) begin
                address = 15'h4000 + i; // Test addresses 0x4000 to 0x400F
                in = 16'hB0 + i; // Example data (0xB0 to 0xBF)
                load = 1; // Enable loading
                #10; // Wait for a short period
                load = 0; // Disable loading
                #20; // Wait for a short period

            // Read back from Screen
            address = 15'h4000 + i;
            #10;
            if (out !== in) begin
                $display("Error: Expected 0x%h, got %h at address 0x%h", in, out, address);
                $fwrite(log_file, "Error: Expected 0x%h, got %h at address 0x%h\n", in, out, address);
            end else begin
                $display("Screen Test Passed: Read 0x%h from address 0x%h", out, address);
                $fwrite(log_file, "Screen Test Passed: Read 0x%h from address 0x%h\n", out, address);
            end
        end

        // Test Keyboard functionality
        $display("Testing Keyboard functionality...");
        address = 15'h6000; // Simulate reading from Keyboard address 0x6000
        #10; // Wait for a short period
        if (out !== 16'hFFFF) begin
            $display("Error: Expected 0xFFFF, got %h", out);
            $fwrite(log_file, "Error: Expected 0xFFFF, got %h\n", out);
        end else begin
            $display("Keyboard Test Passed: Read 0x%h from address 0x%h", out, address);
            $fwrite(log_file, "Keyboard Test Passed: Read 0x%h from address 0x%h\n", out, address);
        end


        

        // Test invalid address access
        $display("Testing invalid address access...");
        address = 15'h7000; // Invalid address
        #10; // Wait for a short period
        if (out !== 16'b0) begin
            $display("Error: Expected 0x0000, got %h", out);
            $fwrite(log_file, "Error: Expected 0x0000, got %h\n", out);
        end else begin
            $display("Invalid Address Test Passed: Read 0x%h from address 0x%h", out, address);
            $fwrite(log_file, "Invalid Address Test Passed: Read 0x%h from address 0x%h\n", out, address);
        end

        // Close output file
        $fclose(log_file);
        $finish;
    end

endmodule

Project-05/Memory/Memory.vcd
$date
	Mon Aug 26 21:15:36 2024
$end
$version
	Icarus Verilog
$end
$timescale
	1ps
$end
$scope module tb_Memory $end
$var wire 16 ! out [15:0] $end
$var reg 15 " address [14:0] $end
$var reg 16 # in [15:0] $end
$var reg 1 $ load $end
$var integer 32 % i [31:0] $end
$var integer 32 & log_file [31:0] $end
$scope module memory $end
$var wire 15 ' address [14:0] $end
$var wire 16 ( in [15:0] $end
$var wire 1 $ load $end
$var wire 1 ) ram_load $end
$var wire 1 * screen_load $end
$var wire 16 + screen_out [15:0] $end
$var wire 13 , screen_address [12:0] $end
$var wire 16 - ram_out [15:0] $end
$var wire 14 . ram_address [13:0] $end
$var wire 16 / keyboard_out [15:0] $end
$var wire 1 0 keyboard_load $end
$var reg 16 1 out [15:0] $end
$scope module keyboard $end
$var reg 16 2 out [15:0] $end
$upscope $end
$scope module ram $end
$var wire 14 3 address [13:0] $end
$var wire 16 4 in [15:0] $end
$var wire 1 ) load $end
$var reg 16 5 out [15:0] $end
$upscope $end
$scope module screen $end
$var wire 13 6 address [12:0] $end
$var wire 16 7 in [15:0] $end
$var wire 1 * load $end
$var reg 16 8 out [15:0] $end
$upscope $end
$upscope $end
$scope begin $ivl_for_loop0 $end
$var integer 32 9 i [31:0] $end
$upscope $end
$upscope $end
$enddefinitions $end
$comment Show the parameter values. $end
$dumpall
$end
#0
$dumpvars
bx 9
bx 8
b10100000 7
b0 6
b10100000 5
b10100000 4
b0 3
b1111111111111111 2
b10100000 1
00
b1111111111111111 /
b0 .
b10100000 -
b0 ,
bx +
0*
1)
b10100000 (
b0 '
b10000000000000000000000000000011 &
b0 %
1$
b10100000 #
b0 "
b10100000 !
$end
#10000
0)
0$
#30000
b10100001 !
b10100001 1
1)
b10100001 -
b10100001 5
b1 .
b1 3
b1 ,
b1 6
1$
b10100001 #
b10100001 (
b10100001 4
b10100001 7
b1 "
b1 '
b1 %
#40000
0)
0$
#60000
b10100010 !
b10100010 1
1)
b10100010 -
b10100010 5
b10 .
b10 3
b10 ,
b10 6
1$
b10100010 #
b10100010 (
b10100010 4
b10100010 7
b10 "
b10 '
b10 %
#70000
0)
0$
#90000
b10100011 !
b10100011 1
1)
b10100011 -
b10100011 5
b11 .
b11 3
b11 ,
b11 6
1$
b10100011 #
b10100011 (
b10100011 4
b10100011 7
b11 "
b11 '
b11 %
#100000
0)
0$
#120000
b10100100 !
b10100100 1
1)
b10100100 -
b10100100 5
b100 .
b100 3
b100 ,
b100 6
1$
b10100100 #
b10100100 (
b10100100 4
b10100100 7
b100 "
b100 '
b100 %
#130000
0)
0$
#150000
b10100101 !
b10100101 1
1)
b10100101 -
b10100101 5
b101 .
b101 3
b101 ,
b101 6
1$
b10100101 #
b10100101 (
b10100101 4
b10100101 7
b101 "
b101 '
b101 %
#160000
0)
0$
#180000
b10100110 !
b10100110 1
1)
b10100110 -
b10100110 5
b110 .
b110 3
b110 ,
b110 6
1$
b10100110 #
b10100110 (
b10100110 4
b10100110 7
b110 "
b110 '
b110 %
#190000
0)
0$
#210000
b10100111 !
b10100111 1
1)
b10100111 -
b10100111 5
b111 .
b111 3
b111 ,
b111 6
1$
b10100111 #
b10100111 (
b10100111 4
b10100111 7
b111 "
b111 '
b111 %
#220000
0)
0$
#240000
b10101000 !
b10101000 1
1)
b10101000 -
b10101000 5
b1000 .
b1000 3
b1000 ,
b1000 6
1$
b10101000 #
b10101000 (
b10101000 4
b10101000 7
b1000 "
b1000 '
b1000 %
#250000
0)
0$
#270000
b10101001 !
b10101001 1
1)
b10101001 -
b10101001 5
b1001 .
b1001 3
b1001 ,
b1001 6
1$
b10101001 #
b10101001 (
b10101001 4
b10101001 7
b1001 "
b1001 '
b1001 %
#280000
0)
0$
#300000
b10101010 !
b10101010 1
1)
b10101010 -
b10101010 5
b1010 .
b1010 3
b1010 ,
b1010 6
1$
b10101010 #
b10101010 (
b10101010 4
b10101010 7
b1010 "
b1010 '
b1010 %
#310000
0)
0$
#330000
b10101011 !
b10101011 1
1)
b10101011 -
b10101011 5
b1011 .
b1011 3
b1011 ,
b1011 6
1$
b10101011 #
b10101011 (
b10101011 4
b10101011 7
b1011 "
b1011 '
b1011 %
#340000
0)
0$
#360000
b10101100 !
b10101100 1
1)
b10101100 -
b10101100 5
b1100 .
b1100 3
b1100 ,
b1100 6
1$
b10101100 #
b10101100 (
b10101100 4
b10101100 7
b1100 "
b1100 '
b1100 %
#370000
0)
0$
#390000
b10101101 !
b10101101 1
1)
b10101101 -
b10101101 5
b1101 .
b1101 3
b1101 ,
b1101 6
1$
b10101101 #
b10101101 (
b10101101 4
b10101101 7
b1101 "
b1101 '
b1101 %
#400000
0)
0$
#420000
b10101110 !
b10101110 1
1)
b10101110 -
b10101110 5
b1110 .
b1110 3
b1110 ,
b1110 6
1$
b10101110 #
b10101110 (
b10101110 4
b10101110 7
b1110 "
b1110 '
b1110 %
#430000
0)
0$
#450000
b10101111 !
b10101111 1
1)
b10101111 -
b10101111 5
b1111 .
b1111 3
b1111 ,
b1111 6
1$
b10101111 #
b10101111 (
b10101111 4
b10101111 7
b1111 "
b1111 '
b1111 %
#460000
0)
0$
#480000
b10110000 +
b10110000 8
1*
0)
b10110000 -
b10110000 5
b10110000 !
b10110000 1
b0 .
b0 3
b0 ,
b0 6
1$
b10110000 #
b10110000 (
b10110000 4
b10110000 7
b100000000000000 "
b100000000000000 '
b0 9
b10000 %
#490000
0*
0$
#520000
1*
b10110001 !
b10110001 1
b10110001 +
b10110001 8
b10100001 -
b10100001 5
b1 .
b1 3
b1 ,
b1 6
1$
b10110001 #
b10110001 (
b10110001 4
b10110001 7
b100000000000001 "
b100000000000001 '
b1 9
#530000
0*
0$
#560000
1*
b10110010 !
b10110010 1
b10110010 +
b10110010 8
b10100010 -
b10100010 5
b10 .
b10 3
b10 ,
b10 6
1$
b10110010 #
b10110010 (
b10110010 4
b10110010 7
b100000000000010 "
b100000000000010 '
b10 9
#570000
0*
0$
#600000
1*
b10110011 !
b10110011 1
b10110011 +
b10110011 8
b10100011 -
b10100011 5
b11 .
b11 3
b11 ,
b11 6
1$
b10110011 #
b10110011 (
b10110011 4
b10110011 7
b100000000000011 "
b100000000000011 '
b11 9
#610000
0*
0$
#640000
1*
b10110100 !
b10110100 1
b10110100 +
b10110100 8
b10100100 -
b10100100 5
b100 .
b100 3
b100 ,
b100 6
1$
b10110100 #
b10110100 (
b10110100 4
b10110100 7
b100000000000100 "
b100000000000100 '
b100 9
#650000
0*
0$
#680000
1*
b10110101 !
b10110101 1
b10110101 +
b10110101 8
b10100101 -
b10100101 5
b101 .
b101 3
b101 ,
b101 6
1$
b10110101 #
b10110101 (
b10110101 4
b10110101 7
b100000000000101 "
b100000000000101 '
b101 9
#690000
0*
0$
#720000
1*
b10110110 !
b10110110 1
b10110110 +
b10110110 8
b10100110 -
b10100110 5
b110 .
b110 3
b110 ,
b110 6
1$
b10110110 #
b10110110 (
b10110110 4
b10110110 7
b100000000000110 "
b100000000000110 '
b110 9
#730000
0*
0$
#760000
1*
b10110111 !
b10110111 1
b10110111 +
b10110111 8
b10100111 -
b10100111 5
b111 .
b111 3
b111 ,
b111 6
1$
b10110111 #
b10110111 (
b10110111 4
b10110111 7
b100000000000111 "
b100000000000111 '
b111 9
#770000
0*
0$
#800000
1*
b10111000 !
b10111000 1
b10111000 +
b10111000 8
b10101000 -
b10101000 5
b1000 .
b1000 3
b1000 ,
b1000 6
1$
b10111000 #
b10111000 (
b10111000 4
b10111000 7
b100000000001000 "
b100000000001000 '
b1000 9
#810000
0*
0$
#840000
1*
b10111001 !
b10111001 1
b10111001 +
b10111001 8
b10101001 -
b10101001 5
b1001 .
b1001 3
b1001 ,
b1001 6
1$
b10111001 #
b10111001 (
b10111001 4
b10111001 7
b100000000001001 "
b100000000001001 '
b1001 9
#850000
0*
0$
#880000
1*
b10111010 !
b10111010 1
b10111010 +
b10111010 8
b10101010 -
b10101010 5
b1010 .
b1010 3
b1010 ,
b1010 6
1$
b10111010 #
b10111010 (
b10111010 4
b10111010 7
b100000000001010 "
b100000000001010 '
b1010 9
#890000
0*
0$
#920000
1*
b10111011 !
b10111011 1
b10111011 +
b10111011 8
b10101011 -
b10101011 5
b1011 .
b1011 3
b1011 ,
b1011 6
1$
b10111011 #
b10111011 (
b10111011 4
b10111011 7
b100000000001011 "
b100000000001011 '
b1011 9
#930000
0*
0$
#960000
1*
b10111100 !
b10111100 1
b10111100 +
b10111100 8
b10101100 -
b10101100 5
b1100 .
b1100 3
b1100 ,
b1100 6
1$
b10111100 #
b10111100 (
b10111100 4
b10111100 7
b100000000001100 "
b100000000001100 '
b1100 9
#970000
0*
0$
#1000000
1*
b10111101 !
b10111101 1
b10111101 +
b10111101 8
b10101101 -
b10101101 5
b1101 .
b1101 3
b1101 ,
b1101 6
1$
b10111101 #
b10111101 (
b10111101 4
b10111101 7
b100000000001101 "
b100000000001101 '
b1101 9
#1010000
0*
0$
#1040000
1*
b10111110 !
b10111110 1
b10111110 +
b10111110 8
b10101110 -
b10101110 5
b1110 .
b1110 3
b1110 ,
b1110 6
1$
b10111110 #
b10111110 (
b10111110 4
b10111110 7
b100000000001110 "
b100000000001110 '
b1110 9
#1050000
0*
0$
#1080000
1*
b10111111 !
b10111111 1
b10111111 +
b10111111 8
b10101111 -
b10101111 5
b1111 .
b1111 3
b1111 ,
b1111 6
1$
b10111111 #
b10111111 (
b10111111 4
b10111111 7
b100000000001111 "
b100000000001111 '
b1111 9
#1090000
0*
0$
#1120000
bx -
bx 5
b10110000 +
b10110000 8
b1111111111111111 !
b1111111111111111 1
b10000000000000 .
b10000000000000 3
b0 ,
b0 6
10
b110000000000000 "
b110000000000000 '
b10000 9
#1130000
bx +
bx 8
b0 !
b0 1
b11000000000000 .
b11000000000000 3
b1000000000000 ,
b1000000000000 6
00
b111000000000000 "
b111000000000000 '
