Project-02/ALU16/ALU16.v
module ALU16 (
    input [15:0] a,          // First operand (16 bits)
    input [15:0] b,          // Second operand (16 bits)
    input [3:0] control,     // Control signal to select the operation
    output reg [15:0] out,   // Output result (16 bits)
    output reg zero,         // Zero flag (1 bit)
    output reg carry,        // Carry flag (1 bit)
    output reg overflow,     // Overflow flag (1 bit)
    output reg negative       // Negative flag (1 bit)
);

    // Control signal definitions for different ALU operations
    localparam ADD  = 4'b0000; // Addition
    localparam SUB  = 4'b0001; // Subtraction
    localparam AND  = 4'b0010; // Bitwise AND
    localparam OR   = 4'b0011; // Bitwise OR
    localparam XOR  = 4'b0100; // Bitwise XOR
    localparam SLL  = 4'b0101; // Shift Left Logical
    localparam SRL  = 4'b0110; // Shift Right Logical
    localparam SRA  = 4'b0111; // Shift Right Arithmetic

    // Always block to perform operations based on the control signal
    always @(*) begin
        // Initialize outputs and flags to default values
        out = 16'b0;            // Default output is zero
        zero = 1'b0;           // Default zero flag is false
        carry = 1'b0;          // Default carry flag is false
        overflow = 1'b0;       // Default overflow flag is false
        negative = 1'b0;       // Default negative flag is false
        
        // Perform the operation based on the control signal
        case (control)
            ADD: begin
                {carry, out} = a + b; // Perform addition and capture carry
                // Check for overflow: if the signs of the operands are the same
                // and differ from the sign of the result, overflow has occurred
                overflow = (a[15] == b[15]) && (out[15] != a[15]);
            end
            SUB: begin
                {carry, out} = a - b; // Perform subtraction and capture carry
                // Check for overflow: if the signs of the operands are different
                // and the sign of the result differs from the sign of the first operand
                overflow = (a[15] != b[15]) && (out[15] != a[15]);
            end
            AND: out = a & b; // Perform bitwise AND
            OR:  out = a | b; // Perform bitwise OR
            XOR: out = a ^ b; // Perform bitwise XOR
            SLL: out = a << 1; // Shift left logical by 1
            SRL: out = a >> 1; // Shift right logical by 1
            SRA: out = $signed(a) >>> 1; // Shift right arithmetic by 1
            default: out = 16'b0; // Default case, output zero
        endcase
        
        // Set the zero flag: true if the output is zero
        zero = (out == 16'b0);
        
        // Set the negative flag: true if the sign bit (MSB) of the output is 1
        negative = out[15]; // The sign bit of the result
    end
endmodule

Project-02/ALU16/ALU16_tb.v
module ALU16_tb;
    // Declare registers for inputs
    reg [15:0] a, b;
    reg [3:0] control;
    
    // Declare wires for outputs
    wire [15:0] out;
    wire zero, carry, overflow, negative;

    // Instantiate the ALU16 module
    ALU16 uut (
        .a(a),
        .b(b),
        .control(control),
        .out(out),
        .zero(zero),
        .carry(carry),
        .overflow(overflow),
        .negative(negative)
    );

    // File descriptor for output file
    integer file;

    initial begin
        $dumpfile("ALU16.vcd");
        $dumpvars(0, ALU16_tb);
        // Open the output file
        file = $fopen("ALU16.out", "w");
        
        
        // Write the header to the file
        $fdisplay(file, "|         a        |        b         | control |       out        | zero | carry | overflow | negative |");

        // Test case 1: Addition
        a = 16'h0001; b = 16'h0001; control = 4'b0000; #10;
        $fdisplay(file, "| %016b | %016b |   %b  | %016b |   %b  |   %b   |    %b     |    %b     |", a, b, control, out, zero, carry, overflow, negative);

        // Test case 2: Subtraction
        a = 16'h0002; b = 16'h0001; control = 4'b0001; #10;
        $fdisplay(file, "| %016b | %016b |   %b  | %016b |   %b  |   %b   |    %b     |    %b     |", a, b, control, out, zero, carry, overflow, negative);

        // Test case 3: Bitwise AND
        a = 16'h000F; b = 16'h00F0; control = 4'b0010; #10;
        $fdisplay(file, "| %016b | %016b |   %b  | %016b |   %b  |   %b   |    %b     |    %b     |", a, b, control, out, zero, carry, overflow, negative);

        // Test case 4: Bitwise OR
        a = 16'h00F0; b = 16'h000F; control = 4'b0011; #10;
        $fdisplay(file, "| %016b | %016b |   %b  | %016b |   %b  |   %b   |    %b     |    %b     |", a, b, control, out, zero, carry, overflow, negative);

        // Test case 5: Bitwise XOR
        a = 16'h00F0; b = 16'h000F; control = 4'b0100; #10;
        $fdisplay(file, "| %016b | %016b |   %b  | %016b |   %b  |   %b   |    %b     |    %b     |", a, b, control, out, zero, carry, overflow, negative);

        // Test case 6: Shift Left Logical
        a = 16'h0001; b = 16'b0; control = 4'b0101; #10;
        $fdisplay(file, "| %016b | %016b |   %b  | %016b |   %b  |   %b   |    %b     |    %b     |", a, b, control, out, zero, carry, overflow, negative);

        // Test case 7: Shift Right Logical
        a = 16'h0002; b = 16'b0; control = 4'b0110; #10;
        $fdisplay(file, "| %016b | %016b |   %b  | %016b |   %b  |   %b   |    %b     |    %b     |", a, b, control, out, zero, carry, overflow, negative);

        // Test case 8: Shift Right Arithmetic
        a = 16'h8000; b = 16'b0; control = 4'b0111; #10;
        $fdisplay(file, "| %016b | %016b |   %b  | %016b |   %b  |   %b   |    %b     |    %b     |", a, b, control, out, zero, carry, overflow, negative);

        // Close the output file
        $fclose(file);
        
        // End the simulation
        $finish;
    end
endmodule

Project-02/ALU16/ALU16.vcd
$date
	Wed Aug 14 17:26:44 2024
$end
$version
	Icarus Verilog
$end
$timescale
	1s
$end
$scope module ALU16_tb $end
$var wire 1 ! zero $end
$var wire 1 " overflow $end
$var wire 16 # out [15:0] $end
$var wire 1 $ negative $end
$var wire 1 % carry $end
$var reg 16 & a [15:0] $end
$var reg 16 ' b [15:0] $end
$var reg 4 ( control [3:0] $end
$var integer 32 ) file [31:0] $end
$scope module uut $end
$var wire 16 * a [15:0] $end
$var wire 16 + b [15:0] $end
$var wire 4 , control [3:0] $end
$var parameter 4 - ADD $end
$var parameter 4 . AND $end
$var parameter 4 / OR $end
$var parameter 4 0 SLL $end
$var parameter 4 1 SRA $end
$var parameter 4 2 SRL $end
$var parameter 4 3 SUB $end
$var parameter 4 4 XOR $end
$var reg 1 % carry $end
$var reg 1 $ negative $end
$var reg 16 5 out [15:0] $end
$var reg 1 " overflow $end
$var reg 1 ! zero $end
$upscope $end
$upscope $end
$enddefinitions $end
$comment Show the parameter values. $end
$dumpall
b100 4
b1 3
b110 2
b111 1
b101 0
b11 /
b10 .
b0 -
$end
#0
$dumpvars
b10 5
b0 ,
b1 +
b1 *
b10000000000000000000000000000011 )
b0 (
b1 '
b1 &
0%
0$
b10 #
0"
0!
$end
#10
b1 #
b1 5
b1 (
b1 ,
b10 &
b10 *
#20
1!
b0 #
b0 5
b10 (
b10 ,
b11110000 '
b11110000 +
b1111 &
b1111 *
#30
b11111111 #
b11111111 5
0!
b11 (
b11 ,
b1111 '
b1111 +
b11110000 &
b11110000 *
#40
b11111111 #
b11111111 5
b100 (
b100 ,
#50
b10 #
b10 5
b101 (
b101 ,
b0 '
b0 +
b1 &
b1 *
#60
b1 #
b1 5
b110 (
b110 ,
b10 &
b10 *
#70
1$
b1100000000000000 #
b1100000000000000 5
b111 (
b111 ,
b1000000000000000 &
b1000000000000000 *
