And16 gate/And16.v
module And16_using_NAND (
    input  [15:0] a,  // 16-bit input a
    input  [15:0] b,  // 16-bit input b
    output [15:0] out // 16-bit output out
);

    wire [15:0] nand_out; // Intermediate wires for NAND outputs

    // Generate NAND gates for each bit
    genvar i;
    generate
        for (i = 0; i < 16; i = i + 1) begin : nand_gates
            assign nand_out[i] = ~(a[i] & b[i]); // NAND operation
            assign out[i] = ~(nand_out[i] & nand_out[i]); // AND operation using NAND
        end
    endgenerate

endmodule

And16 gate/And16_tb.v
`timescale 1ns / 1ps

module tb_And16_using_NAND;

    // Inputs
    reg [15:0] a;  // 16-bit input a
    reg [15:0] b;  // 16-bit input b

    // Output
    wire [15:0] out; // 16-bit output

    // Instantiate the And16_using_NAND module
    And16_using_NAND uut (
        .a(a),
        .b(b),
        .out(out)
    );

    // File handling
    integer output_file; // File for output results
    integer i;          // Loop variable
    reg [15:0] expected_output; // Variable to store expected output

    // Initialize the testbench
    initial begin
        $dumpfile("And16.vcd"); // Specify the output VCD file
        $dumpvars(0, tb_And16_using_NAND);  // Dump all variables in the testbench

        // Open the output file for writing
        output_file = $fopen("And16.out", "w");

        // Write header to the output file
        $fwrite(output_file, "|        a         |        b         |       out        |\n");

        // Test all combinations of a and b
        for (i = 0; i < 256; i = i + 1) begin
            a = i;            // Set a to the current value of i
            b = 8'hFF;       // Set b to 0xFF for testing
            
            // Wait for a short time to allow the output to settle
            #10;

            // Calculate expected output
            expected_output = a & b;

            // Write the inputs and output to the output file in the specified format
            $fwrite(output_file, "| %016b | %016b | %016b |\n", a, b, out);
        end

        // Close the output file
        $fclose(output_file);
        
        // Finish the simulation
        $finish;
    end

endmodule

Project-01/And16 gate/And16.vcd
$date
	Sat Aug 03 16:51:49 2024
$end
$version
	Icarus Verilog
$end
$timescale
	1ps
$end
$scope module tb_And16_using_NAND $end
$var wire 16 ! out [15:0] $end
$var reg 16 " a [15:0] $end
$var reg 16 # b [15:0] $end
$var reg 16 $ expected_output [15:0] $end
$var integer 32 % i [31:0] $end
$var integer 32 & output_file [31:0] $end
$scope module uut $end
$var wire 16 ' a [15:0] $end
$var wire 16 ( b [15:0] $end
$var wire 16 ) out [15:0] $end
$var wire 16 * nand_out [15:0] $end
$scope begin nand_gates[0] $end
$var parameter 2 + i $end
$upscope $end
$scope begin nand_gates[1] $end
$var parameter 2 , i $end
$upscope $end
$scope begin nand_gates[2] $end
$var parameter 3 - i $end
$upscope $end
$scope begin nand_gates[3] $end
$var parameter 3 . i $end
$upscope $end
$scope begin nand_gates[4] $end
$var parameter 4 / i $end
$upscope $end
$scope begin nand_gates[5] $end
$var parameter 4 0 i $end
$upscope $end
$scope begin nand_gates[6] $end
$var parameter 4 1 i $end
$upscope $end
$scope begin nand_gates[7] $end
$var parameter 4 2 i $end
$upscope $end
$scope begin nand_gates[8] $end
$var parameter 5 3 i $end
$upscope $end
$scope begin nand_gates[9] $end
$var parameter 5 4 i $end
$upscope $end
$scope begin nand_gates[10] $end
$var parameter 5 5 i $end
$upscope $end
$scope begin nand_gates[11] $end
$var parameter 5 6 i $end
$upscope $end
$scope begin nand_gates[12] $end
$var parameter 5 7 i $end
$upscope $end
$scope begin nand_gates[13] $end
$var parameter 5 8 i $end
$upscope $end
$scope begin nand_gates[14] $end
$var parameter 5 9 i $end
$upscope $end
$scope begin nand_gates[15] $end
$var parameter 5 : i $end
$upscope $end
$upscope $end
$upscope $end
$enddefinitions $end
$comment Show the parameter values. $end
$dumpall
b1111 :
b1110 9
b1101 8
b1100 7
b1011 6
b1010 5
b1001 4
b1000 3
b111 2
b110 1
b101 0
b100 /
b11 .
b10 -
b1 ,
b0 +
$end
#0
$dumpvars
b1111111111111111 *
b0 )
b11111111 (
b0 '
b10000000000000000000000000000011 &
b0 %
bx $
b11111111 #
b0 "
b0 !
$end
#10000
b1 !
b1 )
b1111111111111110 *
b1 "
b1 '
b1 %
b0 $
#20000
b10 !
b10 )
b1111111111111101 *
b10 "
b10 '
b10 %
b1 $
#30000
b11 !
b11 )
b1111111111111100 *
b11 "
b11 '
b11 %
b10 $
#40000
b100 !
b100 )
b1111111111111011 *
b100 "
b100 '
b100 %
b11 $
#50000
b101 !
b101 )
b1111111111111010 *
b101 "
b101 '
b101 %
b100 $
#60000
b110 !
b110 )
b1111111111111001 *
b110 "
b110 '
b110 %
b101 $
#70000
b111 !
b111 )
b1111111111111000 *
b111 "
b111 '
b111 %
b110 $
#80000
b1000 !
b1000 )
b1111111111110111 *
b1000 "
b1000 '
b1000 %
b111 $
#90000
b1001 !
b1001 )
b1111111111110110 *
b1001 "
b1001 '
b1001 %
b1000 $
#100000
b1010 !
b1010 )
b1111111111110101 *
b1010 "
b1010 '
b1010 %
b1001 $
#110000
b1011 !
b1011 )
b1111111111110100 *
b1011 "
b1011 '
b1011 %
b1010 $
#120000
b1100 !
b1100 )
b1111111111110011 *
b1100 "
b1100 '
b1100 %
b1011 $
#130000
b1101 !
b1101 )
b1111111111110010 *
b1101 "
b1101 '
b1101 %
b1100 $
#140000
b1110 !
b1110 )
b1111111111110001 *
b1110 "
b1110 '
b1110 %
b1101 $
#150000
b1111 !
b1111 )
b1111111111110000 *
b1111 "
b1111 '
b1111 %
b1110 $
#160000
b10000 !
b10000 )
b1111111111101111 *
b10000 "
b10000 '
b10000 %
b1111 $
#170000
b10001 !
b10001 )
b1111111111101110 *
b10001 "
b10001 '
b10001 %
b10000 $
#180000
b10010 !
b10010 )
b1111111111101101 *
b10010 "
b10010 '
b10010 %
b10001 $
#190000
b10011 !
b10011 )
b1111111111101100 *
b10011 "
b10011 '
b10011 %
b10010 $
#200000
b10100 !
b10100 )
b1111111111101011 *
b10100 "
b10100 '
b10100 %
b10011 $
#210000
b10101 !
b10101 )
b1111111111101010 *
b10101 "
b10101 '
b10101 %
b10100 $
#220000
b10110 !
b10110 )
b1111111111101001 *
b10110 "
b10110 '
b10110 %
b10101 $
#230000
b10111 !
b10111 )
b1111111111101000 *
b10111 "
b10111 '
b10111 %
b10110 $
#240000
b11000 !
b11000 )
b1111111111100111 *
b11000 "
b11000 '
b11000 %
b10111 $
#250000
b11001 !
b11001 )
b1111111111100110 *
b11001 "
b11001 '
b11001 %
b11000 $
#260000
b11010 !
b11010 )
b1111111111100101 *
b11010 "
b11010 '
b11010 %
b11001 $
#270000
b11011 !
b11011 )
b1111111111100100 *
b11011 "
b11011 '
b11011 %
b11010 $
#280000
b11100 !
b11100 )
b1111111111100011 *
b11100 "
b11100 '
b11100 %
b11011 $
#290000
b11101 !
b11101 )
b1111111111100010 *
b11101 "
b11101 '
b11101 %
b11100 $
#300000
b11110 !
b11110 )
b1111111111100001 *
b11110 "
b11110 '
b11110 %
b11101 $
#310000
b11111 !
b11111 )
b1111111111100000 *
b11111 "
b11111 '
b11111 %
b11110 $
#320000
b100000 !
b100000 )
b1111111111011111 *
b100000 "
b100000 '
b100000 %
b11111 $
#330000
b100001 !
b100001 )
b1111111111011110 *
b100001 "
b100001 '
b100001 %
b100000 $
#340000
b100010 !
b100010 )
b1111111111011101 *
b100010 "
b100010 '
b100010 %
b100001 $
#350000
b100011 !
b100011 )
b1111111111011100 *
b100011 "
b100011 '
b100011 %
b100010 $
#360000
b100100 !
b100100 )
b1111111111011011 *
b100100 "
b100100 '
b100100 %
b100011 $
#370000
b100101 !
b100101 )
b1111111111011010 *
b100101 "
b100101 '
b100101 %
b100100 $
#380000
b100110 !
b100110 )
b1111111111011001 *
b100110 "
b100110 '
b100110 %
b100101 $
#390000
b100111 !
b100111 )
b1111111111011000 *
b100111 "
b100111 '
b100111 %
b100110 $
#400000
b101000 !
b101000 )
b1111111111010111 *
b101000 "
b101000 '
b101000 %
b100111 $
#410000
b101001 !
b101001 )
b1111111111010110 *
b101001 "
b101001 '
b101001 %
b101000 $
#420000
b101010 !
b101010 )
b1111111111010101 *
b101010 "
b101010 '
b101010 %
b101001 $
#430000
b101011 !
b101011 )
b1111111111010100 *
b101011 "
b101011 '
b101011 %
b101010 $
#440000
b101100 !
b101100 )
b1111111111010011 *
b101100 "
b101100 '
b101100 %
b101011 $
#450000
b101101 !
b101101 )
b1111111111010010 *
b101101 "
b101101 '
b101101 %
b101100 $
#460000
b101110 !
b101110 )
b1111111111010001 *
b101110 "
b101110 '
b101110 %
b101101 $
#470000
b101111 !
b101111 )
b1111111111010000 *
b101111 "
b101111 '
b101111 %
b101110 $
#480000
b110000 !
b110000 )
b1111111111001111 *
b110000 "
b110000 '
b110000 %
b101111 $
#490000
b110001 !
b110001 )
b1111111111001110 *
b110001 "
b110001 '
b110001 %
b110000 $
#500000
b110010 !
b110010 )
b1111111111001101 *
b110010 "
b110010 '
b110010 %
b110001 $
#510000
b110011 !
b110011 )
b1111111111001100 *
b110011 "
b110011 '
b110011 %
b110010 $
#520000
b110100 !
b110100 )
b1111111111001011 *
b110100 "
b110100 '
b110100 %
b110011 $
#530000
b110101 !
b110101 )
b1111111111001010 *
b110101 "
b110101 '
b110101 %
b110100 $
#540000
b110110 !
b110110 )
b1111111111001001 *
b110110 "
b110110 '
b110110 %
b110101 $
#550000
b110111 !
b110111 )
b1111111111001000 *
b110111 "
b110111 '
b110111 %
b110110 $
#560000
b111000 !
b111000 )
b1111111111000111 *
b111000 "
b111000 '
b111000 %
b110111 $
#570000
b111001 !
b111001 )
b1111111111000110 *
b111001 "
b111001 '
b111001 %
b111000 $
#580000
b111010 !
b111010 )
b1111111111000101 *
b111010 "
b111010 '
b111010 %
b111001 $
#590000
b111011 !
b111011 )
b1111111111000100 *
b111011 "
b111011 '
b111011 %
b111010 $
#600000
b111100 !
b111100 )
b1111111111000011 *
b111100 "
b111100 '
b111100 %
b111011 $
#610000
b111101 !
b111101 )
b1111111111000010 *
b111101 "
b111101 '
b111101 %
b111100 $
#620000
b111110 !
b111110 )
b1111111111000001 *
b111110 "
b111110 '
b111110 %
b111101 $
#630000
b111111 !
b111111 )
b1111111111000000 *
b111111 "
b111111 '
b111111 %
b111110 $
#640000
b1000000 !
b1000000 )
b1111111110111111 *
b1000000 "
b1000000 '
b1000000 %
b111111 $
#650000
b1000001 !
b1000001 )
b1111111110111110 *
b1000001 "
b1000001 '
b1000001 %
b1000000 $
#660000
b1000010 !
b1000010 )
b1111111110111101 *
b1000010 "
b1000010 '
b1000010 %
b1000001 $
#670000
b1000011 !
b1000011 )
b1111111110111100 *
b1000011 "
b1000011 '
b1000011 %
b1000010 $
#680000
b1000100 !
b1000100 )
b1111111110111011 *
b1000100 "
b1000100 '
b1000100 %
b1000011 $
#690000
b1000101 !
b1000101 )
b1111111110111010 *
b1000101 "
b1000101 '
b1000101 %
b1000100 $
#700000
b1000110 !
b1000110 )
b1111111110111001 *
b1000110 "
b1000110 '
b1000110 %
b1000101 $
#710000
b1000111 !
b1000111 )
b1111111110111000 *
b1000111 "
b1000111 '
b1000111 %
b1000110 $
#720000
b1001000 !
b1001000 )
b1111111110110111 *
b1001000 "
b1001000 '
b1001000 %
b1000111 $
#730000
b1001001 !
b1001001 )
b1111111110110110 *
b1001001 "
b1001001 '
b1001001 %
b1001000 $
#740000
b1001010 !
b1001010 )
b1111111110110101 *
b1001010 "
b1001010 '
b1001010 %
b1001001 $
#750000
b1001011 !
b1001011 )
b1111111110110100 *
b1001011 "
b1001011 '
b1001011 %
b1001010 $
#760000
b1001100 !
b1001100 )
b1111111110110011 *
b1001100 "
b1001100 '
b1001100 %
b1001011 $
#770000
b1001101 !
b1001101 )
b1111111110110010 *
b1001101 "
b1001101 '
b1001101 %
b1001100 $
#780000
b1001110 !
b1001110 )
b1111111110110001 *
b1001110 "
b1001110 '
b1001110 %
b1001101 $
#790000
b1001111 !
b1001111 )
b1111111110110000 *
b1001111 "
b1001111 '
b1001111 %
b1001110 $
#800000
b1010000 !
b1010000 )
b1111111110101111 *
b1010000 "
b1010000 '
b1010000 %
b1001111 $
#810000
b1010001 !
b1010001 )
b1111111110101110 *
b1010001 "
b1010001 '
b1010001 %
b1010000 $
#820000
b1010010 !
b1010010 )
b1111111110101101 *
b1010010 "
b1010010 '
b1010010 %
b1010001 $
#830000
b1010011 !
b1010011 )
b1111111110101100 *
b1010011 "
b1010011 '
b1010011 %
b1010010 $
#840000
b1010100 !
b1010100 )
b1111111110101011 *
b1010100 "
b1010100 '
b1010100 %
b1010011 $
#850000
b1010101 !
b1010101 )
b1111111110101010 *
b1010101 "
b1010101 '
b1010101 %
b1010100 $
#860000
b1010110 !
b1010110 )
b1111111110101001 *
b1010110 "
b1010110 '
b1010110 %
b1010101 $
#870000
b1010111 !
b1010111 )
b1111111110101000 *
b1010111 "
b1010111 '
b1010111 %
b1010110 $
#880000
b1011000 !
b1011000 )
b1111111110100111 *
b1011000 "
b1011000 '
b1011000 %
b1010111 $
#890000
b1011001 !
b1011001 )
b1111111110100110 *
b1011001 "
b1011001 '
b1011001 %
b1011000 $
#900000
b1011010 !
b1011010 )
b1111111110100101 *
b1011010 "
b1011010 '
b1011010 %
b1011001 $
#910000
b1011011 !
b1011011 )
b1111111110100100 *
b1011011 "
b1011011 '
b1011011 %
b1011010 $
#920000
b1011100 !
b1011100 )
b1111111110100011 *
b1011100 "
b1011100 '
b1011100 %
b1011011 $
#930000
b1011101 !
b1011101 )
b1111111110100010 *
b1011101 "
b1011101 '
b1011101 %
b1011100 $
#940000
b1011110 !
b1011110 )
b1111111110100001 *
b1011110 "
b1011110 '
b1011110 %
b1011101 $
#950000
b1011111 !
b1011111 )
b1111111110100000 *
b1011111 "
b1011111 '
b1011111 %
b1011110 $
#960000
b1100000 !
b1100000 )
b1111111110011111 *
b1100000 "
b1100000 '
b1100000 %
b1011111 $
#970000
b1100001 !
b1100001 )
b1111111110011110 *
b1100001 "
b1100001 '
b1100001 %
b1100000 $
#980000
b1100010 !
b1100010 )
b1111111110011101 *
b1100010 "
b1100010 '
b1100010 %
b1100001 $
#990000
b1100011 !
b1100011 )
b1111111110011100 *
b1100011 "
b1100011 '
b1100011 %
b1100010 $
#1000000
b1100100 !
b1100100 )
b1111111110011011 *
b1100100 "
b1100100 '
b1100100 %
b1100011 $
#1010000
b1100101 !
b1100101 )
b1111111110011010 *
b1100101 "
b1100101 '
b1100101 %
b1100100 $
#1020000
b1100110 !
b1100110 )
b1111111110011001 *
b1100110 "
b1100110 '
b1100110 %
b1100101 $
#1030000
b1100111 !
b1100111 )
b1111111110011000 *
b1100111 "
b1100111 '
b1100111 %
b1100110 $
#1040000
b1101000 !
b1101000 )
b1111111110010111 *
b1101000 "
b1101000 '
b1101000 %
b1100111 $
#1050000
b1101001 !
b1101001 )
b1111111110010110 *
b1101001 "
b1101001 '
b1101001 %
b1101000 $
#1060000
b1101010 !
b1101010 )
b1111111110010101 *
b1101010 "
b1101010 '
b1101010 %
b1101001 $
#1070000
b1101011 !
b1101011 )
b1111111110010100 *
b1101011 "
b1101011 '
b1101011 %
b1101010 $
#1080000
b1101100 !
b1101100 )
b1111111110010011 *
b1101100 "
b1101100 '
b1101100 %
b1101011 $
#1090000
b1101101 !
b1101101 )
b1111111110010010 *
b1101101 "
b1101101 '
b1101101 %
b1101100 $
#1100000
b1101110 !
b1101110 )
b1111111110010001 *
b1101110 "
b1101110 '
b1101110 %
b1101101 $
#1110000
b1101111 !
b1101111 )
b1111111110010000 *
b1101111 "
b1101111 '
b1101111 %
b1101110 $
#1120000
b1110000 !
b1110000 )
b1111111110001111 *
b1110000 "
b1110000 '
b1110000 %
b1101111 $
#1130000
b1110001 !
b1110001 )
b1111111110001110 *
b1110001 "
b1110001 '
b1110001 %
b1110000 $
#1140000
b1110010 !
b1110010 )
b1111111110001101 *
b1110010 "
b1110010 '
b1110010 %
b1110001 $
#1150000
b1110011 !
b1110011 )
b1111111110001100 *
b1110011 "
b1110011 '
b1110011 %
b1110010 $
#1160000
b1110100 !
b1110100 )
b1111111110001011 *
b1110100 "
b1110100 '
b1110100 %
b1110011 $
#1170000
b1110101 !
b1110101 )
b1111111110001010 *
b1110101 "
b1110101 '
b1110101 %
b1110100 $
#1180000
b1110110 !
b1110110 )
b1111111110001001 *
b1110110 "
b1110110 '
b1110110 %
b1110101 $
#1190000
b1110111 !
b1110111 )
b1111111110001000 *
b1110111 "
b1110111 '
b1110111 %
b1110110 $
#1200000
b1111000 !
b1111000 )
b1111111110000111 *
b1111000 "
b1111000 '
b1111000 %
b1110111 $
#1210000
b1111001 !
b1111001 )
b1111111110000110 *
b1111001 "
b1111001 '
b1111001 %
b1111000 $
#1220000
b1111010 !
b1111010 )
b1111111110000101 *
b1111010 "
b1111010 '
b1111010 %
b1111001 $
#1230000
b1111011 !
b1111011 )
b1111111110000100 *
b1111011 "
b1111011 '
b1111011 %
b1111010 $
#1240000
b1111100 !
b1111100 )
b1111111110000011 *
b1111100 "
b1111100 '
b1111100 %
b1111011 $
#1250000
b1111101 !
b1111101 )
b1111111110000010 *
b1111101 "
b1111101 '
b1111101 %
b1111100 $
#1260000
b1111110 !
b1111110 )
b1111111110000001 *
b1111110 "
b1111110 '
b1111110 %
b1111101 $
#1270000
b1111111 !
b1111111 )
b1111111110000000 *
b1111111 "
b1111111 '
b1111111 %
b1111110 $
#1280000
b10000000 !
b10000000 )
b1111111101111111 *
b10000000 "
b10000000 '
b10000000 %
b1111111 $
#1290000
b10000001 !
b10000001 )
b1111111101111110 *
b10000001 "
b10000001 '
b10000001 %
b10000000 $
#1300000
b10000010 !
b10000010 )
b1111111101111101 *
b10000010 "
b10000010 '
b10000010 %
b10000001 $
#1310000
b10000011 !
b10000011 )
b1111111101111100 *
b10000011 "
b10000011 '
b10000011 %
b10000010 $
#1320000
b10000100 !
b10000100 )
b1111111101111011 *
b10000100 "
b10000100 '
b10000100 %
b10000011 $
#1330000
b10000101 !
b10000101 )
b1111111101111010 *
b10000101 "
b10000101 '
b10000101 %
b10000100 $
#1340000
b10000110 !
b10000110 )
b1111111101111001 *
b10000110 "
b10000110 '
b10000110 %
b10000101 $
#1350000
b10000111 !
b10000111 )
b1111111101111000 *
b10000111 "
b10000111 '
b10000111 %
b10000110 $
#1360000
b10001000 !
b10001000 )
b1111111101110111 *
b10001000 "
b10001000 '
b10001000 %
b10000111 $
#1370000
b10001001 !
b10001001 )
b1111111101110110 *
b10001001 "
b10001001 '
b10001001 %
b10001000 $
#1380000
b10001010 !
b10001010 )
b1111111101110101 *
b10001010 "
b10001010 '
b10001010 %
b10001001 $
#1390000
b10001011 !
b10001011 )
b1111111101110100 *
b10001011 "
b10001011 '
b10001011 %
b10001010 $
#1400000
b10001100 !
b10001100 )
b1111111101110011 *
b10001100 "
b10001100 '
b10001100 %
b10001011 $
#1410000
b10001101 !
b10001101 )
b1111111101110010 *
b10001101 "
b10001101 '
b10001101 %
b10001100 $
#1420000
b10001110 !
b10001110 )
b1111111101110001 *
b10001110 "
b10001110 '
b10001110 %
b10001101 $
#1430000
b10001111 !
b10001111 )
b1111111101110000 *
b10001111 "
b10001111 '
b10001111 %
b10001110 $
#1440000
b10010000 !
b10010000 )
b1111111101101111 *
b10010000 "
b10010000 '
b10010000 %
b10001111 $
#1450000
b10010001 !
b10010001 )
b1111111101101110 *
b10010001 "
b10010001 '
b10010001 %
b10010000 $
#1460000
b10010010 !
b10010010 )
b1111111101101101 *
b10010010 "
b10010010 '
b10010010 %
b10010001 $
#1470000
b10010011 !
b10010011 )
b1111111101101100 *
b10010011 "
b10010011 '
b10010011 %
b10010010 $
#1480000
b10010100 !
b10010100 )
b1111111101101011 *
b10010100 "
b10010100 '
b10010100 %
b10010011 $
#1490000
b10010101 !
b10010101 )
b1111111101101010 *
b10010101 "
b10010101 '
b10010101 %
b10010100 $
#1500000
b10010110 !
b10010110 )
b1111111101101001 *
b10010110 "
b10010110 '
b10010110 %
b10010101 $
#1510000
b10010111 !
b10010111 )
b1111111101101000 *
b10010111 "
b10010111 '
b10010111 %
b10010110 $
#1520000
b10011000 !
b10011000 )
b1111111101100111 *
b10011000 "
b10011000 '
b10011000 %
b10010111 $
#1530000
b10011001 !
b10011001 )
b1111111101100110 *
b10011001 "
b10011001 '
b10011001 %
b10011000 $
#1540000
b10011010 !
b10011010 )
b1111111101100101 *
b10011010 "
b10011010 '
b10011010 %
b10011001 $
#1550000
b10011011 !
b10011011 )
b1111111101100100 *
b10011011 "
b10011011 '
b10011011 %
b10011010 $
#1560000
b10011100 !
b10011100 )
b1111111101100011 *
b10011100 "
b10011100 '
b10011100 %
b10011011 $
#1570000
b10011101 !
b10011101 )
b1111111101100010 *
b10011101 "
b10011101 '
b10011101 %
b10011100 $
#1580000
b10011110 !
b10011110 )
b1111111101100001 *
b10011110 "
b10011110 '
b10011110 %
b10011101 $
#1590000
b10011111 !
b10011111 )
b1111111101100000 *
b10011111 "
b10011111 '
b10011111 %
b10011110 $
#1600000
b10100000 !
b10100000 )
b1111111101011111 *
b10100000 "
b10100000 '
b10100000 %
b10011111 $
#1610000
b10100001 !
b10100001 )
b1111111101011110 *
b10100001 "
b10100001 '
b10100001 %
b10100000 $
#1620000
b10100010 !
b10100010 )
b1111111101011101 *
b10100010 "
b10100010 '
b10100010 %
b10100001 $
#1630000
b10100011 !
b10100011 )
b1111111101011100 *
b10100011 "
b10100011 '
b10100011 %
b10100010 $
#1640000
b10100100 !
b10100100 )
b1111111101011011 *
b10100100 "
b10100100 '
b10100100 %
b10100011 $
#1650000
b10100101 !
b10100101 )
b1111111101011010 *
b10100101 "
b10100101 '
b10100101 %
b10100100 $
#1660000
b10100110 !
b10100110 )
b1111111101011001 *
b10100110 "
b10100110 '
b10100110 %
b10100101 $
#1670000
b10100111 !
b10100111 )
b1111111101011000 *
b10100111 "
b10100111 '
b10100111 %
b10100110 $
#1680000
b10101000 !
b10101000 )
b1111111101010111 *
b10101000 "
b10101000 '
b10101000 %
b10100111 $
#1690000
b10101001 !
b10101001 )
b1111111101010110 *
b10101001 "
b10101001 '
b10101001 %
b10101000 $
#1700000
b10101010 !
b10101010 )
b1111111101010101 *
b10101010 "
b10101010 '
b10101010 %
b10101001 $
#1710000
b10101011 !
b10101011 )
b1111111101010100 *
b10101011 "
b10101011 '
b10101011 %
b10101010 $
#1720000
b10101100 !
b10101100 )
b1111111101010011 *
b10101100 "
b10101100 '
b10101100 %
b10101011 $
#1730000
b10101101 !
b10101101 )
b1111111101010010 *
b10101101 "
b10101101 '
b10101101 %
b10101100 $
#1740000
b10101110 !
b10101110 )
b1111111101010001 *
b10101110 "
b10101110 '
b10101110 %
b10101101 $
#1750000
b10101111 !
b10101111 )
b1111111101010000 *
b10101111 "
b10101111 '
b10101111 %
b10101110 $
#1760000
b10110000 !
b10110000 )
b1111111101001111 *
b10110000 "
b10110000 '
b10110000 %
b10101111 $
#1770000
b10110001 !
b10110001 )
b1111111101001110 *
b10110001 "
b10110001 '
b10110001 %
b10110000 $
#1780000
b10110010 !
b10110010 )
b1111111101001101 *
b10110010 "
b10110010 '
b10110010 %
b10110001 $
#1790000
b10110011 !
b10110011 )
b1111111101001100 *
b10110011 "
b10110011 '
b10110011 %
b10110010 $
#1800000
b10110100 !
b10110100 )
b1111111101001011 *
b10110100 "
b10110100 '
b10110100 %
b10110011 $
#1810000
b10110101 !
b10110101 )
b1111111101001010 *
b10110101 "
b10110101 '
b10110101 %
b10110100 $
#1820000
b10110110 !
b10110110 )
b1111111101001001 *
b10110110 "
b10110110 '
b10110110 %
b10110101 $
#1830000
b10110111 !
b10110111 )
b1111111101001000 *
b10110111 "
b10110111 '
b10110111 %
b10110110 $
#1840000
b10111000 !
b10111000 )
b1111111101000111 *
b10111000 "
b10111000 '
b10111000 %
b10110111 $
#1850000
b10111001 !
b10111001 )
b1111111101000110 *
b10111001 "
b10111001 '
b10111001 %
b10111000 $
#1860000
b10111010 !
b10111010 )
b1111111101000101 *
b10111010 "
b10111010 '
b10111010 %
b10111001 $
#1870000
b10111011 !
b10111011 )
b1111111101000100 *
b10111011 "
b10111011 '
b10111011 %
b10111010 $
#1880000
b10111100 !
b10111100 )
b1111111101000011 *
b10111100 "
b10111100 '
b10111100 %
b10111011 $
#1890000
b10111101 !
b10111101 )
b1111111101000010 *
b10111101 "
b10111101 '
b10111101 %
b10111100 $
#1900000
b10111110 !
b10111110 )
b1111111101000001 *
b10111110 "
b10111110 '
b10111110 %
b10111101 $
#1910000
b10111111 !
b10111111 )
b1111111101000000 *
b10111111 "
b10111111 '
b10111111 %
b10111110 $
#1920000
b11000000 !
b11000000 )
b1111111100111111 *
b11000000 "
b11000000 '
b11000000 %
b10111111 $
#1930000
b11000001 !
b11000001 )
b1111111100111110 *
b11000001 "
b11000001 '
b11000001 %
b11000000 $
#1940000
b11000010 !
b11000010 )
b1111111100111101 *
b11000010 "
b11000010 '
b11000010 %
b11000001 $
#1950000
b11000011 !
b11000011 )
b1111111100111100 *
b11000011 "
b11000011 '
b11000011 %
b11000010 $
#1960000
b11000100 !
b11000100 )
b1111111100111011 *
b11000100 "
b11000100 '
b11000100 %
b11000011 $
#1970000
b11000101 !
b11000101 )
b1111111100111010 *
b11000101 "
b11000101 '
b11000101 %
b11000100 $
#1980000
b11000110 !
b11000110 )
b1111111100111001 *
b11000110 "
b11000110 '
b11000110 %
b11000101 $
#1990000
b11000111 !
b11000111 )
b1111111100111000 *
b11000111 "
b11000111 '
b11000111 %
b11000110 $
#2000000
b11001000 !
b11001000 )
b1111111100110111 *
b11001000 "
b11001000 '
b11001000 %
b11000111 $
#2010000
b11001001 !
b11001001 )
b1111111100110110 *
b11001001 "
b11001001 '
b11001001 %
b11001000 $
#2020000
b11001010 !
b11001010 )
b1111111100110101 *
b11001010 "
b11001010 '
b11001010 %
b11001001 $
#2030000
b11001011 !
b11001011 )
b1111111100110100 *
b11001011 "
b11001011 '
b11001011 %
b11001010 $
#2040000
b11001100 !
b11001100 )
b1111111100110011 *
b11001100 "
b11001100 '
b11001100 %
b11001011 $
#2050000
b11001101 !
b11001101 )
b1111111100110010 *
b11001101 "
b11001101 '
b11001101 %
b11001100 $
#2060000
b11001110 !
b11001110 )
b1111111100110001 *
b11001110 "
b11001110 '
b11001110 %
b11001101 $
#2070000
b11001111 !
b11001111 )
b1111111100110000 *
b11001111 "
b11001111 '
b11001111 %
b11001110 $
#2080000
b11010000 !
b11010000 )
b1111111100101111 *
b11010000 "
b11010000 '
b11010000 %
b11001111 $
#2090000
b11010001 !
b11010001 )
b1111111100101110 *
b11010001 "
b11010001 '
b11010001 %
b11010000 $
#2100000
b11010010 !
b11010010 )
b1111111100101101 *
b11010010 "
b11010010 '
b11010010 %
b11010001 $
#2110000
b11010011 !
b11010011 )
b1111111100101100 *
b11010011 "
b11010011 '
b11010011 %
b11010010 $
#2120000
b11010100 !
b11010100 )
b1111111100101011 *
b11010100 "
b11010100 '
b11010100 %
b11010011 $
#2130000
b11010101 !
b11010101 )
b1111111100101010 *
b11010101 "
b11010101 '
b11010101 %
b11010100 $
#2140000
b11010110 !
b11010110 )
b1111111100101001 *
b11010110 "
b11010110 '
b11010110 %
b11010101 $
#2150000
b11010111 !
b11010111 )
b1111111100101000 *
b11010111 "
b11010111 '
b11010111 %
b11010110 $
#2160000
b11011000 !
b11011000 )
b1111111100100111 *
b11011000 "
b11011000 '
b11011000 %
b11010111 $
#2170000
b11011001 !
b11011001 )
b1111111100100110 *
b11011001 "
b11011001 '
b11011001 %
b11011000 $
#2180000
b11011010 !
b11011010 )
b1111111100100101 *
b11011010 "
b11011010 '
b11011010 %
b11011001 $
#2190000
b11011011 !
b11011011 )
b1111111100100100 *
b11011011 "
b11011011 '
b11011011 %
b11011010 $
#2200000
b11011100 !
b11011100 )
b1111111100100011 *
b11011100 "
b11011100 '
b11011100 %
b11011011 $
#2210000
b11011101 !
b11011101 )
b1111111100100010 *
b11011101 "
b11011101 '
b11011101 %
b11011100 $
#2220000
b11011110 !
b11011110 )
b1111111100100001 *
b11011110 "
b11011110 '
b11011110 %
b11011101 $
#2230000
b11011111 !
b11011111 )
b1111111100100000 *
b11011111 "
b11011111 '
b11011111 %
b11011110 $
#2240000
b11100000 !
b11100000 )
b1111111100011111 *
b11100000 "
b11100000 '
b11100000 %
b11011111 $
#2250000
b11100001 !
b11100001 )
b1111111100011110 *
b11100001 "
b11100001 '
b11100001 %
b11100000 $
#2260000
b11100010 !
b11100010 )
b1111111100011101 *
b11100010 "
b11100010 '
b11100010 %
b11100001 $
#2270000
b11100011 !
b11100011 )
b1111111100011100 *
b11100011 "
b11100011 '
b11100011 %
b11100010 $
#2280000
b11100100 !
b11100100 )
b1111111100011011 *
b11100100 "
b11100100 '
b11100100 %
b11100011 $
#2290000
b11100101 !
b11100101 )
b1111111100011010 *
b11100101 "
b11100101 '
b11100101 %
b11100100 $
#2300000
b11100110 !
b11100110 )
b1111111100011001 *
b11100110 "
b11100110 '
b11100110 %
b11100101 $
#2310000
b11100111 !
b11100111 )
b1111111100011000 *
b11100111 "
b11100111 '
b11100111 %
b11100110 $
#2320000
b11101000 !
b11101000 )
b1111111100010111 *
b11101000 "
b11101000 '
b11101000 %
b11100111 $
#2330000
b11101001 !
b11101001 )
b1111111100010110 *
b11101001 "
b11101001 '
b11101001 %
b11101000 $
#2340000
b11101010 !
b11101010 )
b1111111100010101 *
b11101010 "
b11101010 '
b11101010 %
b11101001 $
#2350000
b11101011 !
b11101011 )
b1111111100010100 *
b11101011 "
b11101011 '
b11101011 %
b11101010 $
#2360000
b11101100 !
b11101100 )
b1111111100010011 *
b11101100 "
b11101100 '
b11101100 %
b11101011 $
#2370000
b11101101 !
b11101101 )
b1111111100010010 *
b11101101 "
b11101101 '
b11101101 %
b11101100 $
#2380000
b11101110 !
b11101110 )
b1111111100010001 *
b11101110 "
b11101110 '
b11101110 %
b11101101 $
