DeMux8way/DeMux8way.v
// 4-way Demultiplexer Module
module DMux4Way (
    input wire in,
    input wire [1:0] sel,
    output wire a, b, c, d
);
    assign a = (sel == 2'b00) ? in : 1'b0;
    assign b = (sel == 2'b01) ? in : 1'b0;
    assign c = (sel == 2'b10) ? in : 1'b0;
    assign d = (sel == 2'b11) ? in : 1'b0;
endmodule

// 2-way Demultiplexer Module
module DMux (
    input wire in,
    input wire sel,
    output wire a, b
);
    assign a = (sel == 1'b0) ? in : 1'b0;
    assign b = (sel == 1'b1) ? in : 1'b0;
endmodule

// 8-way Demultiplexer Module
module DMux8Way (
    input wire in,
    input wire [2:0] sel,
    output wire a, b, c, d, e, f, g, h
);
    wire aeCase, bfCase, cgCase, dhCase;

    // First level: 4-way demultiplexer
    DMux4Way demux4 (
        .in(in),
        .sel(sel[1:0]),
        .a(aeCase),
        .b(bfCase),
        .c(cgCase),
        .d(dhCase)
    );

    // Second level: Distributing outputs
    DMux demux_a (
        .in(aeCase),
        .sel(sel[2]),
        .a(a),
        .b(e)
    );

    DMux demux_b (
        .in(bfCase),
        .sel(sel[2]),
        .a(b),
        .b(f)
    );

    DMux demux_c (
        .in(cgCase),
        .sel(sel[2]),
        .a(c),
        .b(g)
    );

    DMux demux_d (
        .in(dhCase),
        .sel(sel[2]),
        .a(d),
        .b(h)
    );
endmodule

Project-01/DeMux8way/DeMux8way_tb.v
`timescale 1ns / 1ps

module DMux8Way_tb;

    // Inputs
    reg in;
    reg [2:0] sel;

    // Outputs
    wire a, b, c, d, e, f, g, h;

    // Instantiate the DMux8Way module
    DMux8Way uut (
        .in(in),
        .sel(sel),
        .a(a),
        .b(b),
        .c(c),
        .d(d),
        .e(e),
        .f(f),
        .g(g),
        .h(h)
    );

    integer output_file;

    initial begin
        $dumpfile("DeMux8way.vcd");
        $dumpvars(0, DMux8Way_tb);
        // Open the output file
        
        output_file = $fopen("DeMux8way.out", "w");
        // Print table header
        $fwrite(output_file, "| in  |  sel  |  a  |  b  |  c  |  d  |  e  |  f  |  g  |  h  |\n");

        // Test case 1: in = 0, sel = 000
        in = 0; sel = 3'b000; #10;
        $fwrite(output_file, "|  %b  |  %b  |  %b  |  %b  |  %b  |  %b  |  %b  |  %b  |  %b  |  %b  |\n", 
                 in, sel, a, b, c, d, e, f, g, h);

        // Test case 2: in = 0, sel = 001
        in = 0; sel = 3'b001; #10;
        $fwrite(output_file, "|  %b  |  %b  |  %b  |  %b  |  %b  |  %b  |  %b  |  %b  |  %b  |  %b  |\n", 
                 in, sel, a, b, c, d, e, f, g, h);

        // Test case 3: in = 0, sel = 010
        in = 0; sel = 3'b010; #10;
        $fwrite(output_file, "|  %b  |  %b  |  %b  |  %b  |  %b  |  %b  |  %b  |  %b  |  %b  |  %b  |\n", 
                 in, sel, a, b, c, d, e, f, g, h);

        // Test case 4: in = 0, sel = 011
        in = 0; sel = 3'b011; #10;
        $fwrite(output_file, "|  %b  |  %b  |  %b  |  %b  |  %b  |  %b  |  %b  |  %b  |  %b  |  %b  |\n", 
                 in, sel, a, b, c, d, e, f, g, h);

        // Test case 5: in = 0, sel = 100
        in = 0; sel = 3'b100; #10;
        $fwrite(output_file, "|  %b  |  %b  |  %b  |  %b  |  %b  |  %b  |  %b  |  %b  |  %b  |  %b  |\n", 
                 in, sel, a, b, c, d, e, f, g, h);

        // Test case 6: in = 0, sel = 101
        in = 0; sel = 3'b101; #10;
        $fwrite(output_file, "|  %b  |  %b  |  %b  |  %b  |  %b  |  %b  |  %b  |  %b  |  %b  |  %b  |\n", 
                 in, sel, a, b, c, d, e, f, g, h);

        // Test case 7: in = 0, sel = 110
        in = 0; sel = 3'b110; #10;
        $fwrite(output_file, "|  %b  |  %b  |  %b  |  %b  |  %b  |  %b  |  %b  |  %b  |  %b  |  %b  |\n", 
                 in, sel, a, b, c, d, e, f, g, h);

        // Test case 8: in = 0, sel = 111
        in = 0; sel = 3'b111; #10;
        $fwrite(output_file, "|  %b  |  %b  |  %b  |  %b  |  %b  |  %b  |  %b  |  %b  |  %b  |  %b  |\n", 
                 in, sel, a, b, c, d, e, f, g, h);

        // Test case 9: in = 1, sel = 000
        in = 1; sel = 3'b000; #10;
        $fwrite(output_file, "|  %b  |  %b  |  %b  |  %b  |  %b  |  %b  |  %b  |  %b  |  %b  |  %b  |\n", 
                 in, sel, a, b, c, d, e, f, g, h);

        // Test case 10: in = 1, sel = 001
        in = 1; sel = 3'b001; #10;
        $fwrite(output_file, "|  %b  |  %b  |  %b  |  %b  |  %b  |  %b  |  %b  |  %b  |  %b  |  %b  |\n", 
                 in, sel, a, b, c, d, e, f, g, h);

        // Test case 11: in = 1, sel = 010
        in = 1; sel = 3'b010; #10;
        $fwrite(output_file, "|  %b  |  %b  |  %b  |  %b  |  %b  |  %b  |  %b  |  %b  |  %b  |  %b  |\n", 
                 in, sel, a, b, c, d, e, f, g, h);

        // Test case 12: in = 1, sel = 011
        in = 1; sel = 3'b011; #10;
        $fwrite(output_file, "|  %b  |  %b  |  %b  |  %b  |  %b  |  %b  |  %b  |  %b  |  %b  |  %b  |\n", 
                 in, sel, a, b, c, d, e, f, g, h);

        // Test case 13: in = 1, sel = 100
        in = 1; sel = 3'b100; #10;
        $fwrite(output_file, "|  %b  |  %b  |  %b  |  %b  |  %b  |  %b  |  %b  |  %b  |  %b  |  %b  |\n", 
                 in, sel, a, b, c, d, e, f, g, h);

        // Test case 14: in = 1, sel = 101
        in = 1; sel = 3'b101; #10;
        $fwrite(output_file, "|  %b  |  %b  |  %b  |  %b  |  %b  |  %b  |  %b  |  %b  |  %b  |  %b  |\n", 
                 in, sel, a, b, c, d, e, f, g, h);

        // Test case 15: in = 1, sel = 110
        in = 1; sel = 3'b110; #10;
        $fwrite(output_file, "|  %b  |  %b  |  %b  |  %b  |  %b  |  %b  |  %b  |  %b  |  %b  |  %b  |\n", 
                 in, sel, a, b, c, d, e, f, g, h);

        // Test case 16: in = 1, sel = 111
        in = 1; sel = 3'b111; #10;
        $fwrite(output_file, "|  %b  |  %b  |  %b  |  %b  |  %b  |  %b  |  %b  |  %b  |  %b  |  %b  |\n", 
                 in, sel, a, b, c, d, e, f, g, h);

        // End simulation after all tests
        $finish;
    end
endmodule

Project-01/DeMux8way/DeMux8way.vcd
$date
	Wed Aug 07 20:59:54 2024
$end
$version
	Icarus Verilog
$end
$timescale
	1ps
$end
$scope module DMux8Way_tb $end
$var wire 1 ! h $end
$var wire 1 " g $end
$var wire 1 # f $end
$var wire 1 $ e $end
$var wire 1 % d $end
$var wire 1 & c $end
$var wire 1 ' b $end
$var wire 1 ( a $end
$var reg 1 ) in $end
$var reg 3 * sel [2:0] $end
$var integer 32 + output_file [31:0] $end
$scope module uut $end
$var wire 1 ) in $end
$var wire 3 , sel [2:0] $end
$var wire 1 ! h $end
$var wire 1 " g $end
$var wire 1 # f $end
$var wire 1 $ e $end
$var wire 1 - dhCase $end
$var wire 1 % d $end
$var wire 1 . cgCase $end
$var wire 1 & c $end
$var wire 1 / bfCase $end
$var wire 1 ' b $end
$var wire 1 0 aeCase $end
$var wire 1 ( a $end
$scope module demux4 $end
$var wire 1 ) in $end
$var wire 2 1 sel [1:0] $end
$var wire 1 - d $end
$var wire 1 . c $end
$var wire 1 / b $end
$var wire 1 0 a $end
$upscope $end
$scope module demux_a $end
$var wire 1 0 in $end
$var wire 1 2 sel $end
$var wire 1 $ b $end
$var wire 1 ( a $end
$upscope $end
$scope module demux_b $end
$var wire 1 / in $end
$var wire 1 3 sel $end
$var wire 1 # b $end
$var wire 1 ' a $end
$upscope $end
$scope module demux_c $end
$var wire 1 . in $end
$var wire 1 4 sel $end
$var wire 1 " b $end
$var wire 1 & a $end
$upscope $end
$scope module demux_d $end
$var wire 1 - in $end
$var wire 1 5 sel $end
$var wire 1 ! b $end
$var wire 1 % a $end
$upscope $end
$upscope $end
$upscope $end
$enddefinitions $end
$comment Show the parameter values. $end
$dumpall
$end
#0
$dumpvars
05
04
03
02
b0 1
00
0/
0.
0-
b0 ,
b10000000000000000000000000000011 +
b0 *
0)
0(
0'
0&
0%
0$
0#
0"
0!
$end
#10000
b1 1
b1 *
b1 ,
#20000
b10 1
b10 *
b10 ,
#30000
b11 1
b11 *
b11 ,
#40000
b0 1
12
13
14
15
b100 *
b100 ,
#50000
b1 1
b101 *
b101 ,
#60000
b10 1
b110 *
b110 ,
#70000
b11 1
b111 *
b111 ,
#80000
1(
10
0!
b0 1
02
03
04
05
0-
b0 *
b0 ,
1)
#90000
0(
1'
00
1/
b1 1
b1 *
b1 ,
#100000
0'
1&
0/
1.
b10 1
b10 *
b10 ,
#110000
0&
1%
0.
1-
b11 1
b11 *
b11 ,
#120000
1$
0%
10
0-
b0 1
12
13
14
15
b100 *
b100 ,
#130000
0$
1#
00
1/
b1 1
b101 *
b101 ,
#140000
0#
1"
0/
1.
b10 1
b110 *
b110 ,
#150000
0"
1!
0.
1-
b11 1
b111 *
b111 ,
