Project-03/PC/PC.v
// 16-bit Program Counter Module
module ProgramCounter (
    input wire [15:0] in,     // 16-bit input value for loading
    input wire load,          // Load control signal
    input wire inc,           // Increment control signal
    input wire reset,         // Reset control signal
    output reg [15:0] out     // 16-bit output value (current PC)
);

    // Always block triggered on the rising edge of the clock
    // or when any of the control signals change
    always @(*) begin
        // Check the reset signal first
        if (reset) begin
            out = 16'b0; // Set output to 0 if reset is high
        end else if (load) begin
            out = in; // Load the input value if load is high
        end else if (inc) begin
            out = out + 1; // Increment the current value if inc is high
        end else begin
            out = out; // Hold the current value if no control signals are active
        end
    end

endmodule

Project-03/PC/PC_tb.v
`timescale 1ns / 1ps

// Testbench for the Program Counter
module tb_ProgramCounter;
    reg [15:0] in;
    reg reset;
    reg load;
    reg inc;
    wire [15:0] out;

    ProgramCounter pc (
        .in(in),
        .reset(reset),
        .load(load),
        .inc(inc),
        .out(out)
    );

    // File descriptor for output file
    integer output_file;

    initial begin
        // Open output file for writing
        output_file = $fopen("PC.out", "w"); // Open the output file
        $dumpfile("PC.vcd"); // Create a VCD file for waveform analysis
        $dumpvars(0, tb_ProgramCounter); // Dump all variables in the testbench

        // Print header to the output file
        $fwrite(output_file, "| time |   in   | reset | load | inc |   out   |\n");

        // Test Case 1: Initial state
        #0;
        $fwrite(output_file, "| %2d.%1d | %6d |   %1b   |   %1b  |  %1b  |  %6d |\n", $time / 10, $time % 10, in, reset, load, inc, out);

        // Test Case 2: Increment without load/reset
        #1;
        in = 16'b0;       reset = 1'b0;  load = 1'b0;  inc = 1'b1; // Increment
        $fwrite(output_file, "| %2d.%1d | %6d |   %1b   |   %1b  |  %1b  |  %6d |\n", $time / 10, $time % 10, in, reset, load, inc, out);

        // Test Case 3: Increment again
        #1;
        $fwrite(output_file, "| %2d.%1d | %6d |   %1b   |   %1b  |  %1b  |  %6d |\n", $time / 10, $time % 10, in, reset, load, inc, out);

        // Test Case 4: Load a value
        #1;
        in = -32123;      reset = 1'b0;  load = 1'b1;  inc = 1'b0; // Load value
        $fwrite(output_file, "| %2d.%1d | %6d |   %1b   |   %1b  |  %1b  |  %6d |\n", $time / 10, $time % 10, in, reset, load, inc, out);

        // Test Case 5: Increment after load
        #1;
        reset = 1'b0;  load = 1'b0;  inc = 1'b1; // Increment
        $fwrite(output_file, "| %2d.%1d | %6d |   %1b   |   %1b  |  %1b  |  %6d |\n", $time / 10, $time % 10, in, reset, load, inc, out);

        // Test Case 6: Load another value
        #1;
        load = 1'b1;  inc = 1'b0; // Load value
        $fwrite(output_file, "| %2d.%1d | %6d |   %1b   |   %1b  |  %1b  |  %6d |\n", $time / 10, $time % 10, in, reset, load, inc, out);

        // Test Case 7: Reset the counter
        #1;
        reset = 1'b1;  load = 1'b0;  inc = 1'b0; // Reset
        $fwrite(output_file, "| %2d.%1d | %6d |   %1b   |   %1b  |  %1b  |  %6d |\n", $time / 10, $time % 10, in, reset, load, inc, out);

        // Test Case 8: Load a new value
        #1;
        in = 12345;       reset = 1'b0;  load = 1'b1;  inc = 1'b0; // Load new value
        $fwrite(output_file, "| %2d.%1d | %6d |   %1b   |   %1b  |  %1b  |  %6d |\n", $time / 10, $time % 10, in, reset, load, inc, out);

        // Test Case 9: Increment the loaded value
        #1;
        load = 1'b0;  inc = 1'b1; // Increment
        $fwrite(output_file, "| %2d.%1d | %6d |   %1b   |   %1b  |  %1b  |  %6d |\n", $time / 10, $time % 10, in, reset, load, inc, out);

        // Test Case 10: Reset again
        #1;
        reset = 1'b1;  load = 1'b0;  inc = 1'b0; // Reset
        $fwrite(output_file, "| %2d.%1d | %6d |   %1b   |   %1b  |  %1b  |  %6d |\n", $time / 10, $time % 10, in, reset, load, inc, out);

        // Test Case 11: Load a value after reset
        #1;
        in = 22222;       reset = 1'b0;  load = 1'b1;  inc = 1'b0; // Load new value
        $fwrite(output_file, "| %2d.%1d | %6d |   %1b   |   %1b  |  %1b  |  %6d |\n", $time / 10, $time % 10, in, reset, load, inc, out);

        // Test Case 12: Increment the new value
        #1;
        load = 1'b0;  inc = 1'b1; // Increment
        $fwrite(output_file, "| %2d.%1d | %6d |   %1b   |   %1b  |  %1b  |  %6d |\n", $time / 10, $time % 10, in, reset, load, inc, out);

        // Close the output file
        $fclose(output_file); // Close the output file
        #10 $finish; // End the simulation
    end

endmodule

Project-03/PC/PC.vcd
$date
	Fri Aug 16 21:06:04 2024
$end
$version
	Icarus Verilog
$end
$timescale
	1ps
$end
$scope module tb_ProgramCounter $end
$var wire 16 ! out [15:0] $end
$var reg 16 " in [15:0] $end
$var reg 1 # inc $end
$var reg 1 $ load $end
$var reg 1 % reset $end
$var integer 32 & output_file [31:0] $end
$scope module pc $end
$var wire 16 ' in [15:0] $end
$var wire 1 # inc $end
$var wire 1 $ load $end
$var wire 1 % reset $end
$var reg 16 ( out [15:0] $end
$upscope $end
$upscope $end
$enddefinitions $end
$comment Show the parameter values. $end
$dumpall
$end
#0
$dumpvars
bx (
bx '
b10000000000000000000000000000011 &
x%
x$
x#
bx "
bx !
$end
#1000
1#
0$
0%
b0 "
b0 '
#3000
b1000001010000101 !
b1000001010000101 (
0#
1$
b1000001010000101 "
b1000001010000101 '
#4000
b1000001010000110 !
b1000001010000110 (
1#
0$
#5000
b1000001010000101 !
b1000001010000101 (
0#
1$
#6000
b0 !
b0 (
0$
1%
#7000
b11000000111001 !
b11000000111001 (
1$
0%
b11000000111001 "
b11000000111001 '
#8000
b11000000111010 !
b11000000111010 (
1#
0$
#9000
b0 !
b0 (
0#
1%
#10000
b101011011001110 !
b101011011001110 (
1$
0%
b101011011001110 "
b101011011001110 '
#11000
b101011011001111 !
b101011011001111 (
1#
0$
