Project-03/Ram64/RAM64.v
module RAM64(
    input wire [5:0] address,   // 3-bit address to select one of 8 registers
    input wire [15:0] in,       // 16-bit input data to be written
    input wire load,            // Load signal
    output reg [15:0] out       // 16-bit output data
);

    // Declare an array of 8 registers, each 16 bits wide
    reg [15:0] memory [0:63];

    // Always block to handle read and write operations
    always @(posedge load or negedge load) begin
        if (load) begin
            // Write data to the specified address
            memory[address] <= in;
        end
    end

    // Always block to handle reading from memory
    always @(*) begin
        // Output the value stored at the specified address
        out = memory[address];
    end

endmodule

Project-03/Ram64/RAM64_tb.v
`timescale 1ns / 1ps

module tb_RAM64;

    // Parameters
    parameter ADDRESS_WIDTH = 6; // 3 bits for 8 addresses
    parameter DATA_WIDTH = 16;    // 16 bits for data

    // Inputs
    reg [ADDRESS_WIDTH-1:0] address; // Address input
    reg [DATA_WIDTH-1:0] in;          // Data input
    reg load;                          // Load signal

    // Outputs
    wire [DATA_WIDTH-1:0] out;        // Output data

    // Instantiate the RAM8 module
    RAM64 uut (
        .address(address),
        .in(in),
        .load(load),
        .out(out)
    );

    // File handling
    integer output_file;
    integer i;

    // Initial block
    initial begin
        // Open the output file
        output_file = $fopen("RAM64.out", "w");
        

        // Dump waveform data to VCD file
        $dumpfile("RAM64.vcd");
        $dumpvars(0, tb_RAM64);

        for (i = 0; i < 64; i = i + 1) begin
            address = i;
            in = 16'h5A5A + i;
            load = 1;
            #10;
            $fwrite(output_file, "Address: %b, Written Data: %h\n", address, in);

            #10;

            load = 0;
            #10;
            $fwrite(output_file, "Address: %b, Written Data: %h\n", address, in);
        end

        // Read from all addresses
        for (i = 0; i < 64; i = i + 1) begin
            address = i;
            #10;
            $fwrite(output_file, "Address: %b, Read Data: %h\n", address, out);
        end

        // Close the output file
        $fclose(output_file);

        $finish;

        
    end

endmodule

Project-03/Ram64/RAM64.vcd
$date
	Mon Aug 19 22:22:38 2024
$end
$version
	Icarus Verilog
$end
$timescale
	1ps
$end
$scope module tb_RAM64 $end
$var wire 16 ! out [15:0] $end
$var parameter 32 " ADDRESS_WIDTH $end
$var parameter 32 # DATA_WIDTH $end
$var reg 6 $ address [5:0] $end
$var reg 16 % in [15:0] $end
$var reg 1 & load $end
$var integer 32 ' i [31:0] $end
$var integer 32 ( output_file [31:0] $end
$scope module uut $end
$var wire 6 ) address [5:0] $end
$var wire 16 * in [15:0] $end
$var wire 1 & load $end
$var reg 16 + out [15:0] $end
$upscope $end
$upscope $end
$enddefinitions $end
$comment Show the parameter values. $end
$dumpall
b10000 #
b110 "
$end
#0
$dumpvars
b101101001011010 +
b101101001011010 *
b0 )
b10000000000000000000000000000011 (
b0 '
1&
b101101001011010 %
b0 $
b101101001011010 !
$end
#20000
0&
#30000
b101101001011011 !
b101101001011011 +
1&
b101101001011011 %
b101101001011011 *
b1 $
b1 )
b1 '
#50000
0&
#60000
b101101001011100 !
b101101001011100 +
1&
b101101001011100 %
b101101001011100 *
b10 $
b10 )
b10 '
#80000
0&
#90000
b101101001011101 !
b101101001011101 +
1&
b101101001011101 %
b101101001011101 *
b11 $
b11 )
b11 '
#110000
0&
#120000
b101101001011110 !
b101101001011110 +
1&
b101101001011110 %
b101101001011110 *
b100 $
b100 )
b100 '
#140000
0&
#150000
b101101001011111 !
b101101001011111 +
1&
b101101001011111 %
b101101001011111 *
b101 $
b101 )
b101 '
#170000
0&
#180000
b101101001100000 !
b101101001100000 +
1&
b101101001100000 %
b101101001100000 *
b110 $
b110 )
b110 '
#200000
0&
#210000
b101101001100001 !
b101101001100001 +
1&
b101101001100001 %
b101101001100001 *
b111 $
b111 )
b111 '
#230000
0&
#240000
b101101001100010 !
b101101001100010 +
1&
b101101001100010 %
b101101001100010 *
b1000 $
b1000 )
b1000 '
#260000
0&
#270000
b101101001100011 !
b101101001100011 +
1&
b101101001100011 %
b101101001100011 *
b1001 $
b1001 )
b1001 '
#290000
0&
#300000
b101101001100100 !
b101101001100100 +
1&
b101101001100100 %
b101101001100100 *
b1010 $
b1010 )
b1010 '
#320000
0&
#330000
b101101001100101 !
b101101001100101 +
1&
b101101001100101 %
b101101001100101 *
b1011 $
b1011 )
b1011 '
#350000
0&
#360000
b101101001100110 !
b101101001100110 +
1&
b101101001100110 %
b101101001100110 *
b1100 $
b1100 )
b1100 '
#380000
0&
#390000
b101101001100111 !
b101101001100111 +
1&
b101101001100111 %
b101101001100111 *
b1101 $
b1101 )
b1101 '
#410000
0&
#420000
b101101001101000 !
b101101001101000 +
1&
b101101001101000 %
b101101001101000 *
b1110 $
b1110 )
b1110 '
#440000
0&
#450000
b101101001101001 !
b101101001101001 +
1&
b101101001101001 %
b101101001101001 *
b1111 $
b1111 )
b1111 '
#470000
0&
#480000
b101101001101010 !
b101101001101010 +
1&
b101101001101010 %
b101101001101010 *
b10000 $
b10000 )
b10000 '
#500000
0&
#510000
b101101001101011 !
b101101001101011 +
1&
b101101001101011 %
b101101001101011 *
b10001 $
b10001 )
b10001 '
#530000
0&
#540000
b101101001101100 !
b101101001101100 +
1&
b101101001101100 %
b101101001101100 *
b10010 $
b10010 )
b10010 '
#560000
0&
#570000
b101101001101101 !
b101101001101101 +
1&
b101101001101101 %
b101101001101101 *
b10011 $
b10011 )
b10011 '
#590000
0&
#600000
b101101001101110 !
b101101001101110 +
1&
b101101001101110 %
b101101001101110 *
b10100 $
b10100 )
b10100 '
#620000
0&
#630000
b101101001101111 !
b101101001101111 +
1&
b101101001101111 %
b101101001101111 *
b10101 $
b10101 )
b10101 '
#650000
0&
#660000
b101101001110000 !
b101101001110000 +
1&
b101101001110000 %
b101101001110000 *
b10110 $
b10110 )
b10110 '
#680000
0&
#690000
b101101001110001 !
b101101001110001 +
1&
b101101001110001 %
b101101001110001 *
b10111 $
b10111 )
b10111 '
#710000
0&
#720000
b101101001110010 !
b101101001110010 +
1&
b101101001110010 %
b101101001110010 *
b11000 $
b11000 )
b11000 '
#740000
0&
#750000
b101101001110011 !
b101101001110011 +
1&
b101101001110011 %
b101101001110011 *
b11001 $
b11001 )
b11001 '
#770000
0&
#780000
b101101001110100 !
b101101001110100 +
1&
b101101001110100 %
b101101001110100 *
b11010 $
b11010 )
b11010 '
#800000
0&
#810000
b101101001110101 !
b101101001110101 +
1&
b101101001110101 %
b101101001110101 *
b11011 $
b11011 )
b11011 '
#830000
0&
#840000
b101101001110110 !
b101101001110110 +
1&
b101101001110110 %
b101101001110110 *
b11100 $
b11100 )
b11100 '
#860000
0&
#870000
b101101001110111 !
b101101001110111 +
1&
b101101001110111 %
b101101001110111 *
b11101 $
b11101 )
b11101 '
#890000
0&
#900000
b101101001111000 !
b101101001111000 +
1&
b101101001111000 %
b101101001111000 *
b11110 $
b11110 )
b11110 '
#920000
0&
#930000
b101101001111001 !
b101101001111001 +
1&
b101101001111001 %
b101101001111001 *
b11111 $
b11111 )
b11111 '
#950000
0&
#960000
b101101001111010 !
b101101001111010 +
1&
b101101001111010 %
b101101001111010 *
b100000 $
b100000 )
b100000 '
#980000
0&
#990000
b101101001111011 !
b101101001111011 +
1&
b101101001111011 %
b101101001111011 *
b100001 $
b100001 )
b100001 '
#1010000
0&
#1020000
b101101001111100 !
b101101001111100 +
1&
b101101001111100 %
b101101001111100 *
b100010 $
b100010 )
b100010 '
#1040000
0&
#1050000
b101101001111101 !
b101101001111101 +
1&
b101101001111101 %
b101101001111101 *
b100011 $
b100011 )
b100011 '
#1070000
0&
#1080000
b101101001111110 !
b101101001111110 +
1&
b101101001111110 %
b101101001111110 *
b100100 $
b100100 )
b100100 '
#1100000
0&
#1110000
b101101001111111 !
b101101001111111 +
1&
b101101001111111 %
b101101001111111 *
b100101 $
b100101 )
b100101 '
#1130000
0&
#1140000
b101101010000000 !
b101101010000000 +
1&
b101101010000000 %
b101101010000000 *
b100110 $
b100110 )
b100110 '
#1160000
0&
#1170000
b101101010000001 !
b101101010000001 +
1&
b101101010000001 %
b101101010000001 *
b100111 $
b100111 )
b100111 '
#1190000
0&
#1200000
b101101010000010 !
b101101010000010 +
1&
b101101010000010 %
b101101010000010 *
b101000 $
b101000 )
b101000 '
#1220000
0&
#1230000
b101101010000011 !
b101101010000011 +
1&
b101101010000011 %
b101101010000011 *
b101001 $
b101001 )
b101001 '
#1250000
0&
#1260000
b101101010000100 !
b101101010000100 +
1&
b101101010000100 %
b101101010000100 *
b101010 $
b101010 )
b101010 '
#1280000
0&
#1290000
b101101010000101 !
b101101010000101 +
1&
b101101010000101 %
b101101010000101 *
b101011 $
b101011 )
b101011 '
#1310000
0&
#1320000
b101101010000110 !
b101101010000110 +
1&
b101101010000110 %
b101101010000110 *
b101100 $
b101100 )
b101100 '
#1340000
0&
#1350000
b101101010000111 !
b101101010000111 +
1&
b101101010000111 %
b101101010000111 *
b101101 $
b101101 )
b101101 '
#1370000
0&
#1380000
b101101010001000 !
b101101010001000 +
1&
b101101010001000 %
b101101010001000 *
b101110 $
b101110 )
b101110 '
#1400000
0&
#1410000
b101101010001001 !
b101101010001001 +
1&
b101101010001001 %
b101101010001001 *
b101111 $
b101111 )
b101111 '
#1430000
0&
#1440000
b101101010001010 !
b101101010001010 +
1&
b101101010001010 %
b101101010001010 *
b110000 $
b110000 )
b110000 '
#1460000
0&
#1470000
b101101010001011 !
b101101010001011 +
1&
b101101010001011 %
b101101010001011 *
b110001 $
b110001 )
b110001 '
#1490000
0&
#1500000
b101101010001100 !
b101101010001100 +
1&
b101101010001100 %
b101101010001100 *
b110010 $
b110010 )
b110010 '
#1520000
0&
#1530000
b101101010001101 !
b101101010001101 +
1&
b101101010001101 %
b101101010001101 *
b110011 $
b110011 )
b110011 '
#1550000
0&
#1560000
b101101010001110 !
b101101010001110 +
1&
b101101010001110 %
b101101010001110 *
b110100 $
b110100 )
b110100 '
#1580000
0&
#1590000
b101101010001111 !
b101101010001111 +
1&
b101101010001111 %
b101101010001111 *
b110101 $
b110101 )
b110101 '
#1610000
0&
#1620000
b101101010010000 !
b101101010010000 +
1&
b101101010010000 %
b101101010010000 *
b110110 $
b110110 )
b110110 '
#1640000
0&
#1650000
b101101010010001 !
b101101010010001 +
1&
b101101010010001 %
b101101010010001 *
b110111 $
b110111 )
b110111 '
#1670000
0&
#1680000
b101101010010010 !
b101101010010010 +
1&
b101101010010010 %
b101101010010010 *
b111000 $
b111000 )
b111000 '
#1700000
0&
#1710000
b101101010010011 !
b101101010010011 +
1&
b101101010010011 %
b101101010010011 *
b111001 $
b111001 )
b111001 '
#1730000
0&
#1740000
b101101010010100 !
b101101010010100 +
1&
b101101010010100 %
b101101010010100 *
b111010 $
b111010 )
b111010 '
#1760000
0&
#1770000
b101101010010101 !
b101101010010101 +
1&
b101101010010101 %
b101101010010101 *
b111011 $
b111011 )
b111011 '
#1790000
0&
#1800000
b101101010010110 !
b101101010010110 +
1&
b101101010010110 %
b101101010010110 *
b111100 $
b111100 )
b111100 '
#1820000
0&
#1830000
b101101010010111 !
b101101010010111 +
1&
b101101010010111 %
b101101010010111 *
b111101 $
b111101 )
b111101 '
#1850000
0&
#1860000
b101101010011000 !
b101101010011000 +
1&
b101101010011000 %
b101101010011000 *
b111110 $
b111110 )
b111110 '
#1880000
0&
#1890000
b101101010011001 !
b101101010011001 +
1&
b101101010011001 %
b101101010011001 *
b111111 $
b111111 )
b111111 '
#1910000
0&
#1920000
b101101001011010 !
b101101001011010 +
b0 $
b0 )
b0 '
#1930000
b101101001011011 !
b101101001011011 +
b1 $
b1 )
b1 '
#1940000
b101101001011100 !
b101101001011100 +
b10 $
b10 )
b10 '
#1950000
b101101001011101 !
b101101001011101 +
b11 $
b11 )
b11 '
#1960000
b101101001011110 !
b101101001011110 +
b100 $
b100 )
b100 '
#1970000
b101101001011111 !
b101101001011111 +
b101 $
b101 )
b101 '
#1980000
b101101001100000 !
b101101001100000 +
b110 $
b110 )
b110 '
#1990000
b101101001100001 !
b101101001100001 +
b111 $
b111 )
b111 '
#2000000
b101101001100010 !
b101101001100010 +
b1000 $
b1000 )
b1000 '
#2010000
b101101001100011 !
b101101001100011 +
b1001 $
b1001 )
b1001 '
#2020000
b101101001100100 !
b101101001100100 +
b1010 $
b1010 )
b1010 '
#2030000
b101101001100101 !
b101101001100101 +
b1011 $
b1011 )
b1011 '
#2040000
b101101001100110 !
b101101001100110 +
b1100 $
b1100 )
b1100 '
#2050000
b101101001100111 !
b101101001100111 +
b1101 $
b1101 )
b1101 '
#2060000
b101101001101000 !
b101101001101000 +
b1110 $
b1110 )
b1110 '
#2070000
b101101001101001 !
b101101001101001 +
b1111 $
b1111 )
b1111 '
#2080000
b101101001101010 !
b101101001101010 +
b10000 $
b10000 )
b10000 '
#2090000
b101101001101011 !
b101101001101011 +
b10001 $
b10001 )
b10001 '
#2100000
b101101001101100 !
b101101001101100 +
b10010 $
b10010 )
b10010 '
#2110000
b101101001101101 !
b101101001101101 +
b10011 $
b10011 )
b10011 '
#2120000
b101101001101110 !
b101101001101110 +
b10100 $
b10100 )
b10100 '
#2130000
b101101001101111 !
b101101001101111 +
b10101 $
b10101 )
b10101 '
#2140000
b101101001110000 !
b101101001110000 +
b10110 $
b10110 )
b10110 '
#2150000
b101101001110001 !
b101101001110001 +
b10111 $
b10111 )
b10111 '
#2160000
b101101001110010 !
b101101001110010 +
b11000 $
b11000 )
b11000 '
#2170000
b101101001110011 !
b101101001110011 +
b11001 $
b11001 )
b11001 '
#2180000
b101101001110100 !
b101101001110100 +
b11010 $
b11010 )
b11010 '
#2190000
b101101001110101 !
b101101001110101 +
b11011 $
b11011 )
b11011 '
#2200000
b101101001110110 !
b101101001110110 +
b11100 $
b11100 )
b11100 '
#2210000
b101101001110111 !
b101101001110111 +
b11101 $
b11101 )
b11101 '
#2220000
b101101001111000 !
b101101001111000 +
b11110 $
b11110 )
b11110 '
#2230000
b101101001111001 !
b101101001111001 +
b11111 $
b11111 )
b11111 '
#2240000
b101101001111010 !
b101101001111010 +
b100000 $
b100000 )
b100000 '
#2250000
b101101001111011 !
b101101001111011 +
b100001 $
b100001 )
b100001 '
#2260000
b101101001111100 !
b101101001111100 +
b100010 $
b100010 )
b100010 '
#2270000
b101101001111101 !
b101101001111101 +
b100011 $
b100011 )
b100011 '
#2280000
b101101001111110 !
b101101001111110 +
b100100 $
b100100 )
b100100 '
#2290000
b101101001111111 !
b101101001111111 +
b100101 $
b100101 )
b100101 '
#2300000
b101101010000000 !
b101101010000000 +
b100110 $
b100110 )
b100110 '
#2310000
b101101010000001 !
b101101010000001 +
b100111 $
b100111 )
b100111 '
#2320000
b101101010000010 !
b101101010000010 +
b101000 $
b101000 )
b101000 '
#2330000
b101101010000011 !
b101101010000011 +
b101001 $
b101001 )
b101001 '
#2340000
b101101010000100 !
b101101010000100 +
b101010 $
b101010 )
b101010 '
#2350000
b101101010000101 !
b101101010000101 +
b101011 $
b101011 )
b101011 '
#2360000
b101101010000110 !
b101101010000110 +
b101100 $
b101100 )
b101100 '
#2370000
b101101010000111 !
b101101010000111 +
b101101 $
b101101 )
b101101 '
#2380000
b101101010001000 !
b101101010001000 +
b101110 $
b101110 )
b101110 '
#2390000
b101101010001001 !
b101101010001001 +
b101111 $
b101111 )
b101111 '
#2400000
b101101010001010 !
b101101010001010 +
b110000 $
b110000 )
b110000 '
#2410000
b101101010001011 !
b101101010001011 +
b110001 $
b110001 )
b110001 '
#2420000
b101101010001100 !
b101101010001100 +
b110010 $
b110010 )
b110010 '
#2430000
b101101010001101 !
b101101010001101 +
b110011 $
b110011 )
b110011 '
#2440000
b101101010001110 !
b101101010001110 +
b110100 $
b110100 )
b110100 '
#2450000
b101101010001111 !
b101101010001111 +
b110101 $
b110101 )
b110101 '
#2460000
b101101010010000 !
b101101010010000 +
b110110 $
b110110 )
b110110 '
#2470000
b101101010010001 !
b101101010010001 +
b110111 $
b110111 )
b110111 '
#2480000
b101101010010010 !
b101101010010010 +
b111000 $
b111000 )
b111000 '
#2490000
b101101010010011 !
b101101010010011 +
b111001 $
b111001 )
b111001 '
#2500000
b101101010010100 !
b101101010010100 +
b111010 $
b111010 )
b111010 '
#2510000
b101101010010101 !
b101101010010101 +
b111011 $
b111011 )
b111011 '
#2520000
b101101010010110 !
b101101010010110 +
b111100 $
b111100 )
b111100 '
#2530000
b101101010010111 !
b101101010010111 +
b111101 $
b111101 )
b111101 '
#2540000
b101101010011000 !
b101101010011000 +
b111110 $
b111110 )
b111110 '
#2550000
b101101010011001 !
b101101010011001 +
b111111 $
b111111 )
b111111 '
#2560000
b1000000 '
