Project-01/Mux16/Mux16.v
module Mux16 (
    input [15:0] a,
    input [15:0] b,
    input wire sel,

    output [15:0] out
);

    assign out = (sel) ? b : a;
    
endmodule

Mux16/Mux16_tb.v
`timescale 1ns / 1ps

module tb_mux16;

    reg [15:0] a;       // First 16-bit input
    reg [15:0] b;       // Second 16-bit input
    reg sel;         // Select signal
    wire [15:0] out;    // Output

    // Instantiate the MUX
    Mux16 uut (
        .a(a),
        .b(b),
        .sel(sel),
        .out(out)
    );

    // File for output
    integer output_file;

    initial begin
        $dumpfile("Mux16.vcd");
        $dumpvars(0, tb_mux16);
        // Open the output file
        output_file = $fopen("Mux16.out", "w");
        
        // Write the header
        $fwrite(output_file, "|        a         |        b         | sel |       out        |\n");

        // Test cases
        a = 16'b0000000000000000; // Input a
        b = 16'b0000000000000000; // Input b

        // Test select = 0 (should output a)
        sel = 0;
        #10; // Wait for 10 time units
        $fwrite(output_file, "| %b | %b |  %b  | %b |\n", a, b, sel, out);

        // Test select = 1 (should output b)
        sel = 1;
        #10; // Wait for 10 time units
        $fwrite(output_file, "| %b | %b |  %b  | %b |\n", a, b, sel, out);

        // Change inputs
        b = 16'b0001001000110100; // New input b

        // Test select = 0 (should output a)
        sel = 0;
        #10; // Wait for 10 time units
        $fwrite(output_file, "| %b | %b |  %b  | %b |\n", a, b, sel, out);

        // Test select = 1 (should output b)
        sel = 1;
        #10; // Wait for 10 time units
        $fwrite(output_file, "| %b | %b |  %b  | %b |\n", a, b, sel, out);

        // Change inputs
        a = 16'b1001100001110110; // New input a
        b = 16'b0000000000000000; // New input b

        // Test select = 0 (should output a)
        sel = 0;
        #10; // Wait for 10 time units
        $fwrite(output_file, "| %b | %b |  %b  | %b |\n", a, b, sel, out);

        // Test select = 1 (should output b)
        sel = 1;
        #10; // Wait for 10 time units
        $fwrite(output_file, "| %b | %b |  %b  | %b |\n", a, b, sel, out);

        // Change inputs
        a = 16'b1010101010101010; // New input a
        b = 16'b0101010101010101; // New input b

        // Test select = 0 (should output a)
        sel = 0;
        #10; // Wait for 10 time units
        $fwrite(output_file, "| %b | %b |  %b  | %b |\n", a, b, sel, out);

        // Test select = 1 (should output b)
        sel = 1;
        #10; // Wait for 10 time units
        $fwrite(output_file, "| %b | %b |  %b  | %b |\n", a, b, sel, out);

        // Close the file
        $fclose(output_file);
        
        // End simulation
        $finish;
    end
endmodule

Project-01/Mux16/Mux16.vcd
$date
	Tue Aug 06 19:56:52 2024
$end
$version
	Icarus Verilog
$end
$timescale
	1ps
$end
$scope module tb_mux16 $end
$var wire 16 ! out [15:0] $end
$var reg 16 " a [15:0] $end
$var reg 16 # b [15:0] $end
$var reg 1 $ sel $end
$var integer 32 % output_file [31:0] $end
$scope module uut $end
$var wire 16 & a [15:0] $end
$var wire 16 ' b [15:0] $end
$var wire 1 $ sel $end
$var wire 16 ( out [15:0] $end
$upscope $end
$upscope $end
$enddefinitions $end
$comment Show the parameter values. $end
$dumpall
$end
#0
$dumpvars
b0 (
b0 '
b0 &
b10000000000000000000000000000011 %
0$
b0 #
b0 "
b0 !
$end
#10000
1$
#20000
0$
b1001000110100 #
b1001000110100 '
#30000
b1001000110100 !
b1001000110100 (
1$
#40000
b1001100001110110 !
b1001100001110110 (
0$
b0 #
b0 '
b1001100001110110 "
b1001100001110110 &
#50000
b0 !
b0 (
1$
#60000
b1010101010101010 !
b1010101010101010 (
0$
b101010101010101 #
b101010101010101 '
b1010101010101010 "
b1010101010101010 &
#70000
b101010101010101 !
b101010101010101 (
1$
